Workbook
Name Macrobond_Object1: Downloads_dagcijfers!$A$3:$B$9233
Name Macrobond_Object1: Downloads_maandcijfers!$A$3:$CJ$513
Name Macrobond_Object1: downloads_saffier!$A$4:$E$163
Name Macrobond_Object1: Saffier_futures_cijfers!$A$4:$Y$111
Name Macrobond_Object2: Downloads_kwartaalcijfers!$A$3:$AE$317

Sheet Downloads_maandcijfers
B4: United States, Crude Oil, Brent Europe Spot Price FOB, USD | C4: Euro Area, FX Spot Rates, Macrobond, EUR per USD | D4: United States, Economic Policy Uncertainty, Economic Policy Uncertainty Indices, Headline Index, Index | E4: Europe, Economic Policy Uncertainty, Economic Policy Uncertainty Indices, News Based Index, Index | F4: United States, Volatility Indices, CBOE, S&P 500 Volatility Index (VIX), Close | G4: Germany, Government Benchmarks, Government Bond, 10 Year, Yield | H4: United States, Government Benchmarks, Federal Reserve, 10 Year, Yield | I4: Italy, Government Benchmarks, Macrobond, 10 Year, Yield | J4: Netherlands, Government Benchmarks, Macrobond, 10 Year, Yield | K4: Euro Area 20, Eurostat, HICP, All-Items HICP, 2015=100, Index | L4: Euro Area 20, Eurostat, HICP, Food Including Alcohol & Tobacco, 2015=100, Index | M4: Euro Area 20, Eurostat, HICP, Energy, 2015=100, Index | N4: Euro Area 20, Eurostat, HICP, Overall Index Excluding Energy, Food, Alcohol & Tobacco, 2015=100, Index | O4: Euro Area, Foreign Trade, CPB World Trade Monitor, Import, Volume, SA, Index | P4: Euro Area, Foreign Trade, CPB World Trade Monitor, Export, Volume, SA, Index | Q4: Euro Area, Business Surveys, S&P Global, Composite, Composite PMI Output Index, SA, Index | R4: Euro Area, Business Surveys, S&P Global, Manufacturing, Manufacturing PMI, SA, Index | S4: Euro Area, Business Surveys, S&P Global, Services, Services PMI Business Activity Index, SA, Index | T4: Euro Area, Business Surveys, S&P Global, Construction, Construction PMI Total Activity Index, SA, Index | U4: Euro Area, Consumer Surveys, DG ECFIN, Consumer Confidence, Balance, SA | V4: Euro Area, Business Surveys, DG ECFIN, Business Climate, Indicator (BCI), SA | W4: Euro Area, Business Surveys, DG ECFIN, Services Confidence Indicator, Total Service Sector, Balance, SA | X4: Euro Area, Business Surveys, DG ECFIN, Industrial Confidence Indicator, Total Sector, Monthly, Balance, SA | Y4: Euro Area, Business Surveys, DG ECFIN, Construction Confidence Indicator, Balance, SA | Z4: World, Baltic Exchange, Shipping, Dry Index (BDI), USD | AA4: World, Harper Petersen, Shipping, Harpex, Index, USD | AB4: World, Drewry Shipping Consultants Ltd, Shipping, Composite, Index | AC4: Netherlands, Equity Indices, Euronext Amsterdam, AEX-Index, Price Return, Close, EUR | AD4: United States, Equity Indices, S&P, 500, Index, Price Return, Close, USD | AE4: World, Equity Indices, MSCI, Mid & Large Cap, Index, Price Return, USD | AF4: United States, Policy Rates, Federal Reserve, Target Rates, Federal Funds Target Rate | AG4: Euro Area, Policy Rates, ECB, Deposit Facility, Effective Rate | AH4: United Kingdom, Policy Rates, Bank of England, Bank Rate | AI4: Japan, Policy Rates, Bank of Japan, Interest on Excess Reserves (Policy-Rate Balances in Current Accounts Held by Financial Institutions at the Bank) | AJ4: China, Liquidity Facilities, People's Bank of China, Medium-term Lending Facility, Medium-term Lending Facility, 1-Year Rate | AK4: United States, Consumer Price Index, Harmonized CPI (HICP), All Items, Index | AL4: United States, Consumer Price Index, All Urban Consumers, U.S. City Average, All Items Less Food & Energy, SA, Index | AM4: Germany, Business Surveys, S&P Global, Composite, Composite PMI Output Index, SA, Index | AN4: Germany, Business Surveys, S&P Global, Manufacturing, Manufacturing PMI, SA, Index | AO4: France, Business Surveys, S&P Global, Composite, Composite PMI Output Index, SA, Index | AP4: France, Business Surveys, S&P Global, Manufacturing, Manufacturing PMI, SA, Index | AQ4: United States, Business Surveys, S&P Global, Composite, Composite PMI Output Index, SA, Index | AR4: United States, Business Surveys, S&P Global, Manufacturing, Manufacturing PMI, SA, Index | AS4: United Kingdom, Business Surveys, S&P Global, Composite, Composite PMI Output Index, SA, Index | AT4: United Kingdom, Business Surveys, S&P Global, Manufacturing, Manufacturing PMI, SA, Index | AU4: China, Business Surveys, S&P Global, Composite, Caixin, Composite PMI Output Index, SA, Index | AV4: China, Business Surveys, S&P Global, Manufacturing, Caixin, Manufacturing PMI, SA, Index | AW4: India, Business Surveys, S&P Global, Composite, HSBC, Composite PMI Output Index, SA, Index | AX4: India, Business Surveys, S&P Global, Manufacturing, HSBC, Manufacturing PMI, SA, Index | AY4: World, Business Surveys, S&P Global, Composite, JPMorgan, Composite PMI Output Index, SA, Index | AZ4: World, Business Surveys, S&P Global, Manufacturing, JPMorgan, Manufacturing PMI, SA, Index | BA4: Japan, Business Surveys, S&P Global, Composite, au Jibun Bank, Composite PMI Output Index, SA, Index | BB4: Japan, Business Surveys, S&P Global, Manufacturing, au Jibun Bank, Manufacturing PMI, SA, Index | BC4: World, Foreign Trade, Global Supply Chain Pressure Index, Total, Index | BD4: World, Foreign Trade, CPB World Trade Monitor, Total, Volume, SA, Index | BE4: World, Foreign Trade, RWI/ISL Container Throughput Index, Total, SA, Index | BF4: World, Foreign Trade, RWI/ISL Container Throughput Index, North Range, SA, Index | BG4: United States, Corporate Benchmarks, Moody's, Long-Term, Baa Rated, Yield | BH4: United States, Economic Policy Uncertainty, Trade Policy Uncertainty (TPU), Trade Policy Uncertainty Index (TPU), Index | BI4: Euro Area 20, ECB, Hourly Compensation, Total - All Activities, Reference Sector: Total Economy, Counterpart Area: Domestic (Home or Reference Area), Calendar Adjusted, Current Prices, SA, Index | BJ4: Euro Area 20, Eurostat, Labor Cost Index - Nominal Value, Labor Cost, Wages & Salaries (Total), Industry, Construction & Services (Except Activities of Households as Employers & Extra-Territorial Organisations & Bodies) (B-S), 2020=100, Calendar Adjusted, SA, Index | BK4: Natural Gas, Future, ICE Dutch TTF Daily Gas, 1st Position, Close, EUR | BL4: Netherlands, Business Surveys, S&P Global, Manufacturing, Manufacturing PMI, SA, Index | BM4: Euro Area, Interbank Rates, EURIBOR, 3 Month, Fixing | BN4: Netherlands, Government Benchmarks, Macrobond, 10 Year, Yield | BO4: United States, OECD MEI, Leading Indicators OECD, Leading Indicators, Composite Leading Indicators, Amplitude Adjusted, OECD, SA, Index | BP4: China, OECD MEI, Leading Indicators OECD, Leading Indicators, Composite Leading Indicators, Amplitude Adjusted, OECD, SA, Index | BQ4: Four Big European, OECD MEI, Leading Indicators OECD, Leading Indicators, Composite Leading Indicators, Amplitude Adjusted, OECD, SA, Index | BR4: Euro Area, Commodity Indices, HWWI, Weighting Period 2017-2019, HWWI Index, Average of Period, EUR | BS4: Euro Area, Commodity Indices, HWWI, Weighting Period 2017-2019, HWWI Index excluding Energy, Average of Period, EUR | BT4: Euro Area, Commodity Indices, HWWI, Weighting Period 2017-2019, Industrial Raw Materials Index, Average of Period, EUR | BU4: Euro Area, Commodity Indices, HWWI, Weighting Period 2017-2019, Energy Raw Materials Index, Average of Period, EUR | BV4: Euro Area, Commodity Indices, HWWI, Weighting Period 2017-2019, Food Index, Average of Period, EUR | BW4: World, Foreign Trade, Kiel Institute, Export, Real Trade Flows, SA, Change P/P | BX4: World, Foreign Trade, Kiel Institute, Import, Real Trade Flows, SA, Change P/P | BY4: Euro Area 20, Foreign Trade, Kiel Institute, Import, Real Trade Flows, Extra-Euro Area 20, SA, Change P/P | BZ4: Euro Area 20, Foreign Trade, Kiel Institute, Export, Real Trade Flows, Extra-Euro Area 20, SA, Change P/P | CA4: Euro Area 20, Foreign Trade, Kiel Institute, Import, Real Trade Flows, Intra-Euro Area 20, SA, Change P/P | CB4: Euro Area 20, Foreign Trade, Kiel Institute, Export, Real Trade Flows, Intra-Euro Area 20, SA, Change P/P | CC4: Netherlands, ECB Composite Cost of Borrowing, For Non-Financial Corporations | CD4: Netherlands, ECB Composite Cost of Borrowing, For Short-Term Loans | CE4: Netherlands, ECB Composite Cost of Borrowing, For Long-Term Loans | CF4: Netherlands, ECB Composite Cost of Borrowing, For Households For House Purchase | CG4: Netherlands, Business Surveys, DG ECFIN, Services Confidence Indicator, Total Service Sector, Balance, SA | CH4: Netherlands, Business Surveys, DG ECFIN, Industrial Confidence Indicator, Total Sector, Monthly, Balance, SA | CI4: Netherlands, Business Surveys, DG ECFIN, Construction Confidence Indicator, Balance, SA | CJ4: Netherlands, Business Surveys, DG ECFIN, Retail Trade Confidence Indicator, Balance, SA
A5: 30317 | C5: 1.0662 | G5: 7.71 | H5: 10.8 | AD5: 145.3 | AE5: 158.0337 | AF5: 8.5 | AH5: 11 | AL5: 97.6 | BG5: 14.11 | BH5: 44.216434 | BO5: 98.59094 | BQ5: 98.85226
A6: 30348 | C6: 1.0593 | G6: 7.71 | H6: 10.27 | AD6: 148.06 | AE6: 160.9138 | AF6: 8.5 | AH6: 11 | AL6: 98 | BG6: 14.11 | BH6: 47.943553 | BO6: 99.20538 | BQ6: 99.03355
A7: 30376 | C7: 1.0825 | G7: 7.42 | H7: 10.62 | AD7: 152.96 | AE7: 166.1387 | AF7: 8.625 | AH7: 10.5625 | AL7: 98.2 | BG7: 14.11 | BH7: 39.36063 | BO7: 99.83798 | BQ7: 99.21072
A8: 30407 | C8: 1.0857 | G8: 7.51 | H8: 10.27 | AD8: 164.42 | AE8: 177.5606 | AF8: 8.625 | AH8: 10.0625 | AL8: 98.6 | BG8: 14.11 | BH8: 33.669141 | BO8: 100.4557 | BQ8: 99.36791
A9: 30437 | C9: 1.1038 | G9: 7.69 | H9: 10.81 | AD9: 162.39 | AE9: 175.3825 | AF9: 8.75 | AH9: 10.0625 | AL9: 98.9 | BG9: 14.11 | BH9: 40.559676 | BO9: 101.0241 | BQ9: 99.51093
A10: 30468 | C10: 1.1214 | G10: 8.11 | H10: 10.96 | AD10: 168.11 | AE10: 180.4522 | AF10: 9 | AH10: 9.5625 | AL10: 99.2 | BG10: 14.11 | BH10: 30.909182 | BO10: 101.5105 | BQ10: 99.65131
A11: 30498 | C11: 1.1599 | G11: 8.24 | H11: 11.76 | AD11: 162.56 | AE11: 176.796 | AF11: 9.4375 | AH11: 9.5625 | AL11: 99.8 | BG11: 14.11 | BH11: 38.485725 | BO11: 101.8985 | BQ11: 99.78407
A12: 30529 | C12: 1.1868 | G12: 8.37 | H12: 11.98 | AD12: 164.4 | AE12: 177.3121 | AF12: 9.5 | AH12: 9.5625 | AL12: 100.1 | BG12: 14.11 | BH12: 27.837468 | BO12: 102.1883 | BQ12: 99.90173
A13: 30560 | C13: 1.1636 | G13: 8.48 | H13: 11.44 | AD13: 166.07 | AE13: 180.4669 | AF13: 9.375 | AH13: 9.5625 | AL13: 100.5 | BG13: 14.11 | BH13: 29.90736 | BO13: 102.4 | BQ13: 99.99452
A14: 30590 | C14: 1.1641 | G14: 8.26 | H14: 11.74 | AD14: 163.55 | AE14: 177.9077 | AF14: 9.375 | AH14: 9.0625 | AL14: 101 | BG14: 14.11 | BH14: 26.994876 | BO14: 102.5413 | BQ14: 100.0811
A15: 30621 | C15: 1.1928 | G15: 8.31 | H15: 11.63 | AD15: 166.4 | AE15: 182.0605 | AF15: 9.375 | AH15: 9.0625 | AL15: 101.5 | BG15: 14.11 | BH15: 30.371025 | BO15: 102.6177 | BQ15: 100.1606
A16: 30651 | C16: 1.2086 | G16: 8.41 | H16: 11.82 | AD16: 164.93 | AE16: 183.952 | AF16: 9.375 | AH16: 9.0625 | AL16: 101.8 | BG16: 14.11 | BH16: 24.386279 | BO16: 102.6312 | BQ16: 100.215
... A28: 31017 | C28: 1.4105 | G28: 7.04 | H28: 11.55 | AD28: 167.24 | AE28: 187.205 | AF28: 8.125 | AH28: 9.5 | AL28: 106.8 | BG28: 14.11 | BH28: 25.772489 | BO28: 100.3601 | BQ28: 99.74073
A29: 31048 | C29: 1.4226 | D29: 125.22474 | G29: 7.12 | H29: 11.17 | U29: -10.4 | V29: -0.18 | X29: -5.9 | Y29: -50.1 | AD29: 179.63 | AE29: 197.0574 | AF29: 8.25 | AH29: 13.875 | AL29: 107.1 | BG29: 14.11 | BH29: 26.59244 | BO29: 100.3054 | BQ29: 99.71529 | CH29: -3.2 | CI29: -23.1
A30: 31079 | C30: 1.4978 | D30: 99.020809 | G30: 7.59 | H30: 11.91 | U30: -10.8 | V30: -0.18 | X30: -8 | Y30: -51.1 | Z30: 984 | AD30: 181.19 | AE30: 196.9641 | AF30: 8.375 | AH30: 13.875 | AL30: 107.7 | BG30: 14.11 | BH30: 30.645161 | BO30: 100.2539 | BQ30: 99.67143 | CH30: 1.8 | CI30: -18.4
A31: 31107 | C31: 1.3753 | D31: 112.19051 | G31: 7.63 | H31: 11.65 | U31: -11.8 | V31: -0.27 | X31: -9.5 | Y31: -48.3 | Z31: 1016 | AD31: 180.66 | AE31: 203.3034 | AF31: 8.5 | AH31: 12.875 | AL31: 108.1 | BG31: 14.11 | BH31: 42.439081 | BO31: 100.2115 | BQ31: 99.62137 | CH31: 1.9 | CI31: -20.6
A32: 31138 | C32: 1.3807 | D32: 102.81132 | G32: 7.31 | H32: 11.41 | U32: -11 | V32: -0.24 | X32: -8.8 | Y32: -45.1 | Z32: 1063 | AD32: 179.83 | AE32: 202.2416 | AF32: 8.25 | AH32: 12.375 | AL32: 108.4 | BG32: 14.11 | BH32: 42.02379 | BO32: 100.1772 | BQ32: 99.57984 | CH32: -1.3 | CI32: -20.1
A33: 31168 | C33: 1.3764 | D33: 120.08272 | G33: 7.2 | H33: 10.28 | U33: -11.5 | V33: -0.11 | X33: -7.6 | Y33: -45.2 | Z33: 932 | AD33: 189.57 | AE33: 212.126 | AF33: 7.75 | AH33: 12.375 | AL33: 108.8 | BG33: 14.11 | BH33: 31.659582 | BO33: 100.1469 | BQ33: 99.54821 | CH33: -1.5 | CI33: -23.9
A34: 31199 | C34: 1.3606 | D34: 132.71319 | G34: 7.05 | H34: 10.25 | U34: -11.9 | V34: -0.14 | X34: -7.9 | Y34: -43.3 | Z34: 872 | AD34: 191.85 | AE34: 215.3965 | AF34: 7.75 | AH34: 12.375 | AL34: 109.1 | BG34: 14.11 | BH34: 34.803326 | BO34: 100.121 | BQ34: 99.52658 | CH34: -1 | CI34: -22.7
A35: 31229 | C35: 1.2477 | D35: 128.00182 | G35: 6.86 | H35: 10.57 | U35: -11.6 | V35: -0.1 | X35: -8.1 | Y35: -40.9 | Z35: 726 | AD35: 190.92 | AE35: 219.314 | AF35: 7.75 | AH35: 11.375 | AL35: 109.4 | BG35: 14.11 | BH35: 50.395429 | BO35: 100.0893 | BQ35: 99.52212 | CH35: 0 | CI35: -20.7
A36: 31260 | C36: 1.2494 | D36: 126.76611 | G36: 6.59 | H36: 10.28 | U36: -11.2 | V36: -0.1 | X36: -7.6 | Y36: -38.8 | Z36: 738 | AD36: 188.63 | AE36: 220.5866 | AF36: 7.8125 | AH36: 11.375 | AL36: 109.8 | BG36: 14.11 | BH36: 41.984177 | BO36: 100.061 | BQ36: 99.54453 | CH36: -2.7 | CI36: -19.8
A37: 31291 | C37: 1.2103 | D37: 126.76856 | G37: 6.4 | H37: 10.31 | U37: -10.9 | V37: -0.1 | X37: -6.3 | Y37: -35.7 | Z37: 894 | AD37: 182.08 | AE37: 221.7017 | AF37: 8 | AH37: 11.375 | AL37: 110 | BG37: 14.11 | BH37: 60.030251 | BO37: 100.0409 | BQ37: 99.59404 | CH37: -3.2 | CI37: -17.4
A38: 31321 | C38: 1.1824 | D38: 116.05771 | G38: 6.59 | H38: 10.01 | U38: -8.3 | V38: -0.01 | X38: -5.8 | Y38: -34.8 | Z38: 905 | AD38: 189.82 | AE38: 233.095 | AF38: 8 | AH38: 11.375 | AL38: 110.5 | BG38: 14.11 | BH38: 36.138472 | BO38: 100.0354 | BQ38: 99.66045 | CH38: -2.8 | CI38: -14.6
A39: 31352 | C39: 1.1401 | D39: 122.03688 | G39: 6.58 | H39: 9.59 | U39: -8 | V39: -0.11 | X39: -5.2 | Y39: -34.4 | Z39: 915 | AD39: 202.17 | AE39: 245.5733 | AF39: 8 | AH39: 11.375 | AL39: 111.1 | BG39: 14.11 | BH39: 39.581438 | BO39: 100.0505 | BQ39: 99.72504 | CH39: -2.5 | CI39: -15.2
A40: 31382 | C40: 1.1262 | D40: 133.24392 | G40: 6.45 | H40: 9 | U40: -8.2 | V40: -0.16 | X40: -6.6 | Y40: -35.3 | Z40: 898 | AD40: 211.28 | AE40: 256.5141 | AF40: 7.75 | AH40: 11.375 | AL40: 111.4 | BG40: 14.11 | BH40: 44.467208 | BO40: 100.0822 | BQ40: 99.78174 | CH40: -4 | CI40: -7.5
A41: 31413 | C41: 1.1022 | D41: 155.93292 | G41: 6.31 | H41: 9.08 | U41: -5.7 | V41: -0.23 | X41: -7.3 | Y41: -34.6 | Z41: 831 | AC41: 119.53 | AD41: 211.78 | AE41: 259.7475 | AF41: 7.75 | AH41: 12.375 | AL41: 111.9 | BG41: 11.37 | BH41: 40.251376 | BO41: 100.1082 | BQ41: 99.83704 | CH41: -1.1 | CI41: -9.2 | CJ41: 31.1
A42: 31444 | C42: 1.0425 | D42: 159.46768 | G42: 6.23 | H42: 8.13 | U42: -5 | V42: -0.21 | X42: -6.9 | Y42: -35.9 | Z42: 737 | AC42: 112.4 | AD42: 226.92 | AE42: 282.5747 | AF42: 7.75 | AH42: 12.375 | AL42: 112.2 | BG42: 10.62 | BH42: 41.183392 | BO42: 100.1166 | BQ42: 99.89671 | CH42: -3.8 | CI42: -7.9 | CJ42: 28.5
A43: 31472 | C43: 1.0652 | D43: 160.1981 | G43: 5.75 | H43: 7.39 | U43: -4.5 | V43: -0.19 | X43: -6.8 | Y43: -33.5 | Z43: 734 | AC43: 122.43 | AD43: 238.9 | AE43: 309.6008 | AF43: 7.25 | AH43: 11.375 | AL43: 112.5 | BG43: 10.31 | BH43: 40.270821 | BO43: 100.1083 | BQ43: 99.95715 | CH43: -4.3 | CI43: -1.2 | CJ43: 29.1
A44: 31503 | C44: 1.0103 | D44: 150.36626 | G44: 5.36 | H44: 7.38 | U44: -5 | V44: -0.27 | X44: -7.3 | Y44: -30.7 | Z44: 658 | AC44: 120.12 | AD44: 235.52 | AE44: 317.5024 | AF44: 6.75 | AH44: 10.375 | AL44: 112.9 | BG44: 10.16 | BH44: 43.61628 | BO44: 100.0924 | BQ44: 100.0071 | CH44: -4.9 | CI44: 5.8 | CJ44: 29.6
A45: 31533 | C45: 1.0747 | D45: 132.63792 | G45: 5.75 | H45: 8.05 | J45: 6.34 | U45: -5.4 | V45: -0.21 | X45: -6.8 | Y45: -28.9 | Z45: 665 | AC45: 126.14 | AD45: 247.35 | AE45: 315.9833 | AF45: 6.8125 | AH45: 9.785 | AL45: 113.1 | BG45: 10.41 | BH45: 41.71588 | BN45: 6.34 | BO45: 100.0741 | BQ45: 100.0301 | CH45: -4.7 | CI45: 4.9 | CJ45: 31.4
A46: 31564 | C46: 1.0215 | D46: 122.51177 | G46: 5.87 | H46: 7.35 | J46: 6.24 | U46: -5.4 | V46: -0.26 | X46: -6.9 | Y46: -28.2 | Z46: 586 | AC46: 123.63 | AD46: 250.84 | AE46: 328.0407 | AF46: 6.875 | AH46: 9.785 | AL46: 113.4 | BG46: 10.16 | BH46: 41.210594 | BN46: 6.24 | BO46: 100.042 | BQ46: 100.0373 | CH46: -4.6 | CI46: 4.6 | CJ46: 31.1
A47: 31594 | C47: 0.9923 | D47: 132.11963 | G47: 5.77 | H47: 7.34 | J47: 6.16 | U47: -5.4 | V47: -0.27 | X47: -6.8 | Y47: -26.4 | Z47: 554 | AC47: 119.01 | AD47: 236.12 | AE47: 330.052 | AF47: 6.375 | AH47: 9.785 | AL47: 113.8 | BG47: 10.25 | BH47: 32.038759 | BN47: 6.16 | BO47: 99.99278 | BQ47: 100.0309 | CH47: -3.7 | CI47: -6.2 | CJ47: 29
A48: 31625 | C48: 0.9711 | D48: 127.5525 | G48: 5.6 | H48: 6.95 | J48: 5.89 | U48: -4.4 | V48: -0.3 | X48: -6.5 | Y48: -24.8 | Z48: 664 | AC48: 120.43 | AD48: 252.93 | AE48: 358.2604 | AF48: 5.875 | AH48: 9.785 | AL48: 114.2 | BG48: 10.02 | BH48: 37.768814 | BN48: 5.89 | BO48: 99.94153 | BQ48: 100.0136 | CH48: -5.6 | CI48: -3.3 | CJ48: 31.7
A49: 31656 | C49: 0.9699 | D49: 132.01833 | G49: 5.82 | H49: 7.45 | J49: 6.08 | U49: -4.4 | V49: -0.33 | X49: -7.2 | Y49: -23.7 | Z49: 800 | AC49: 115.25 | AD49: 231.32 | AE49: 343.3508 | AF49: 5.875 | AH49: 9.785 | AL49: 114.6 | BG49: 10.2 | BH49: 49.158038 | BN49: 6.08 | BO49: 99.89735 | BQ49: 99.98862 | CH49: -6.4 | CI49: -5.6 | CJ49: 32.3
A50: 31686 | C50: 0.9906 | D50: 111.50926 | G50: 6.14 | H50: 7.34 | J50: 6.24 | U50: -4 | V50: -0.41 | X50: -8.3 | Y50: -23.9 | Z50: 786 | AC50: 116.06 | AD50: 243.98 | AE50: 336.8208 | AF50: 5.875 | AH50: 10.875 | AL50: 115 | BG50: 10.16 | BH50: 43.373721 | BN50: 6.24 | BO50: 99.8709 | BQ50: 99.96295 | CH50: -4.9 | CI50: -6.7 | CJ50: 29.6
A51: 31717 | C51: 0.9504 | D51: 115.02029 | G51: 6.17 | H51: 7.15 | J51: 6.16 | U51: -4.3 | V51: -0.43 | X51: -7.7 | Y51: -25.1 | Z51: 738 | AC51: 118.99 | AD51: 249.22 | AE51: 350.4577 | AF51: 5.875 | AH51: 10.875 | AL51: 115.3 | BG51: 10 | BH51: 44.255445 | BN51: 6.16 | BO51: 99.88484 | BQ51: 99.94996 | CH51: -4.7 | CI51: -10.7 | CJ51: 29.3
A52: 31747 | C52: 0.9271 | D52: 108.96811 | G52: 5.96 | H52: 7.23 | J52: 6.27 | U52: -4.7 | V52: -0.34 | X52: -6.9 | Y52: -26.5 | Z52: 699 | AC52: 114.69 | AD52: 242.16 | AE52: 356.8254 | AF52: 5.875 | AH52: 10.875 | AL52: 115.6 | BG52: 9.99 | BH52: 33.568141 | BN52: 6.27 | BO52: 99.96575 | BQ52: 99.97139 | CH52: -4.5 | CI52: -6.4 | CJ52: 33.2
A53: 31778 | C53: 0.8899 | D53: 122.11428 | E53: 57.107346 | G53: 5.95 | H53: 7.18 | J53: 6.08 | U53: -4.7 | V53: -0.39 | X53: -8 | Y53: -28.4 | Z53: 866 | AC53: 106.75 | AD53: 274.08 | AE53: 398.1059 | AF53: 6 | AH53: 10.875 | AL53: 115.9 | BG53: 9.68 | BH53: 51.199847 | BN53: 6.08 | BO53: 100.1237 | BQ53: 100.0465 | CH53: -6.2 | CI53: -6.9 | CJ53: 26.8
A54: 31809 | C54: 0.8842 | D54: 109.14523 | E54: 49.240593 | G54: 5.94 | H54: 7.19 | J54: 6.21 | U54: -5.4 | V54: -0.54 | X54: -9.1 | Y54: -28.1 | Z54: 852 | AC54: 106.16 | AD54: 284.2 | AE54: 410.5891 | AF54: 6 | AH54: 10.875 | AL54: 116.2 | BG54: 9.62 | BH54: 48.559818 | BN54: 6.21 | BO54: 100.3355 | BQ54: 100.148 | CH54: -4.5 | CI54: -1.7 | CJ54: 29
A55: 31837 | C55: 0.8695 | D55: 122.08486 | E55: 79.679747 | G55: 5.88 | H55: 7.51 | J55: 6.08 | U55: -5.6 | V55: -0.36 | X55: -7.6 | Y55: -26.5 | Z55: 992 | AC55: 109.62 | AD55: 291.7 | AE55: 435.3544 | AF55: 6 | AH55: 9.875 | AL55: 116.6 | BG55: 9.7 | BH55: 64.365256 | BN55: 6.08 | BO55: 100.5561 | BQ55: 100.2785 | CH55: -5.4 | CI55: 0.5 | CJ55: 26.9
A56: 31868 | C56: 0.8626 | D56: 110.85971 | E56: 63.258819 | G56: 5.62 | H56: 8.21 | J56: 6.12 | U56: -6 | V56: -0.37 | X56: -7.2 | Y56: -23.4 | Z56: 1020 | AC56: 109.67 | AD56: 288.35 | AE56: 460.2089 | AF56: 6.5 | AH56: 9.375 | AL56: 117.3 | BG56: 10.37 | BH56: 83.273907 | BN56: 6.12 | BO56: 100.7574 | BQ56: 100.413 | CH56: -6.2 | CI56: 0.5 | CJ56: 27.6
A57: 31898 | C57: 0.8769 | D57: 110.04291 | E57: 47.488354 | G57: 5.54 | H57: 8.49 | J57: 6.07 | U57: -6.8 | V57: -0.3 | X57: -6.4 | Y57: -20.8 | Z57: 1070 | AC57: 109.15 | AD57: 290.1 | AE57: 460.177 | AF57: 6.75 | AH57: 8.875 | AL57: 117.7 | BG57: 10.57 | BH57: 43.018902 | BN57: 6.07 | BO57: 100.9236 | BQ57: 100.5274 | CH57: -6.8 | CI57: 0.4 | CJ57: 19.4
A58: 31929 | B58: 19.08 | C58: 0.8803 | D58: 121.15791 | E58: 71.710519 | G58: 5.83 | H58: 8.38 | J58: 6.37 | U58: -7.3 | V58: -0.24 | X58: -6.5 | Y58: -21.1 | Z58: 880 | AC58: 117.56 | AD58: 304 | AE58: 459.236 | AF58: 6.75 | AH58: 8.875 | AL58: 117.9 | BG58: 10.5 | BH58: 44.402232 | BN58: 6.37 | BO58: 101.0392 | BQ58: 100.6101 | CH58: -6.4 | CI58: 0.6 | CJ58: 20.1
A59: 31959 | B59: 20.03 | C59: 0.8958 | D59: 106.348 | E59: 33.791031 | G59: 6.18 | H59: 8.66 | J59: 6.58 | U59: -7.2 | V59: -0.16 | X59: -6.2 | Y59: -20.3 | Z59: 976 | AC59: 124.14 | AD59: 318.66 | AE59: 467.7377 | AF59: 6.625 | AH59: 8.875 | AL59: 118.3 | BG59: 10.77 | BH59: 47.50262 | BN59: 6.58 | BO59: 101.0853 | BQ59: 100.6435 | CH59: -5.3 | CI59: 0.3 | CJ59: 22.4
A60: 31990 | B60: 18.63 | C60: 0.8731 | D60: 74.837964 | E60: 37.788699 | G60: 6.42 | H60: 9 | J60: 6.55 | U60: -7.2 | V60: -0.1 | X60: -4.4 | Y60: -23.4 | Z60: 1111 | AC60: 123.57 | AD60: 329.79 | AE60: 494.7011 | AF60: 6.75 | AH60: 9.875 | AL60: 118.7 | BG60: 10.92 | BH60: 30.955189 | BN60: 6.55 | BO60: 101.0408 | BQ60: 100.629 | CH60: -6.3 | CI60: -3.3 | CJ60: 21.1
A61: 32021 | B61: 18.48 | C61: 0.8844 | D61: 78.981394 | E61: 35.242371 | G61: 6.68 | H61: 9.63 | J61: 7.06 | U61: -5.5 | V61: -0.02 | X61: -3 | Y61: -23.8 | Z61: 1045 | AC61: 121.3 | AD61: 321.83 | AE61: 485.4003 | AF61: 7.3125 | AH61: 9.875 | AL61: 119.2 | BG61: 11.54 | BH61: 36.716807 | BN61: 7.06 | BO61: 100.911 | BQ61: 100.5776 | CH61: -4.5 | CI61: -2.5 | CJ61: 19.2
A62: 32051 | B62: 18.8 | C62: 0.8386 | D62: 143.60309 | E62: 99.403613 | G62: 6.89 | H62: 8.88 | J62: 6.51 | U62: -6.2 | V62: 0 | X62: -2.9 | Y62: -19.9 | Z62: 1172 | AC62: 87.91 | AD62: 251.79 | AE62: 402.279 | AF62: 7.3125 | AH62: 9.375 | AL62: 119.8 | BG62: 11.33 | BH62: 44.787094 | BN62: 6.51 | BO62: 100.7259 | BQ62: 100.4953 | CH62: -3.1 | CI62: -3.5 | CJ62: 20.9
A63: 32082 | B63: 17.7 | C63: 0.7938 | D63: 155.42208 | E63: 124.73959 | G63: 6.33 | H63: 8.99 | J63: 6.25 | U63: -7.1 | V63: 0.05 | X63: -3.1 | Y63: -22.9 | Z63: 1176 | AC63: 72.27 | AD63: 230.31 | AE63: 391.7646 | AF63: 6.8125 | AH63: 8.875 | AL63: 120.1 | BG63: 11.23 | BH63: 50.887178 | BN63: 6.25 | BO63: 100.538 | BQ63: 100.4079 | CH63: -3 | CI63: -2.5 | CJ63: 19.3
A64: 32112 | B64: 17.6 | C64: 0.7629 | D64: 135.47265 | E64: 77.438844 | G64: 6.43 | H64: 8.83 | J64: 6.42 | U64: -6.6 | V64: 0.08 | X64: -3.8 | Y64: -25.8 | Z64: 1264 | AC64: 77.87 | AD64: 247.09 | AE64: 407.9941 | AF64: 6.8125 | AH64: 8.375 | AL64: 120.4 | BG64: 11.22 | BH64: 43.081087 | BN64: 6.42 | BO64: 100.4061 | BQ64: 100.3476 | CH64: -4.1 | CI64: -4.5 | CJ64: 14.8
A65: 32143 | B65: 16.28 | C65: 0.8153 | D65: 131.52146 | E65: 83.657221 | G65: 6.48 | H65: 8.26 | J65: 6.28 | U65: -6.8 | V65: 0.17 | X65: -3.3 | Y65: -22.4 | Z65: 1393 | AC65: 79.94 | AD65: 257.07 | AE65: 417.2128 | AF65: 6.625 | AH65: 8.375 | AL65: 120.9 | BG65: 10.77 | BH65: 49.580817 | BN65: 6.28 | BO65: 100.3376 | BQ65: 100.3397 | CH65: -5.3 | CI65: -4.8 | CJ65: 15.7
A66: 32174 | B66: 14.73 | C66: 0.8141 | D66: 116.58432 | E66: 65.582269 | G66: 6.27 | H66: 8.16 | J66: 6.04 | U66: -6.3 | V66: 0.25 | X66: -2.3 | Y66: -30.5 | Z66: 1564 | AC66: 87.58 | AD66: 267.82 | AE66: 440.6826 | AF66: 6.5 | AH66: 8.875 | AL66: 121.2 | BG66: 10.53 | BH66: 60.861747 | BN66: 6.04 | BO66: 100.3241 | BQ66: 100.3869 | CH66: -4.4 | CI66: -4.9 | CJ66: 17.3
A67: 32203 | B67: 15.65 | C67: 0.795 | D67: 105.05246 | E67: 75.881997 | G67: 6.21 | H67: 8.57 | J67: 6.11 | U67: -6 | V67: 0.41 | X67: -1.8 | Y67: -26.2 | Z67: 1617 | AC67: 91.48 | AD67: 258.89 | AE67: 453.2272 | AF67: 6.75 | AH67: 8.375 | AL67: 121.7 | BG67: 10.76 | BH67: 52.543893 | BN67: 6.11 | BO67: 100.3541 | BQ67: 100.4852 | CH67: -4.2 | CI67: 1.4 | CJ67: 13
A68: 32234 | B68: 16.6 | C68: 0.81 | D68: 113.65598 | E68: 65.337287 | G68: 6.28 | H68: 8.87 | J68: 6.41 | U68: -5.2 | V68: 0.44 | X68: -0.8 | Y68: -22.4 | Z68: 1358 | AC68: 94.85 | AD68: 261.33 | AE68: 458.164 | AF68: 6.75 | AH68: 7.875 | AL68: 122.3 | BG68: 10.94 | BH68: 37.532414 | BN68: 6.41 | BO68: 100.413 | BQ68: 100.6229 | CH68: -3 | CI68: 0.5 | CJ68: 14
A69: 32264 | B69: 16.2 | C69: 0.8327 | D69: 96.145724 | E69: 72.29776 | G69: 6.59 | H69: 9.2 | J69: 6.45 | U69: -5.9 | V69: 0.53 | X69: 0.2 | Y69: -21.1 | Z69: 1349 | AC69: 93.56 | AD69: 262.14 | AE69: 448.228 | AF69: 7.25 | AH69: 7.375 | AL69: 122.7 | BG69: 11.13 | BH69: 32.408918 | BN69: 6.45 | BO69: 100.4877 | BQ69: 100.7812 | CH69: -3 | CI69: 2.2 | CJ69: 14.7
... A89: 32874 | B89: 20.5 | C89: 0.8181 | D89: 100.35918 | E89: 61.936697 | G89: 7.63 | H89: 8.43 | J89: 8.31 | U89: -2.2 | V89: 1.02 | X89: 4.3 | Y89: 1.8 | Z89: 1644 | AC89: 127.39 | AD89: 329.08 | AE89: 539.9443 | AF89: 8.25 | AH89: 14.785 | AL89: 132.1 | BG89: 10.11 | BH89: 30.920652 | BN89: 8.31 | BO89: 99.79606 | BQ89: 101.0773 | CH89: -0.9 | CI89: -0.9 | CJ89: 29.1
A90: 32905 | B90: 19.2 | C90: 0.8274 | D90: 89.590954 | E90: 93.005259 | F90: 21.99 | G90: 8.43 | H90: 8.51 | J90: 8.89 | U90: -2.1 | V90: 0.96 | X90: 3 | Y90: 1.5 | Z90: 1604 | AC90: 120.47 | AD90: 331.89 | AE90: 515.8864 | AF90: 8.25 | AH90: 14.785 | AL90: 132.7 | BG90: 10.19 | BH90: 30.685625 | BN90: 8.89 | BO90: 99.82644 | BQ90: 101.078 | CH90: 0.6 | CI90: 2.9 | CJ90: 25.8
A91: 32933 | B91: 17.95 | C91: 0.8252 | D91: 86.065289 | E91: 109.69106 | F91: 19.73 | G91: 8.67 | H91: 8.65 | J91: 8.66 | U91: -3.1 | V91: 0.96 | X91: 3.7 | Y91: 0.9 | Z91: 1529 | AC91: 131.04 | AD91: 339.94 | AE91: 483.8177 | AF91: 8.25 | AH91: 14.785 | AL91: 133.5 | BG91: 10.23 | BH91: 36.76701 | BN91: 8.66 | BO91: 99.82584 | BQ91: 101.0862 | CH91: -0.9 | CI91: 1.7 | CJ91: 28.9
A92: 32964 | B92: 16.35 | C92: 0.8201 | D92: 76.6617 | E92: 78.421294 | F92: 19.52 | G92: 8.7 | H92: 9.04 | J92: 8.99 | U92: -2.5 | V92: 0.9 | X92: 3.1 | Y92: 0.5 | Z92: 1361 | AC92: 127.53 | AD92: 330.8 | AE92: 475.9222 | AF92: 8.25 | AH92: 14.785 | AL92: 134 | BG92: 10.54 | BH92: 36.441399 | BN92: 8.99 | BO92: 99.75095 | BQ92: 101.0958 | CH92: 0 | CI92: -2.1 | CJ92: 30.7
A93: 32994 | B93: 15.3 | C93: 0.8238 | D93: 118.53795 | E93: 51.542173 | F93: 17.37 | G93: 8.74 | H93: 8.6 | J93: 8.99 | U93: -3.4 | V93: 0.85 | X93: 1.8 | Y93: -1.5 | Z93: 1299 | AC93: 131.07 | AD93: 361.23 | AE93: 525.1005 | AF93: 8.25 | AH93: 14.785 | AL93: 134.4 | BG93: 10.31 | BH93: 37.74057 | BN93: 8.99 | BO93: 99.58015 | BQ93: 101.0834 | CH93: 1.1 | CI93: -1.3 | CJ93: 30.7
A94: 33025 | B94: 15.73 | C94: 0.8068 | D94: 120.52674 | E94: 82.67878 | F94: 15.5 | G94: 8.82 | H94: 8.43 | J94: 8.85 | U94: -3.2 | V94: 0.73 | X94: 1.5 | Y94: 1.4 | Z94: 1089 | AC94: 132.76 | AD94: 358.02 | AE94: 520.4079 | AF94: 8.25 | AH94: 14.785 | AL94: 135.1 | BG94: 10.22 | BH94: 40.41469 | BN94: 8.85 | BO94: 99.29379 | BQ94: 101.0238 | CH94: 0.9 | CI94: 0 | CJ94: 28.6
A95: 33055 | B95: 19.23 | C95: 0.7686 | D95: 111.56962 | E95: 52.08985 | F95: 21.11 | G95: 8.58 | H95: 8.36 | J95: 8.71 | U95: -3 | V95: 0.7 | X95: 1.3 | Y95: -1.2 | Z95: 1165 | AC95: 129.19 | AD95: 356.15 | AE95: 524.1785 | AF95: 8 | AH95: 14.785 | AL95: 135.8 | BG95: 10.13 | BH95: 39.868876 | BN95: 8.71 | BO95: 98.8976 | BQ95: 100.9091 | CH95: 0 | CI95: 0.1 | CJ95: 28.8
A96: 33086 | B96: 27.8 | C96: 0.7589 | D96: 142.16524 | E96: 45.300538 | F96: 29.9 | G96: 8.9 | H96: 8.86 | J96: 9.07 | U96: -3.4 | V96: 0.61 | X96: 0.3 | Y96: 0 | Z96: 1208 | AC96: 112.81 | AD96: 322.56 | AE96: 474.1292 | AF96: 8 | AH96: 14.785 | AL96: 136.6 | BG96: 10.55 | BH96: 34.012132 | BN96: 9.07 | BO96: 98.42283 | BQ96: 100.7357 | CH96: -0.8 | CI96: -0.1 | CJ96: 25.6
A97: 33117 | B97: 41 | C97: 0.7582 | D97: 157.69529 | E97: 128.50286 | F97: 29.11 | G97: 9.09 | H97: 8.82 | J97: 9.31 | U97: -8.4 | V97: 0.48 | X97: 0.8 | Y97: -0.5 | Z97: 1168 | AC97: 102.25 | AD97: 306.05 | AE97: 423.1448 | AF97: 8 | AH97: 14.785 | AL97: 137.1 | BG97: 10.76 | BH97: 33.189222 | BN97: 9.31 | BO97: 97.94213 | BQ97: 100.5101 | CH97: -1.7 | CI97: -0.2 | CJ97: 28.4
A98: 33147 | B98: 34.3 | C98: 0.7322 | D98: 141.11953 | E98: 128.33419 | F98: 30.04 | G98: 9.09 | H98: 8.65 | J98: 9.16 | U98: -8.7 | V98: 0.4 | X98: -0.9 | Y98: -4 | Z98: 1309 | AC98: 105.36 | AD98: 304 | AE98: 461.6402 | AF98: 7.75 | AH98: 13.875 | AL98: 137.6 | BG98: 10.78 | BH98: 30.095982 | BN98: 9.16 | BO98: 97.52457 | BQ98: 100.2601 | CH98: -1.5 | CI98: 1.1 | CJ98: 22.8
A99: 33178 | B99: 31.2 | C99: 0.7287 | D99: 145.29093 | E99: 100.46349 | F99: 22.16 | G99: 8.95 | H99: 8.26 | J99: 9.09 | U99: -7.1 | V99: 0.21 | X99: -1.7 | Y99: -6.1 | Z99: 1348 | AC99: 103.96 | AD99: 322.22 | AE99: 453.0497 | AF99: 7.5 | AH99: 13.875 | AL99: 138 | BG99: 10.53 | BH99: 35.441658 | BN99: 9.09 | BO99: 97.23554 | BQ99: 100.0128 | CH99: -0.9 | CI99: -1.4 | CJ99: 25.5
A100: 33208 | B100: 28.35 | C100: 0.7294 | D100: 134.48512 | E100: 97.188143 | F100: 26.38 | G100: 8.85 | H100: 8.08 | J100: 9.14 | U100: -6.7 | V100: 0.01 | X100: -2.7 | Y100: -5.9 | Z100: 1446 | AC100: 104.01 | AD100: 330.22 | AE100: 461.5268 | AF100: 7 | AH100: 13.875 | AL100: 138.6 | BG100: 10.43 | BH100: 41.611625 | BN100: 9.14 | BO100: 97.1205 | BQ100: 99.79115 | CH100: -1.1 | CI100: -0.2 | CJ100: 22.7
A101: 33239 | B101: 20.7 | C101: 0.7177 | D101: 175.65861 | E101: 83.721219 | F101: 20.91 | G101: 8.94 | H101: 8.03 | J101: 8.92 | U101: -10 | V101: -0.5 | X101: -7.4 | Y101: -6.8 | Z101: 1473 | AC101: 106.12 | AD101: 343.93 | AE101: 477.3869 | AF101: 6.75 | AH101: 13.875 | AL101: 139.5 | BG101: 10.33 | BH101: 32.899384 | BN101: 8.92 | BO101: 97.17929 | BQ101: 99.61333 | CH101: -2.5 | CI101: -3.6 | CJ101: 21.6
A102: 33270 | B102: 19.5 | C102: 0.743 | D102: 115.21345 | E102: 98.123628 | F102: 21.23 | G102: 8.42 | H102: 8.02 | J102: 8.6 | U102: -10.4 | V102: -0.76 | X102: -9.9 | Y102: -7.9 | Z102: 1704 | AC102: 116.77 | AD102: 367.07 | AE102: 520.574 | AF102: 6.25 | AH102: 12.875 | AL102: 140.2 | BG102: 10.11 | BH102: 31.285802 | BN102: 8.6 | BO102: 97.39518 | BQ102: 99.51273 | CH102: -4.4 | CI102: -5.9 | CJ102: 23.4
A103: 33298 | B103: 18 | C103: 0.8242 | D103: 116.02571 | E103: 105.46522 | F103: 16.88 | G103: 8.41 | H103: 8.05 | I103: 13.68 | J103: 8.71 | U103: -7.5 | V103: -0.91 | X103: -10.9 | Y103: -12.1 | Z103: 1609 | AC103: 126.28 | AD103: 375.22 | AE103: 504.264 | AF103: 6 | AH103: 12.375 | AL103: 140.5 | BG103: 10.01 | BH103: 33.235622 | BN103: 8.71 | BO103: 97.71642 | BQ103: 99.50066 | CH103: -3.4 | CI103: -4 | CJ103: 23.6
A104: 33329 | B104: 19.7 | C104: 0.8347 | D104: 107.24167 | E104: 98.640078 | F104: 18.24 | G104: 8.39 | H104: 8.02 | I104: 13.41 | J104: 8.6 | U104: -8.2 | V104: -0.86 | X104: -10.8 | Y104: -17.1 | Z104: 1626 | AC104: 127.11 | AD104: 375.35 | AE104: 507.2434 | AF104: 5.75 | AH104: 11.875 | AL104: 140.9 | BG104: 9.85 | BH104: 39.74462 | BN104: 8.6 | BO104: 98.08286 | BQ104: 99.54465 | CH104: -5.8 | CI104: -4.3 | CJ104: 21.7
A105: 33359 | B105: 19 | C105: 0.8446 | D105: 94.758676 | E105: 94.920871 | F105: 15.93 | G105: 8.39 | H105: 8.06 | I105: 12.79 | J105: 8.54 | U105: -7.6 | V105: -0.91 | X105: -10.9 | Y105: -19.6 | Z105: 1757 | AC105: 128.01 | AD105: 389.83 | AE105: 517.7636 | AF105: 5.75 | AH105: 11.375 | AL105: 141.3 | BG105: 9.83 | BH105: 42.744521 | BN105: 8.54 | BO105: 98.45161 | BQ105: 99.61491 | CH105: -4.2 | CI105: -6.1 | CJ105: 19.3
A106: 33390 | B106: 18.48 | C106: 0.8786 | D106: 96.937604 | E106: 122.41663 | F106: 19.55 | G106: 8.39 | H106: 8.24 | I106: 13.32 | J106: 8.76 | U106: -8.7 | V106: -0.94 | X106: -11.1 | Y106: -19.1 | Z106: 1703 | AC106: 124.53 | AD106: 371.16 | AE106: 484.8461 | AF106: 5.75 | AH106: 11.375 | AL106: 141.8 | BG106: 9.9 | BH106: 39.26646 | BN106: 8.76 | BO106: 98.7893 | BQ106: 99.69368 | CH106: -5.6 | CI106: -6.3 | CJ106: 16.8
A107: 33420 | B107: 19.65 | C107: 0.8496 | D107: 93.531578 | E107: 80.284 | F107: 15.18 | G107: 8.61 | H107: 8.2 | I107: 13.49 | J107: 8.88 | U107: -11.1 | V107: -0.97 | X107: -11.4 | Y107: -18.4 | Z107: 1466 | AC107: 126.84 | AD107: 387.81 | AE107: 506.7775 | AF107: 5.75 | AH107: 10.875 | AL107: 142.3 | BG107: 9.8 | BH107: 44.008631 | BN107: 8.88 | BO107: 99.04856 | BQ107: 99.76798 | CH107: -5.5 | CI107: -4.5 | CJ107: 21.9
A108: 33451 | B108: 20.53 | C108: 0.8504 | D108: 100.59554 | E108: 79.842159 | F108: 14.46 | G108: 8.56 | H108: 7.82 | I108: 13.29 | J108: 8.76 | U108: -11.4 | V108: -0.96 | X108: -11 | Y108: -17.5 | Z108: 1545 | AC108: 126.25 | AD108: 395.43 | AE108: 504.1975 | AF108: 5.5 | AH108: 10.875 | AL108: 142.9 | BG108: 9.57 | BH108: 33.826272 | BN108: 8.76 | BO108: 99.19031 | BQ108: 99.83169 | CH108: -4.8 | CI108: -8.5 | CJ108: 22.8
A109: 33482 | B109: 21.43 | C109: 0.8129 | D109: 117.04782 | E109: 62.662563 | F109: 15.85 | G109: 8.45 | H109: 7.47 | I109: 12.9 | J109: 8.79 | U109: -9.6 | V109: -1.01 | X109: -12.5 | Y109: -19.4 | Z109: 1524 | AC109: 123.31 | AD109: 387.86 | AE109: 516.4321 | AF109: 5.25 | AH109: 10.375 | AL109: 143.4 | BG109: 9.41 | BH109: 33.191289 | BN109: 8.79 | BO109: 99.22101 | BQ109: 99.87463 | CH109: -4.6 | CI109: -8.7 | CJ109: 19.8
A110: 33512 | B110: 22 | C110: 0.8166 | D110: 105.54142 | E110: 105.20462 | F110: 15.48 | G110: 8.36 | H110: 7.47 | I110: 12.79 | J110: 8.78 | U110: -10.2 | V110: -0.98 | X110: -12 | Y110: -19.9 | Z110: 1655 | AC110: 124.25 | AD110: 392.46 | AE110: 523.818 | AF110: 5 | AH110: 10.375 | AL110: 143.7 | BG110: 9.49 | BH110: 35.720773 | BN110: 8.78 | BO110: 99.17326 | BQ110: 99.89034 | CH110: -5.6 | CI110: -6.5 | CJ110: 23.2
A111: 33543 | B111: 20.08 | C111: 0.7994 | D111: 122.24914 | E111: 80.815893 | F111: 20.26 | G111: 8.34 | H111: 7.38 | I111: 13 | J111: 8.83 | U111: -9.9 | V111: -1.04 | X111: -11.9 | Y111: -19.3 | Z111: 1589 | AC111: 124.6 | AD111: 375.22 | AE111: 499.994 | AF111: 4.75 | AH111: 10.375 | AL111: 144.2 | BG111: 9.44 | BH111: 38.609201 | BN111: 8.83 | BO111: 99.10125 | BQ111: 99.88635 | CH111: -2.5 | CI111: -8.2 | CJ111: 22
A112: 33573 | B112: 17.75 | C112: 0.7477 | D112: 139.99912 | E112: 84.470982 | F112: 19.31 | G112: 8.24 | H112: 6.71 | I112: 12.88 | J112: 8.59 | U112: -9.9 | V112: -1.13 | X112: -13.1 | Y112: -13.4 | Z112: 1494 | AC112: 125.72 | AD112: 417.09 | AE112: 535.3642 | AF112: 4 | AH112: 10.375 | AL112: 144.7 | BG112: 9.1 | BH112: 41.897909 | BN112: 8.59 | BO112: 99.06853 | BQ112: 99.86762 | CH112: -3.6 | CI112: -11.5 | CJ112: 20.1
A113: 33604 | B113: 18.15 | C113: 0.7858 | D113: 109.20085 | E113: 52.970736 | F113: 17.4 | G113: 7.98 | H113: 7.31 | I113: 12.6 | J113: 8.35 | U113: -11.1 | V113: -1.12 | X113: -12.7 | Y113: -16.6 | Z113: 1430 | AC113: 133.76 | AD113: 408.79 | AE113: 524.4481 | AF113: 4 | AH113: 10.375 | AL113: 145.1 | BG113: 9.21 | BH113: 51.127564 | BN113: 8.35 | BO113: 99.11964 | BQ113: 99.84193 | CH113: -3 | CI113: -10.2 | CJ113: 19.9
A114: 33635 | B114: 17.45 | C114: 0.8002 | D114: 125.53676 | E114: 60.151297 | F114: 16.68 | G114: 7.92 | H114: 7.27 | I114: 12.48 | J114: 8.18 | U114: -10.1 | V114: -1.07 | X114: -12.6 | Y114: -18 | Z114: 1222 | AC114: 138.66 | AD114: 412.7 | AE114: 514.4016 | AF114: 4 | AH114: 10.375 | AL114: 145.4 | BG114: 9.17 | BH114: 42.272127 | BN114: 8.18 | BO114: 99.24603 | BQ114: 99.80693 | CH114: -3.6 | CI114: -13.2 | CJ114: 20.8
... A116: 33695 | B116: 19.65 | C116: 0.8056 | D116: 87.58229 | E116: 70.483119 | F116: 15.53 | G116: 8.04 | H116: 7.61 | I116: 12.64 | J116: 8.33 | U116: -12.2 | V116: -1.17 | X116: -14.4 | Y116: -25 | Z116: 1216 | AC116: 142.75 | AD116: 414.95 | AE116: 494.99251 | AF116: 3.75 | AH116: 10.375 | AL116: 146.3 | BG116: 9.24 | BH116: 39.768089 | BN116: 8.33 | BO116: 99.56967 | BQ116: 99.64025 | CH116: -4.4 | CI116: -12.7 | CJ116: 17.5
A117: 33725 | B117: 20.7 | C117: 0.7816 | D117: 96.874945 | E117: 91.904872 | F117: 13.86 | G117: 8.08 | H117: 7.33 | I117: 12.67 | J117: 8.28 | U117: -12.9 | V117: -1.23 | X117: -14.5 | Y117: -26.2 | Z117: 1267 | AC117: 144.46 | AD117: 415.35 | AE117: 513.66518 | AF117: 3.75 | AH117: 9.875 | AL117: 146.8 | BG117: 9.1 | BH117: 33.890599 | BN117: 8.28 | BO117: 99.66689 | BP117: 101.877 | BQ117: 99.4678 | CH117: -6.1 | CI117: -12 | CJ117: 18.4
A118: 33756 | B118: 20.6 | C118: 0.744 | D118: 122.34916 | E118: 113.02247 | F118: 13.35 | G118: 8.06 | H118: 7.14 | I118: 13.19 | J118: 8.32 | U118: -12.9 | V118: -1.28 | X118: -15.4 | Y118: -24.1 | Z118: 1091 | AC118: 137.3 | AD118: 408.14 | AE118: 495.42406 | AF118: 3.75 | AH118: 9.875 | AL118: 147.1 | BG118: 9 | BH118: 39.016188 | BN118: 8.32 | BO118: 99.69571 | BP118: 102.1567 | BQ118: 99.21696 | CH118: -5.5 | CI118: -15.1 | CJ118: 12.6
A119: 33786 | B119: 20.38 | C119: 0.726 | D119: 120.91493 | E119: 102.32051 | F119: 13.17 | G119: 8.12 | H119: 6.72 | I119: 14.11 | J119: 8.46 | U119: -12.7 | V119: -1.38 | X119: -17.7 | Y119: -29.9 | Z119: 1060 | AC119: 131.08 | AD119: 424.21 | AE119: 495.64487 | AF119: 3.25 | AH119: 9.875 | AL119: 147.6 | BG119: 8.69 | BH119: 50.34085 | BN119: 8.46 | BO119: 99.68433 | BP119: 102.3881 | BQ119: 98.89837 | CH119: -8.8 | CI119: -17.1 | CJ119: 14.8
A120: 33817 | B120: 19.65 | C120: 0.6933 | D120: 115.90751 | E120: 74.150487 | F120: 13.58 | G120: 8.08 | H120: 6.62 | I120: 13.95 | J120: 8.33 | U120: -13.6 | V120: -1.51 | X120: -19.3 | Y120: -29.7 | Z120: 1073 | AC120: 126.03 | AD120: 414.03 | AE120: 506.63724 | AF120: 3.25 | AH120: 9.875 | AL120: 147.9 | BG120: 8.68 | BH120: 54.207482 | BN120: 8.33 | BO120: 99.67353 | BP120: 102.5667 | BQ120: 98.53934 | CH120: -6.1 | CI120: -16 | CJ120: 14.2
A121: 33848 | B121: 20.18 | C121: 0.7213 | D121: 127.01963 | E121: 179.83533 | F121: 14.28 | G121: 7.71 | H121: 6.37 | I121: 14.15 | J121: 7.81 | U121: -15.3 | V121: -1.78 | X121: -22 | Y121: -30.3 | Z121: 1041 | AC121: 129.96 | AD121: 417.8 | AE121: 500.95269 | AF121: 3 | AH121: 8.875 | AL121: 148.1 | BG121: 8.66 | BH121: 45.732689 | BN121: 7.81 | BO121: 99.70633 | BP121: 102.695 | BQ121: 98.18175 | CH121: -8.8 | CI121: -14.8 | CJ121: 11.7
A122: 33878 | B122: 19.13 | C122: 0.7856 | D122: 138.52178 | E122: 135.07635 | F122: 16.15 | G122: 7.47 | H122: 6.8 | I122: 13.59 | J122: 7.57 | U122: -16.7 | V122: -2.05 | X122: -25.5 | Y122: -40 | Z122: 1111 | AC122: 124.05 | AD122: 418.68 | AE122: 486.38437 | AF122: 3 | AH122: 7.875 | AL122: 148.8 | BG122: 8.99 | BH122: 49.294646 | BN122: 7.57 | BO122: 99.80672 | BP122: 102.7779 | BQ122: 97.85743 | CH122: -7.6 | CI122: -17.5 | CJ122: 8.7
A123: 33909 | B123: 19.25 | C123: 0.815 | D123: 118.77686 | E123: 113.55889 | F123: 13.01 | G123: 7.38 | H123: 6.95 | I123: 13.5 | J123: 7.54 | U123: -17.3 | V123: -2.27 | X123: -27.9 | Y123: -37.8 | Z123: 1320 | AC123: 126.22 | AD123: 431.35 | AE123: 494.11309 | AF123: 3 | AH123: 6.875 | AL123: 149.2 | BG123: 8.95 | BH123: 65.301276 | BN123: 7.54 | BO123: 99.95232 | BP123: 102.8095 | BQ123: 97.59095 | CH123: -12.7 | CI123: -17.6 | CJ123: 4.6
A124: 33939 | B124: 17.85 | C124: 0.8299 | D124: 106.86792 | E124: 98.885536 | F124: 12.57 | G124: 7.33 | H124: 6.7 | I124: 13.54 | J124: 7.22 | U124: -18.1 | V124: -2.39 | X124: -28.9 | Y124: -29 | Z124: 1373 | AC124: 129.71 | AD124: 435.71 | AE124: 497.13209 | AF124: 3 | AH124: 6.875 | AL124: 149.6 | BG124: 8.76 | BH124: 46.451215 | BN124: 7.22 | BO124: 100.083 | BP124: 102.7969 | BQ124: 97.3981 | CH124: -13.3 | CI124: -14.3 | CJ124: 10.9
A125: 33970 | B125: 18.48 | C125: 0.8258 | D125: 102.53033 | E125: 182.15576 | F125: 12.42 | G125: 7.15 | H125: 6.39 | I125: 13.16 | J125: 7.08 | U125: -18.9 | V125: -2.52 | X125: -29.8 | Y125: -37.7 | Z125: 1278 | AC125: 132.48 | AD125: 438.78 | AE125: 497.83276 | AF125: 3 | AH125: 5.875 | AL125: 150.1 | BG125: 8.5 | BH125: 52.84246 | BN125: 7.08 | BO125: 100.1467 | BP125: 102.7483 | BQ125: 97.27782 | CH125: -12.9 | CI125: -15.3 | CJ125: 10.3
A126: 34001 | B126: 18.83 | C126: 0.8489 | D126: 119.96254 | E126: 120.84519 | F126: 13.16 | G126: 6.94 | H126: 6.03 | I126: 13.07 | J126: 6.57 | U126: -18.3 | V126: -2.56 | X126: -29.7 | Y126: -35.7 | Z126: 1373 | AC126: 138.78 | AD126: 443.38 | AE126: 508.67315 | AF126: 3 | AH126: 5.875 | AL126: 150.6 | BG126: 8.23 | BH126: 58.234908 | BN126: 6.57 | BO126: 100.1299 | BP126: 102.6684 | BQ126: 97.22562 | CH126: -13.8 | CI126: -12 | CJ126: 9.1
A127: 34029 | B127: 18.7 | C127: 0.8313 | D127: 121.55786 | E127: 152.96633 | F127: 12.53 | G127: 6.66 | H127: 6.03 | I127: 13.39 | J127: 6.66 | U127: -19 | V127: -2.42 | X127: -28.9 | Y127: -37.3 | Z127: 1503 | AC127: 144.52 | AD127: 451.67 | AE127: 537.19968 | AF127: 3 | AH127: 5.875 | AL127: 150.8 | BG127: 8.21 | BH127: 41.168289 | BN127: 6.66 | BO127: 100.0389 | BP127: 102.5444 | BQ127: 97.2347 | CH127: -13.9 | CI127: -17.5 | CJ127: 8.9
A128: 34060 | B128: 18.85 | C128: 0.8133 | D128: 109.25684 | E128: 81.606912 | F128: 12.42 | G128: 6.68 | H128: 6.05 | I128: 12.94 | J128: 6.72 | U128: -17.1 | V128: -2.52 | X128: -29.7 | Y128: -38.1 | Z128: 1554 | AC128: 142.5 | AD128: 440.19 | AE128: 561.11626 | AF128: 3 | AH128: 5.875 | AL128: 151.4 | BG128: 8.17 | BH128: 46.748119 | BN128: 6.72 | BO128: 99.90532 | BP128: 102.3593 | BQ128: 97.291 | CH128: -13.7 | CI128: -18.4 | CJ128: 9
... A148: 34669 | B148: 16.23 | C148: 0.8155 | D148: 91.795 | E148: 124.67861 | F148: 13.2 | G148: 7.46 | H148: 7.84 | I148: 12.41 | J148: 7.76 | U148: -8.1 | V148: 0.65 | X148: 3.5 | Y148: -21.3 | Z148: 1965 | AC148: 188.08 | AD148: 459.27 | AE148: 618.58971 | AF148: 5.5 | AH148: 6.125 | AL148: 158.3 | BG148: 9.14 | BH148: 44.797688 | BN148: 7.76 | BO148: 100.5019 | BP148: 100.4371 | BQ148: 101.646 | CH148: 0.7 | CI148: -9.7 | CJ148: 10.2
A149: 34700 | B149: 16.8 | C149: 0.8025 | D149: 107.95494 | E149: 128.99573 | F149: 11.96 | G149: 7.6 | H149: 7.6 | I149: 12.34 | J149: 7.59 | U149: -8.4 | V149: 0.71 | X149: 3.1 | Y149: -23.3 | Z149: 1973 | AC149: 185.19 | AD149: 470.42 | AE149: 608.2633 | AF149: 5.5 | AH149: 6.125 | AL149: 159 | BG149: 8.93 | BH149: 40.023226 | BI149: 53.063972 | BN149: 7.59 | BO149: 100.2438 | BP149: 100.5865 | BQ149: 101.5622 | CH149: 1.2 | CI149: -8.2 | CJ149: 7.8
A150: 34731 | B150: 17.23 | C150: 0.788 | D150: 86.323066 | E150: 132.60057 | F150: 11.75 | G150: 7.42 | H150: 7.22 | I150: 12.95 | J150: 7.48 | U150: -8.5 | V150: 0.83 | X150: 3.7 | Y150: -25.8 | Z150: 2038 | AC150: 185.03 | AD150: 487.39 | AE150: 616.07413 | AF150: 6 | AH150: 6.625 | AL150: 159.4 | BG150: 8.75 | BH150: 38.488533 | BI150: 53.063972 | BN150: 7.48 | BO150: 99.92568 | BP150: 100.7774 | BQ150: 101.439 | CH150: 1.5 | CI150: -12.5 | CJ150: 7
A151: 34759 | B151: 17.98 | C151: 0.7505 | D151: 78.096621 | E151: 114.96805 | F151: 13.37 | G151: 7.28 | H151: 7.2 | I151: 13.5 | J151: 7.37 | U151: -8.8 | V151: 0.75 | X151: 2 | Y151: -27.2 | Z151: 2209 | AC151: 178.52 | AD151: 500.71 | AE151: 644.67374 | AF151: 6 | AH151: 6.625 | AL151: 159.9 | BG151: 8.69 | BH151: 31.65565 | BI151: 53.063972 | BN151: 7.37 | BO151: 99.57864 | BP151: 100.9632 | BQ151: 101.2959 | CH151: 2 | CI151: -12.6 | CJ151: 4.7
A152: 34790 | B152: 18.98 | C152: 0.754 | D152: 65.991783 | E152: 89.536835 | F152: 11.75 | G152: 7.09 | H152: 7.07 | I152: 13.1 | J152: 7.1 | U152: -8.3 | V152: 0.69 | W152: 19.6 | X152: 1 | Y152: -27.8 | Z152: 2347 | AC152: 189.18 | AD152: 514.71 | AE152: 666.04261 | AF152: 6 | AH152: 6.625 | AL152: 160.4 | BG152: 8.58 | BH152: 35.362726 | BI152: 53.643622 | BN152: 7.1 | BO152: 99.2558 | BP152: 101.1321 | BQ152: 101.1533 | CH152: 1 | CI152: -11.1 | CJ152: 10.4
A153: 34820 | B153: 17.58 | C153: 0.7655 | D153: 74.70236 | E153: 72.165709 | F153: 12.85 | G153: 6.86 | H153: 6.3 | I153: 12.27 | J153: 6.72 | U153: -7.5 | V153: 0.63 | W153: 19 | X153: -0.2 | Y153: -28.8 | Z153: 2096 | AC153: 195.82 | AD153: 533.4 | AE153: 670.63462 | AF153: 6 | AH153: 6.625 | AL153: 160.7 | BG153: 7.96 | BH153: 60.576293 | BI153: 53.643622 | BN153: 6.72 | BO153: 99.00072 | BP153: 101.2752 | BQ153: 101.0322 | CH153: 0.2 | CI153: -6.9 | CJ153: 10.9
...

Sheet maandcijfers
B1: oliepr | C1: dollar | D1: Beleidsonzekerheid VS | E1: Beleidsonzekerheid EU | F1: Volatiliteit US S&P500 | G1: lange rente Duitsland | H1: lange rente VS | I1: lange rente Italie | J1: lange rente Nederland | K1: HICP eurogebied, totaal | L1: HICP eurogebied, voeding, alc. en tabak | M1: HICP eurogebied, energie | N1: HICP eurogebied, totaal, excl. energie, voeding en tabak | O1: import volume eurogebied (WTM) | P1: export volume eurogebied (WTM) | Q1: PMI samengesteld eurozone | R1: PMI industrie eurozone | S1: PMI diensten eurozone | T1: PMI bouw eurozone | U1: consumentenvertrouwen eurozone | V1: ondernemersvertrouwen eurozone | W1: dienstensector vertrouwenindicator eurozone | X1: industrie vertrouwenindicator eurozone | Y1: bouwsector vertrouwenindicator eurozone | Z1: Baltic Dry Index | AA1: Harpex index | AB1: Global Container Freight Index | AC1: beurs_aex | AD1: SP_500 | AE1: MSCI World | AF1: US Federal funds rate | AG1: ECB Deposit rate | AH1: United Kingdom Bank Rate | AI1: Japan key policy rate | AJ1: PBOC Medium-term Lending Facility | AK1: CPI Verenigde Staten | AL1: CPI excl voedsel en energie VS | AM1: PMI samengesteld Duitsland | AN1: PMI industrie Duitsland | AO1: PMI samengesteld Frankrijk | AP1: PMI industrie Frankrijk | AQ1: PMI samengesteld VS | AR1: PMI industrie VS | AS1: PMI samengesteld VK | AT1: PMI industrie VK | AU1: PMI samengesteld China | AV1: PMI industrie China | AW1: PMI samengesteld India | AX1: PMI industrie India | AY1: PMI samengesteld Wereld | AZ1: PMI industrie Wereld | BA1: PMI samengesteld Japan | BB1: PMI industrie Japan | BC1: Global Supply chain pressure index | BD1: Wereldhandel (WTM) | BE1: Container throughput - Wereld | BF1: Container throughput - Noordwest-Europa | BG1: US Corporate Long-term bond yield | BH1: Trade Policy Uncertainty | BI1: Looncompensatie per uur - eurozone | BJ1: Loonkosten index (op uurbasis)- eurozone | BK1: Gas futures | BL1: PMI industrie - Nederland | BM1: EURIBOR | BN1: interest NL 10yr | BO1: CLI - VS | BP1: CLI - CHN | BQ1: CLI -EU | BR1: HWWI index | BS1: HWWI excl Energy index | BT1: HWWI Industrial Raw Materials index | BU1: HWWI Energy raw materials | BV1: HWWI Food index | BW1: Wereld uitvoer | BX1: Wereld Invoer | BY1: Eurozone extra-EA20 invoer | BZ1: Eurozone extra-EA20 uitvoer | CA1: Eurozone intra-EA20 invoer | CB1: Eurozone intra-EA20 uitvoer | CC1: NL - leenkosten NFC's | CD1: NL- leenkosten KT | CE1: NL- leenkosten LT | CF1: NL - Hypotheekrente
A2: 30317 | B2: =IF(Downloads_maandcijfers!B5="", "", Downloads_maandcijfers!B5) | C2: =IF(Downloads_maandcijfers!C5="", "", Downloads_maandcijfers!C5) -> 1.0662 | D2: =IF(Downloads_maandcijfers!D5="", "", Downloads_maandcijfers!D5) | E2: =IF(Downloads_maandcijfers!E5="", "", Downloads_maandcijfers!E5) | F2: =IF(Downloads_maandcijfers!F5="", "", Downloads_maandcijfers!F5) | G2: =IF(Downloads_maandcijfers!G5="", "", Downloads_maandcijfers!G5) -> 7.71 | H2: =IF(Downloads_maandcijfers!H5="", "", Downloads_maandcijfers!H5) -> 10.8 | I2: =IF(Downloads_maandcijfers!I5="", "", Downloads_maandcijfers!I5) | ... AB2: =IF(Downloads_maandcijfers!AB5="", "", Downloads_maandcijfers!AB5) | AC2: 48.37 | AD2: =IF(Downloads_maandcijfers!AD5="", "", Downloads_maandcijfers!AD5) -> 145.3 | AE2: =IF(Downloads_maandcijfers!AE5="", "", Downloads_maandcijfers!AE5) -> 158.0337 | AF2: =IF(Downloads_maandcijfers!AF5="", "", Downloads_maandcijfers!AF5) -> 8.5 | AG2: =IF(Downloads_maandcijfers!AG5="", "", Downloads_maandcijfers!AG5) | AH2: =IF(Downloads_maandcijfers!AH5="", "", Downloads_maandcijfers!AH5) -> 11 | AI2: =IF(Downloads_maandcijfers!AI5="", "", Downloads_maandcijfers!AI5) | AJ2: =IF(Downloads_maandcijfers!AJ5="", "", Downloads_maandcijfers!AJ5) | AK2: =IF(Downloads_maandcijfers!AK5="", "", Downloads_maandcijfers!AK5) | ... CF2: =IF(Downloads_maandcijfers!CF5="", "", Downloads_maandcijfers!CF5)
A3: 30348 | B3: =IF(Downloads_maandcijfers!B6="", "", Downloads_maandcijfers!B6) | C3: =IF(Downloads_maandcijfers!C6="", "", Downloads_maandcijfers!C6) -> 1.0593 | D3: =IF(Downloads_maandcijfers!D6="", "", Downloads_maandcijfers!D6) | E3: =IF(Downloads_maandcijfers!E6="", "", Downloads_maandcijfers!E6) | F3: =IF(Downloads_maandcijfers!F6="", "", Downloads_maandcijfers!F6) | G3: =IF(Downloads_maandcijfers!G6="", "", Downloads_maandcijfers!G6) -> 7.71 | H3: =IF(Downloads_maandcijfers!H6="", "", Downloads_maandcijfers!H6) -> 10.27 | I3: =IF(Downloads_maandcijfers!I6="", "", Downloads_maandcijfers!I6) | ... AB3: =IF(Downloads_maandcijfers!AB6="", "", Downloads_maandcijfers!AB6) | AC3: 51.26 | AD3: =IF(Downloads_maandcijfers!AD6="", "", Downloads_maandcijfers!AD6) -> 148.06 | AE3: =IF(Downloads_maandcijfers!AE6="", "", Downloads_maandcijfers!AE6) -> 160.9138 | AF3: =IF(Downloads_maandcijfers!AF6="", "", Downloads_maandcijfers!AF6) -> 8.5 | AG3: =IF(Downloads_maandcijfers!AG6="", "", Downloads_maandcijfers!AG6) | AH3: =IF(Downloads_maandcijfers!AH6="", "", Downloads_maandcijfers!AH6) -> 11 | AI3: =IF(Downloads_maandcijfers!AI6="", "", Downloads_maandcijfers!AI6) | AJ3: =IF(Downloads_maandcijfers!AJ6="", "", Downloads_maandcijfers!AJ6) | AK3: =IF(Downloads_maandcijfers!AK6="", "", Downloads_maandcijfers!AK6) | ... CF3: =IF(Downloads_maandcijfers!CF6="", "", Downloads_maandcijfers!CF6)
A4: 30376 | B4: =IF(Downloads_maandcijfers!B7="", "", Downloads_maandcijfers!B7) | C4: =IF(Downloads_maandcijfers!C7="", "", Downloads_maandcijfers!C7) -> 1.0825 | D4: =IF(Downloads_maandcijfers!D7="", "", Downloads_maandcijfers!D7) | E4: =IF(Downloads_maandcijfers!E7="", "", Downloads_maandcijfers!E7) | F4: =IF(Downloads_maandcijfers!F7="", "", Downloads_maandcijfers!F7) | G4: =IF(Downloads_maandcijfers!G7="", "", Downloads_maandcijfers!G7) -> 7.42 | H4: =IF(Downloads_maandcijfers!H7="", "", Downloads_maandcijfers!H7) -> 10.62 | I4: =IF(Downloads_maandcijfers!I7="", "", Downloads_maandcijfers!I7) | ... AB4: =IF(Downloads_maandcijfers!AB7="", "", Downloads_maandcijfers!AB7) | AC4: 60.24 | AD4: =IF(Downloads_maandcijfers!AD7="", "", Downloads_maandcijfers!AD7) -> 152.96 | AE4: =IF(Downloads_maandcijfers!AE7="", "", Downloads_maandcijfers!AE7) -> 166.1387 | AF4: =IF(Downloads_maandcijfers!AF7="", "", Downloads_maandcijfers!AF7) -> 8.625 | AG4: =IF(Downloads_maandcijfers!AG7="", "", Downloads_maandcijfers!AG7) | AH4: =IF(Downloads_maandcijfers!AH7="", "", Downloads_maandcijfers!AH7) -> 10.5625 | AI4: =IF(Downloads_maandcijfers!AI7="", "", Downloads_maandcijfers!AI7) | AJ4: =IF(Downloads_maandcijfers!AJ7="", "", Downloads_maandcijfers!AJ7) | AK4: =IF(Downloads_maandcijfers!AK7="", "", Downloads_maandcijfers!AK7) | ... CF4: =IF(Downloads_maandcijfers!CF7="", "", Downloads_maandcijfers!CF7)
A5: 30407 | B5: =IF(Downloads_maandcijfers!B8="", "", Downloads_maandcijfers!B8) | C5: =IF(Downloads_maandcijfers!C8="", "", Downloads_maandcijfers!C8) -> 1.0857 | D5: =IF(Downloads_maandcijfers!D8="", "", Downloads_maandcijfers!D8) | E5: =IF(Downloads_maandcijfers!E8="", "", Downloads_maandcijfers!E8) | F5: =IF(Downloads_maandcijfers!F8="", "", Downloads_maandcijfers!F8) | G5: =IF(Downloads_maandcijfers!G8="", "", Downloads_maandcijfers!G8) -> 7.51 | H5: =IF(Downloads_maandcijfers!H8="", "", Downloads_maandcijfers!H8) -> 10.27 | I5: =IF(Downloads_maandcijfers!I8="", "", Downloads_maandcijfers!I8) | ... AB5: =IF(Downloads_maandcijfers!AB8="", "", Downloads_maandcijfers!AB8) | AC5: 57.2 | AD5: =IF(Downloads_maandcijfers!AD8="", "", Downloads_maandcijfers!AD8) -> 164.42 | AE5: =IF(Downloads_maandcijfers!AE8="", "", Downloads_maandcijfers!AE8) -> 177.5606 | AF5: =IF(Downloads_maandcijfers!AF8="", "", Downloads_maandcijfers!AF8) -> 8.625 | AG5: =IF(Downloads_maandcijfers!AG8="", "", Downloads_maandcijfers!AG8) | AH5: =IF(Downloads_maandcijfers!AH8="", "", Downloads_maandcijfers!AH8) -> 10.0625 | AI5: =IF(Downloads_maandcijfers!AI8="", "", Downloads_maandcijfers!AI8) | AJ5: =IF(Downloads_maandcijfers!AJ8="", "", Downloads_maandcijfers!AJ8) | AK5: =IF(Downloads_maandcijfers!AK8="", "", Downloads_maandcijfers!AK8) | ... CF5: =IF(Downloads_maandcijfers!CF8="", "", Downloads_maandcijfers!CF8)
A6: 30437 | B6: =IF(Downloads_maandcijfers!B9="", "", Downloads_maandcijfers!B9) | C6: =IF(Downloads_maandcijfers!C9="", "", Downloads_maandcijfers!C9) -> 1.1038 | D6: =IF(Downloads_maandcijfers!D9="", "", Downloads_maandcijfers!D9) | E6: =IF(Downloads_maandcijfers!E9="", "", Downloads_maandcijfers!E9) | F6: =IF(Downloads_maandcijfers!F9="", "", Downloads_maandcijfers!F9) | G6: =IF(Downloads_maandcijfers!G9="", "", Downloads_maandcijfers!G9) -> 7.69 | H6: =IF(Downloads_maandcijfers!H9="", "", Downloads_maandcijfers!H9) -> 10.81 | I6: =IF(Downloads_maandcijfers!I9="", "", Downloads_maandcijfers!I9) | ... AB6: =IF(Downloads_maandcijfers!AB9="", "", Downloads_maandcijfers!AB9) | AC6: 57.24 | AD6: =IF(Downloads_maandcijfers!AD9="", "", Downloads_maandcijfers!AD9) -> 162.39 | AE6: =IF(Downloads_maandcijfers!AE9="", "", Downloads_maandcijfers!AE9) -> 175.3825 | AF6: =IF(Downloads_maandcijfers!AF9="", "", Downloads_maandcijfers!AF9) -> 8.75 | AG6: =IF(Downloads_maandcijfers!AG9="", "", Downloads_maandcijfers!AG9) | AH6: =IF(Downloads_maandcijfers!AH9="", "", Downloads_maandcijfers!AH9) -> 10.0625 | AI6: =IF(Downloads_maandcijfers!AI9="", "", Downloads_maandcijfers!AI9) | AJ6: =IF(Downloads_maandcijfers!AJ9="", "", Downloads_maandcijfers!AJ9) | AK6: =IF(Downloads_maandcijfers!AK9="", "", Downloads_maandcijfers!AK9) | ... CF6: =IF(Downloads_maandcijfers!CF9="", "", Downloads_maandcijfers!CF9)
A7: 30468 | B7: =IF(Downloads_maandcijfers!B10="", "", Downloads_maandcijfers!B10) | C7: =IF(Downloads_maandcijfers!C10="", "", Downloads_maandcijfers!C10) -> 1.1214 | D7: =IF(Downloads_maandcijfers!D10="", "", Downloads_maandcijfers!D10) | E7: =IF(Downloads_maandcijfers!E10="", "", Downloads_maandcijfers!E10) | F7: =IF(Downloads_maandcijfers!F10="", "", Downloads_maandcijfers!F10) | G7: =IF(Downloads_maandcijfers!G10="", "", Downloads_maandcijfers!G10) -> 8.11 | H7: =IF(Downloads_maandcijfers!H10="", "", Downloads_maandcijfers!H10) -> 10.96 | I7: =IF(Downloads_maandcijfers!I10="", "", Downloads_maandcijfers!I10) | ... AB7: =IF(Downloads_maandcijfers!AB10="", "", Downloads_maandcijfers!AB10) | AC7: 64.01 | AD7: =IF(Downloads_maandcijfers!AD10="", "", Downloads_maandcijfers!AD10) -> 168.11 | AE7: =IF(Downloads_maandcijfers!AE10="", "", Downloads_maandcijfers!AE10) -> 180.4522 | AF7: =IF(Downloads_maandcijfers!AF10="", "", Downloads_maandcijfers!AF10) -> 9 | AG7: =IF(Downloads_maandcijfers!AG10="", "", Downloads_maandcijfers!AG10) | AH7: =IF(Downloads_maandcijfers!AH10="", "", Downloads_maandcijfers!AH10) -> 9.5625 | AI7: =IF(Downloads_maandcijfers!AI10="", "", Downloads_maandcijfers!AI10) | AJ7: =IF(Downloads_maandcijfers!AJ10="", "", Downloads_maandcijfers!AJ10) | AK7: =IF(Downloads_maandcijfers!AK10="", "", Downloads_maandcijfers!AK10) | ... CF7: =IF(Downloads_maandcijfers!CF10="", "", Downloads_maandcijfers!CF10)
A8: 30498 | B8: =IF(Downloads_maandcijfers!B11="", "", Downloads_maandcijfers!B11) | C8: =IF(Downloads_maandcijfers!C11="", "", Downloads_maandcijfers!C11) -> 1.1599 | D8: =IF(Downloads_maandcijfers!D11="", "", Downloads_maandcijfers!D11) | E8: =IF(Downloads_maandcijfers!E11="", "", Downloads_maandcijfers!E11) | F8: =IF(Downloads_maandcijfers!F11="", "", Downloads_maandcijfers!F11) | G8: =IF(Downloads_maandcijfers!G11="", "", Downloads_maandcijfers!G11) -> 8.24 | H8: =IF(Downloads_maandcijfers!H11="", "", Downloads_maandcijfers!H11) -> 11.76 | I8: =IF(Downloads_maandcijfers!I11="", "", Downloads_maandcijfers!I11) | ... AB8: =IF(Downloads_maandcijfers!AB11="", "", Downloads_maandcijfers!AB11) | AC8: 66.06 | AD8: =IF(Downloads_maandcijfers!AD11="", "", Downloads_maandcijfers!AD11) -> 162.56 | AE8: =IF(Downloads_maandcijfers!AE11="", "", Downloads_maandcijfers!AE11) -> 176.796 | AF8: =IF(Downloads_maandcijfers!AF11="", "", Downloads_maandcijfers!AF11) -> 9.4375 | AG8: =IF(Downloads_maandcijfers!AG11="", "", Downloads_maandcijfers!AG11) | AH8: =IF(Downloads_maandcijfers!AH11="", "", Downloads_maandcijfers!AH11) -> 9.5625 | AI8: =IF(Downloads_maandcijfers!AI11="", "", Downloads_maandcijfers!AI11) | AJ8: =IF(Downloads_maandcijfers!AJ11="", "", Downloads_maandcijfers!AJ11) | AK8: =IF(Downloads_maandcijfers!AK11="", "", Downloads_maandcijfers!AK11) | ... CF8: =IF(Downloads_maandcijfers!CF11="", "", Downloads_maandcijfers!CF11)
A9: 30529 | B9: =IF(Downloads_maandcijfers!B12="", "", Downloads_maandcijfers!B12) | C9: =IF(Downloads_maandcijfers!C12="", "", Downloads_maandcijfers!C12) -> 1.1868 | D9: =IF(Downloads_maandcijfers!D12="", "", Downloads_maandcijfers!D12) | E9: =IF(Downloads_maandcijfers!E12="", "", Downloads_maandcijfers!E12) | F9: =IF(Downloads_maandcijfers!F12="", "", Downloads_maandcijfers!F12) | G9: =IF(Downloads_maandcijfers!G12="", "", Downloads_maandcijfers!G12) -> 8.37 | H9: =IF(Downloads_maandcijfers!H12="", "", Downloads_maandcijfers!H12) -> 11.98 | I9: =IF(Downloads_maandcijfers!I12="", "", Downloads_maandcijfers!I12) | ... AB9: =IF(Downloads_maandcijfers!AB12="", "", Downloads_maandcijfers!AB12) | AC9: 63.79 | AD9: =IF(Downloads_maandcijfers!AD12="", "", Downloads_maandcijfers!AD12) -> 164.4 | AE9: =IF(Downloads_maandcijfers!AE12="", "", Downloads_maandcijfers!AE12) -> 177.3121 | AF9: =IF(Downloads_maandcijfers!AF12="", "", Downloads_maandcijfers!AF12) -> 9.5 | AG9: =IF(Downloads_maandcijfers!AG12="", "", Downloads_maandcijfers!AG12) | AH9: =IF(Downloads_maandcijfers!AH12="", "", Downloads_maandcijfers!AH12) -> 9.5625 | AI9: =IF(Downloads_maandcijfers!AI12="", "", Downloads_maandcijfers!AI12) | AJ9: =IF(Downloads_maandcijfers!AJ12="", "", Downloads_maandcijfers!AJ12) | AK9: =IF(Downloads_maandcijfers!AK12="", "", Downloads_maandcijfers!AK12) | ... CF9: =IF(Downloads_maandcijfers!CF12="", "", Downloads_maandcijfers!CF12)
A10: 30560 | B10: =IF(Downloads_maandcijfers!B13="", "", Downloads_maandcijfers!B13) | C10: =IF(Downloads_maandcijfers!C13="", "", Downloads_maandcijfers!C13) -> 1.1636 | D10: =IF(Downloads_maandcijfers!D13="", "", Downloads_maandcijfers!D13) | E10: =IF(Downloads_maandcijfers!E13="", "", Downloads_maandcijfers!E13) | F10: =IF(Downloads_maandcijfers!F13="", "", Downloads_maandcijfers!F13) | G10: =IF(Downloads_maandcijfers!G13="", "", Downloads_maandcijfers!G13) -> 8.48 | H10: =IF(Downloads_maandcijfers!H13="", "", Downloads_maandcijfers!H13) -> 11.44 | I10: =IF(Downloads_maandcijfers!I13="", "", Downloads_maandcijfers!I13) | ... AB10: =IF(Downloads_maandcijfers!AB13="", "", Downloads_maandcijfers!AB13) | AC10: 66.96 | AD10: =IF(Downloads_maandcijfers!AD13="", "", Downloads_maandcijfers!AD13) -> 166.07 | AE10: =IF(Downloads_maandcijfers!AE13="", "", Downloads_maandcijfers!AE13) -> 180.4669 | AF10: =IF(Downloads_maandcijfers!AF13="", "", Downloads_maandcijfers!AF13) -> 9.375 | AG10: =IF(Downloads_maandcijfers!AG13="", "", Downloads_maandcijfers!AG13) | AH10: =IF(Downloads_maandcijfers!AH13="", "", Downloads_maandcijfers!AH13) -> 9.5625 | AI10: =IF(Downloads_maandcijfers!AI13="", "", Downloads_maandcijfers!AI13) | AJ10: =IF(Downloads_maandcijfers!AJ13="", "", Downloads_maandcijfers!AJ13) | AK10: =IF(Downloads_maandcijfers!AK13="", "", Downloads_maandcijfers!AK13) | ... CF10: =IF(Downloads_maandcijfers!CF13="", "", Downloads_maandcijfers!CF13)
A11: 30590 | B11: =IF(Downloads_maandcijfers!B14="", "", Downloads_maandcijfers!B14) | C11: =IF(Downloads_maandcijfers!C14="", "", Downloads_maandcijfers!C14) -> 1.1641 | D11: =IF(Downloads_maandcijfers!D14="", "", Downloads_maandcijfers!D14) | E11: =IF(Downloads_maandcijfers!E14="", "", Downloads_maandcijfers!E14) | F11: =IF(Downloads_maandcijfers!F14="", "", Downloads_maandcijfers!F14) | G11: =IF(Downloads_maandcijfers!G14="", "", Downloads_maandcijfers!G14) -> 8.26 | H11: =IF(Downloads_maandcijfers!H14="", "", Downloads_maandcijfers!H14) -> 11.74 | I11: =IF(Downloads_maandcijfers!I14="", "", Downloads_maandcijfers!I14) | ... AB11: =IF(Downloads_maandcijfers!AB14="", "", Downloads_maandcijfers!AB14) | AC11: 64.14 | AD11: =IF(Downloads_maandcijfers!AD14="", "", Downloads_maandcijfers!AD14) -> 163.55 | AE11: =IF(Downloads_maandcijfers!AE14="", "", Downloads_maandcijfers!AE14) -> 177.9077 | AF11: =IF(Downloads_maandcijfers!AF14="", "", Downloads_maandcijfers!AF14) -> 9.375 | AG11: =IF(Downloads_maandcijfers!AG14="", "", Downloads_maandcijfers!AG14) | AH11: =IF(Downloads_maandcijfers!AH14="", "", Downloads_maandcijfers!AH14) -> 9.0625 | AI11: =IF(Downloads_maandcijfers!AI14="", "", Downloads_maandcijfers!AI14) | AJ11: =IF(Downloads_maandcijfers!AJ14="", "", Downloads_maandcijfers!AJ14) | AK11: =IF(Downloads_maandcijfers!AK14="", "", Downloads_maandcijfers!AK14) | ... CF11: =IF(Downloads_maandcijfers!CF14="", "", Downloads_maandcijfers!CF14)
A12: 30621 | B12: =IF(Downloads_maandcijfers!B15="", "", Downloads_maandcijfers!B15) | C12: =IF(Downloads_maandcijfers!C15="", "", Downloads_maandcijfers!C15) -> 1.1928 | D12: =IF(Downloads_maandcijfers!D15="", "", Downloads_maandcijfers!D15) | E12: =IF(Downloads_maandcijfers!E15="", "", Downloads_maandcijfers!E15) | F12: =IF(Downloads_maandcijfers!F15="", "", Downloads_maandcijfers!F15) | G12: =IF(Downloads_maandcijfers!G15="", "", Downloads_maandcijfers!G15) -> 8.31 | H12: =IF(Downloads_maandcijfers!H15="", "", Downloads_maandcijfers!H15) -> 11.63 | I12: =IF(Downloads_maandcijfers!I15="", "", Downloads_maandcijfers!I15) | ... AB12: =IF(Downloads_maandcijfers!AB15="", "", Downloads_maandcijfers!AB15) | AC12: 69.45 | AD12: =IF(Downloads_maandcijfers!AD15="", "", Downloads_maandcijfers!AD15) -> 166.4 | AE12: =IF(Downloads_maandcijfers!AE15="", "", Downloads_maandcijfers!AE15) -> 182.0605 | AF12: =IF(Downloads_maandcijfers!AF15="", "", Downloads_maandcijfers!AF15) -> 9.375 | AG12: =IF(Downloads_maandcijfers!AG15="", "", Downloads_maandcijfers!AG15) | AH12: =IF(Downloads_maandcijfers!AH15="", "", Downloads_maandcijfers!AH15) -> 9.0625 | AI12: =IF(Downloads_maandcijfers!AI15="", "", Downloads_maandcijfers!AI15) | AJ12: =IF(Downloads_maandcijfers!AJ15="", "", Downloads_maandcijfers!AJ15) | AK12: =IF(Downloads_maandcijfers!AK15="", "", Downloads_maandcijfers!AK15) | ... CF12: =IF(Downloads_maandcijfers!CF15="", "", Downloads_maandcijfers!CF15)
A13: 30651 | B13: =IF(Downloads_maandcijfers!B16="", "", Downloads_maandcijfers!B16) | C13: =IF(Downloads_maandcijfers!C16="", "", Downloads_maandcijfers!C16) -> 1.2086 | D13: =IF(Downloads_maandcijfers!D16="", "", Downloads_maandcijfers!D16) | E13: =IF(Downloads_maandcijfers!E16="", "", Downloads_maandcijfers!E16) | F13: =IF(Downloads_maandcijfers!F16="", "", Downloads_maandcijfers!F16) | G13: =IF(Downloads_maandcijfers!G16="", "", Downloads_maandcijfers!G16) -> 8.41 | H13: =IF(Downloads_maandcijfers!H16="", "", Downloads_maandcijfers!H16) -> 11.82 | I13: =IF(Downloads_maandcijfers!I16="", "", Downloads_maandcijfers!I16) | ... AB13: =IF(Downloads_maandcijfers!AB16="", "", Downloads_maandcijfers!AB16) | AC13: 73.22 | AD13: =IF(Downloads_maandcijfers!AD16="", "", Downloads_maandcijfers!AD16) -> 164.93 | AE13: =IF(Downloads_maandcijfers!AE16="", "", Downloads_maandcijfers!AE16) -> 183.952 | AF13: =IF(Downloads_maandcijfers!AF16="", "", Downloads_maandcijfers!AF16) -> 9.375 | AG13: =IF(Downloads_maandcijfers!AG16="", "", Downloads_maandcijfers!AG16) | AH13: =IF(Downloads_maandcijfers!AH16="", "", Downloads_maandcijfers!AH16) -> 9.0625 | AI13: =IF(Downloads_maandcijfers!AI16="", "", Downloads_maandcijfers!AI16) | AJ13: =IF(Downloads_maandcijfers!AJ16="", "", Downloads_maandcijfers!AJ16) | AK13: =IF(Downloads_maandcijfers!AK16="", "", Downloads_maandcijfers!AK16) | ... CF13: =IF(Downloads_maandcijfers!CF16="", "", Downloads_maandcijfers!CF16)
... A37: 31382 | B37: =IF(Downloads_maandcijfers!B40="", "", Downloads_maandcijfers!B40) | C37: =IF(Downloads_maandcijfers!C40="", "", Downloads_maandcijfers!C40) -> 1.1262 | D37: =IF(Downloads_maandcijfers!D40="", "", Downloads_maandcijfers!D40) -> 133.24392 | E37: =IF(Downloads_maandcijfers!E40="", "", Downloads_maandcijfers!E40) | F37: =IF(Downloads_maandcijfers!F40="", "", Downloads_maandcijfers!F40) | G37: =IF(Downloads_maandcijfers!G40="", "", Downloads_maandcijfers!G40) -> 6.45 | H37: =IF(Downloads_maandcijfers!H40="", "", Downloads_maandcijfers!H40) -> 9 | I37: =IF(Downloads_maandcijfers!I40="", "", Downloads_maandcijfers!I40) | ... AB37: =IF(Downloads_maandcijfers!AB40="", "", Downloads_maandcijfers!AB40) | AC37: 121.5 | AD37: =IF(Downloads_maandcijfers!AD40="", "", Downloads_maandcijfers!AD40) -> 211.28 | AE37: =IF(Downloads_maandcijfers!AE40="", "", Downloads_maandcijfers!AE40) -> 256.5141 | AF37: =IF(Downloads_maandcijfers!AF40="", "", Downloads_maandcijfers!AF40) -> 7.75 | AG37: =IF(Downloads_maandcijfers!AG40="", "", Downloads_maandcijfers!AG40) | AH37: =IF(Downloads_maandcijfers!AH40="", "", Downloads_maandcijfers!AH40) -> 11.375 | AI37: =IF(Downloads_maandcijfers!AI40="", "", Downloads_maandcijfers!AI40) | AJ37: =IF(Downloads_maandcijfers!AJ40="", "", Downloads_maandcijfers!AJ40) | AK37: =IF(Downloads_maandcijfers!AK40="", "", Downloads_maandcijfers!AK40) | ... CF37: =IF(Downloads_maandcijfers!CF40="", "", Downloads_maandcijfers!CF40)
A38: 31413 | B38: =IF(Downloads_maandcijfers!B41="", "", Downloads_maandcijfers!B41) | C38: =IF(Downloads_maandcijfers!C41="", "", Downloads_maandcijfers!C41) -> 1.1022 | D38: =IF(Downloads_maandcijfers!D41="", "", Downloads_maandcijfers!D41) -> 155.93292 | E38: =IF(Downloads_maandcijfers!E41="", "", Downloads_maandcijfers!E41) | F38: =IF(Downloads_maandcijfers!F41="", "", Downloads_maandcijfers!F41) | G38: =IF(Downloads_maandcijfers!G41="", "", Downloads_maandcijfers!G41) -> 6.31 | H38: =IF(Downloads_maandcijfers!H41="", "", Downloads_maandcijfers!H41) -> 9.08 | I38: =IF(Downloads_maandcijfers!I41="", "", Downloads_maandcijfers!I41) | ... CF38: =IF(Downloads_maandcijfers!CF41="", "", Downloads_maandcijfers!CF41)
A39: 31444 | B39: =IF(Downloads_maandcijfers!B42="", "", Downloads_maandcijfers!B42) | C39: =IF(Downloads_maandcijfers!C42="", "", Downloads_maandcijfers!C42) -> 1.0425 | D39: =IF(Downloads_maandcijfers!D42="", "", Downloads_maandcijfers!D42) -> 159.46768 | E39: =IF(Downloads_maandcijfers!E42="", "", Downloads_maandcijfers!E42) | F39: =IF(Downloads_maandcijfers!F42="", "", Downloads_maandcijfers!F42) | G39: =IF(Downloads_maandcijfers!G42="", "", Downloads_maandcijfers!G42) -> 6.23 | H39: =IF(Downloads_maandcijfers!H42="", "", Downloads_maandcijfers!H42) -> 8.13 | I39: =IF(Downloads_maandcijfers!I42="", "", Downloads_maandcijfers!I42) | ... CF39: =IF(Downloads_maandcijfers!CF42="", "", Downloads_maandcijfers!CF42)
A40: 31472 | B40: =IF(Downloads_maandcijfers!B43="", "", Downloads_maandcijfers!B43) | C40: =IF(Downloads_maandcijfers!C43="", "", Downloads_maandcijfers!C43) -> 1.0652 | D40: =IF(Downloads_maandcijfers!D43="", "", Downloads_maandcijfers!D43) -> 160.1981 | E40: =IF(Downloads_maandcijfers!E43="", "", Downloads_maandcijfers!E43) | F40: =IF(Downloads_maandcijfers!F43="", "", Downloads_maandcijfers!F43) | G40: =IF(Downloads_maandcijfers!G43="", "", Downloads_maandcijfers!G43) -> 5.75 | H40: =IF(Downloads_maandcijfers!H43="", "", Downloads_maandcijfers!H43) -> 7.39 | I40: =IF(Downloads_maandcijfers!I43="", "", Downloads_maandcijfers!I43) | ... CF40: =IF(Downloads_maandcijfers!CF43="", "", Downloads_maandcijfers!CF43)
A41: 31503 | B41: =IF(Downloads_maandcijfers!B44="", "", Downloads_maandcijfers!B44) | C41: =IF(Downloads_maandcijfers!C44="", "", Downloads_maandcijfers!C44) -> 1.0103 | D41: =IF(Downloads_maandcijfers!D44="", "", Downloads_maandcijfers!D44) -> 150.36626 | E41: =IF(Downloads_maandcijfers!E44="", "", Downloads_maandcijfers!E44) | F41: =IF(Downloads_maandcijfers!F44="", "", Downloads_maandcijfers!F44) | G41: =IF(Downloads_maandcijfers!G44="", "", Downloads_maandcijfers!G44) -> 5.36 | H41: =IF(Downloads_maandcijfers!H44="", "", Downloads_maandcijfers!H44) -> 7.38 | I41: =IF(Downloads_maandcijfers!I44="", "", Downloads_maandcijfers!I44) | ... CF41: =IF(Downloads_maandcijfers!CF44="", "", Downloads_maandcijfers!CF44)
A42: 31533 | B42: =IF(Downloads_maandcijfers!B45="", "", Downloads_maandcijfers!B45) | C42: =IF(Downloads_maandcijfers!C45="", "", Downloads_maandcijfers!C45) -> 1.0747 | D42: =IF(Downloads_maandcijfers!D45="", "", Downloads_maandcijfers!D45) -> 132.63792 | E42: =IF(Downloads_maandcijfers!E45="", "", Downloads_maandcijfers!E45) | F42: =IF(Downloads_maandcijfers!F45="", "", Downloads_maandcijfers!F45) | G42: =IF(Downloads_maandcijfers!G45="", "", Downloads_maandcijfers!G45) -> 5.75 | H42: =IF(Downloads_maandcijfers!H45="", "", Downloads_maandcijfers!H45) -> 8.05 | I42: =IF(Downloads_maandcijfers!I45="", "", Downloads_maandcijfers!I45) | ... CF42: =IF(Downloads_maandcijfers!CF45="", "", Downloads_maandcijfers!CF45)
A43: 31564 | B43: =IF(Downloads_maandcijfers!B46="", "", Downloads_maandcijfers!B46) | C43: =IF(Downloads_maandcijfers!C46="", "", Downloads_maandcijfers!C46) -> 1.0215 | D43: =IF(Downloads_maandcijfers!D46="", "", Downloads_maandcijfers!D46) -> 122.51177 | E43: =IF(Downloads_maandcijfers!E46="", "", Downloads_maandcijfers!E46) | F43: =IF(Downloads_maandcijfers!F46="", "", Downloads_maandcijfers!F46) | G43: =IF(Downloads_maandcijfers!G46="", "", Downloads_maandcijfers!G46) -> 5.87 | H43: =IF(Downloads_maandcijfers!H46="", "", Downloads_maandcijfers!H46) -> 7.35 | I43: =IF(Downloads_maandcijfers!I46="", "", Downloads_maandcijfers!I46) | ... CF43: =IF(Downloads_maandcijfers!CF46="", "", Downloads_maandcijfers!CF46)
A44: 31594 | B44: =IF(Downloads_maandcijfers!B47="", "", Downloads_maandcijfers!B47) | C44: =IF(Downloads_maandcijfers!C47="", "", Downloads_maandcijfers!C47) -> 0.9923 | D44: =IF(Downloads_maandcijfers!D47="", "", Downloads_maandcijfers!D47) -> 132.11963 | E44: =IF(Downloads_maandcijfers!E47="", "", Downloads_maandcijfers!E47) | F44: =IF(Downloads_maandcijfers!F47="", "", Downloads_maandcijfers!F47) | G44: =IF(Downloads_maandcijfers!G47="", "", Downloads_maandcijfers!G47) -> 5.77 | H44: =IF(Downloads_maandcijfers!H47="", "", Downloads_maandcijfers!H47) -> 7.34 | I44: =IF(Downloads_maandcijfers!I47="", "", Downloads_maandcijfers!I47) | ... CF44: =IF(Downloads_maandcijfers!CF47="", "", Downloads_maandcijfers!CF47)
A45: 31625 | B45: =IF(Downloads_maandcijfers!B48="", "", Downloads_maandcijfers!B48) | C45: =IF(Downloads_maandcijfers!C48="", "", Downloads_maandcijfers!C48) -> 0.9711 | D45: =IF(Downloads_maandcijfers!D48="", "", Downloads_maandcijfers!D48) -> 127.5525 | E45: =IF(Downloads_maandcijfers!E48="", "", Downloads_maandcijfers!E48) | F45: =IF(Downloads_maandcijfers!F48="", "", Downloads_maandcijfers!F48) | G45: =IF(Downloads_maandcijfers!G48="", "", Downloads_maandcijfers!G48) -> 5.6 | H45: =IF(Downloads_maandcijfers!H48="", "", Downloads_maandcijfers!H48) -> 6.95 | I45: =IF(Downloads_maandcijfers!I48="", "", Downloads_maandcijfers!I48) | ... CF45: =IF(Downloads_maandcijfers!CF48="", "", Downloads_maandcijfers!CF48)
A46: 31656 | B46: =IF(Downloads_maandcijfers!B49="", "", Downloads_maandcijfers!B49) | C46: =IF(Downloads_maandcijfers!C49="", "", Downloads_maandcijfers!C49) -> 0.9699 | D46: =IF(Downloads_maandcijfers!D49="", "", Downloads_maandcijfers!D49) -> 132.01833 | E46: =IF(Downloads_maandcijfers!E49="", "", Downloads_maandcijfers!E49) | F46: =IF(Downloads_maandcijfers!F49="", "", Downloads_maandcijfers!F49) | G46: =IF(Downloads_maandcijfers!G49="", "", Downloads_maandcijfers!G49) -> 5.82 | H46: =IF(Downloads_maandcijfers!H49="", "", Downloads_maandcijfers!H49) -> 7.45 | I46: =IF(Downloads_maandcijfers!I49="", "", Downloads_maandcijfers!I49) | ... CF46: =IF(Downloads_maandcijfers!CF49="", "", Downloads_maandcijfers!CF49)
A47: 31686 | B47: =IF(Downloads_maandcijfers!B50="", "", Downloads_maandcijfers!B50) | C47: =IF(Downloads_maandcijfers!C50="", "", Downloads_maandcijfers!C50) -> 0.9906 | D47: =IF(Downloads_maandcijfers!D50="", "", Downloads_maandcijfers!D50) -> 111.50926 | E47: =IF(Downloads_maandcijfers!E50="", "", Downloads_maandcijfers!E50) | F47: =IF(Downloads_maandcijfers!F50="", "", Downloads_maandcijfers!F50) | G47: =IF(Downloads_maandcijfers!G50="", "", Downloads_maandcijfers!G50) -> 6.14 | H47: =IF(Downloads_maandcijfers!H50="", "", Downloads_maandcijfers!H50) -> 7.34 | I47: =IF(Downloads_maandcijfers!I50="", "", Downloads_maandcijfers!I50) | ... CF47: =IF(Downloads_maandcijfers!CF50="", "", Downloads_maandcijfers!CF50)
A48: 31717 | B48: =IF(Downloads_maandcijfers!B51="", "", Downloads_maandcijfers!B51) | C48: =IF(Downloads_maandcijfers!C51="", "", Downloads_maandcijfers!C51) -> 0.9504 | D48: =IF(Downloads_maandcijfers!D51="", "", Downloads_maandcijfers!D51) -> 115.02029 | E48: =IF(Downloads_maandcijfers!E51="", "", Downloads_maandcijfers!E51) | F48: =IF(Downloads_maandcijfers!F51="", "", Downloads_maandcijfers!F51) | G48: =IF(Downloads_maandcijfers!G51="", "", Downloads_maandcijfers!G51) -> 6.17 | H48: =IF(Downloads_maandcijfers!H51="", "", Downloads_maandcijfers!H51) -> 7.15 | I48: =IF(Downloads_maandcijfers!I51="", "", Downloads_maandcijfers!I51) | ... CF48: =IF(Downloads_maandcijfers!CF51="", "", Downloads_maandcijfers!CF51)
A49: 31747 | B49: =IF(Downloads_maandcijfers!B52="", "", Downloads_maandcijfers!B52) | C49: =IF(Downloads_maandcijfers!C52="", "", Downloads_maandcijfers!C52) -> 0.9271 | D49: =IF(Downloads_maandcijfers!D52="", "", Downloads_maandcijfers!D52) -> 108.96811 | E49: =IF(Downloads_maandcijfers!E52="", "", Downloads_maandcijfers!E52) | F49: =IF(Downloads_maandcijfers!F52="", "", Downloads_maandcijfers!F52) | G49: =IF(Downloads_maandcijfers!G52="", "", Downloads_maandcijfers!G52) -> 5.96 | H49: =IF(Downloads_maandcijfers!H52="", "", Downloads_maandcijfers!H52) -> 7.23 | I49: =IF(Downloads_maandcijfers!I52="", "", Downloads_maandcijfers!I52) | ... CF49: =IF(Downloads_maandcijfers!CF52="", "", Downloads_maandcijfers!CF52)
... A205: 36495 | B205: =IF(Downloads_maandcijfers!B208="", "", Downloads_maandcijfers!B208) -> 24.93 | C205: =IF(Downloads_maandcijfers!C208="", "", Downloads_maandcijfers!C208) -> 0.9977 | D205: =IF(Downloads_maandcijfers!D208="", "", Downloads_maandcijfers!D208) -> 83.809474 | E205: =IF(Downloads_maandcijfers!E208="", "", Downloads_maandcijfers!E208) -> 65.17728 | F205: =IF(Downloads_maandcijfers!F208="", "", Downloads_maandcijfers!F208) -> 27.41 | G205: =IF(Downloads_maandcijfers!G208="", "", Downloads_maandcijfers!G208) -> 5.15 | H205: =IF(Downloads_maandcijfers!H208="", "", Downloads_maandcijfers!H208) -> 6.45 | I205: =IF(Downloads_maandcijfers!I208="", "", Downloads_maandcijfers!I208) -> 5.61 | ... CF205: =IF(Downloads_maandcijfers!CF208="", "", Downloads_maandcijfers!CF208)
A206: 36526 | B206: =IF(Downloads_maandcijfers!B209="", "", Downloads_maandcijfers!B209) -> 27.08 | C206: =IF(Downloads_maandcijfers!C209="", "", Downloads_maandcijfers!C209) -> 1.0221 | D206: =IF(Downloads_maandcijfers!D209="", "", Downloads_maandcijfers!D209) -> 89.201543 | E206: =IF(Downloads_maandcijfers!E209="", "", Downloads_maandcijfers!E209) -> 51.95106 | F206: =IF(Downloads_maandcijfers!F209="", "", Downloads_maandcijfers!F209) -> 24.95 | G206: =IF(Downloads_maandcijfers!G209="", "", Downloads_maandcijfers!G209) -> 5.54 | H206: =IF(Downloads_maandcijfers!H209="", "", Downloads_maandcijfers!H209) -> 6.68 | I206: =IF(Downloads_maandcijfers!I209="", "", Downloads_maandcijfers!I209) -> 5.78 | ... CF206: =IF(Downloads_maandcijfers!CF209="", "", Downloads_maandcijfers!CF209) | CG206: =IF(Downloads_maandcijfers!CG3668="", "", Downloads_maandcijfers!CG3668) | CH206: =IF(Downloads_maandcijfers!CH3668="", "", Downloads_maandcijfers!CH3668) | CI206: =IF(Downloads_maandcijfers!CI3669=0, "", Downloads_maandcijfers!CI3669) | CJ206: =IF(Downloads_maandcijfers!CJ3669=0, "", Downloads_maandcijfers!CJ3669) | CK206: =IF(Downloads_maandcijfers!CK3669=0, "", Downloads_maandcijfers!CK3669) | CL206: =IF(Downloads_maandcijfers!CL3669=0, "", Downloads_maandcijfers!CL3669) | CM206: =IF(Downloads_maandcijfers!CM3669=0, "", Downloads_maandcijfers!CM3669)
A207: 36557 | B207: =IF(Downloads_maandcijfers!B210="", "", Downloads_maandcijfers!B210) -> 29.01 | C207: =IF(Downloads_maandcijfers!C210="", "", Downloads_maandcijfers!C210) -> 1.0386 | D207: =IF(Downloads_maandcijfers!D210="", "", Downloads_maandcijfers!D210) -> 77.60139 | E207: =IF(Downloads_maandcijfers!E210="", "", Downloads_maandcijfers!E210) -> 72.962877 | F207: =IF(Downloads_maandcijfers!F210="", "", Downloads_maandcijfers!F210) -> 23.37 | G207: =IF(Downloads_maandcijfers!G210="", "", Downloads_maandcijfers!G210) -> 5.51 | H207: =IF(Downloads_maandcijfers!H210="", "", Downloads_maandcijfers!H210) -> 6.42 | I207: =IF(Downloads_maandcijfers!I210="", "", Downloads_maandcijfers!I210) -> 5.76 | ... CF207: =IF(Downloads_maandcijfers!CF210="", "", Downloads_maandcijfers!CF210) | CG207: =IF(Downloads_maandcijfers!CG3669="", "", Downloads_maandcijfers!CG3669) | CH207: =IF(Downloads_maandcijfers!CH3669="", "", Downloads_maandcijfers!CH3669) | CI207: =IF(Downloads_maandcijfers!CI3670=0, "", Downloads_maandcijfers!CI3670) | CJ207: =IF(Downloads_maandcijfers!CJ3670=0, "", Downloads_maandcijfers!CJ3670) | CK207: =IF(Downloads_maandcijfers!CK3670=0, "", Downloads_maandcijfers!CK3670) | CL207: =IF(Downloads_maandcijfers!CL3670=0, "", Downloads_maandcijfers!CL3670) | CM207: =IF(Downloads_maandcijfers!CM3670=0, "", Downloads_maandcijfers!CM3670)
A208: 36586 | B208: =IF(Downloads_maandcijfers!B211="", "", Downloads_maandcijfers!B211) -> 23.98 | C208: =IF(Downloads_maandcijfers!C211="", "", Downloads_maandcijfers!C211) -> 1.0451 | D208: =IF(Downloads_maandcijfers!D211="", "", Downloads_maandcijfers!D211) -> 77.548311 | E208: =IF(Downloads_maandcijfers!E211="", "", Downloads_maandcijfers!E211) -> 75.439555 | F208: =IF(Downloads_maandcijfers!F211="", "", Downloads_maandcijfers!F211) -> 24.11 | G208: =IF(Downloads_maandcijfers!G211="", "", Downloads_maandcijfers!G211) -> 5.33 | H208: =IF(Downloads_maandcijfers!H211="", "", Downloads_maandcijfers!H211) -> 6.03 | I208: =IF(Downloads_maandcijfers!I211="", "", Downloads_maandcijfers!I211) -> 5.5 | ... CF208: =IF(Downloads_maandcijfers!CF211="", "", Downloads_maandcijfers!CF211) | CG208: =IF(Downloads_maandcijfers!CG3670="", "", Downloads_maandcijfers!CG3670) | CH208: =IF(Downloads_maandcijfers!CH3670="", "", Downloads_maandcijfers!CH3670) | CI208: =IF(Downloads_maandcijfers!CI3671=0, "", Downloads_maandcijfers!CI3671) | CJ208: =IF(Downloads_maandcijfers!CJ3671=0, "", Downloads_maandcijfers!CJ3671) | CK208: =IF(Downloads_maandcijfers!CK3671=0, "", Downloads_maandcijfers!CK3671) | CL208: =IF(Downloads_maandcijfers!CL3671=0, "", Downloads_maandcijfers!CL3671) | CM208: =IF(Downloads_maandcijfers!CM3671=0, "", Downloads_maandcijfers!CM3671)
A209: 36617 | B209: =IF(Downloads_maandcijfers!B212="", "", Downloads_maandcijfers!B212) -> 23.79 | C209: =IF(Downloads_maandcijfers!C212="", "", Downloads_maandcijfers!C212) -> 1.0974 | D209: =IF(Downloads_maandcijfers!D212="", "", Downloads_maandcijfers!D212) -> 76.059227 | E209: =IF(Downloads_maandcijfers!E212="", "", Downloads_maandcijfers!E212) -> 72.6052 | F209: =IF(Downloads_maandcijfers!F212="", "", Downloads_maandcijfers!F212) -> 26.2 | G209: =IF(Downloads_maandcijfers!G212="", "", Downloads_maandcijfers!G212) -> 5.22 | H209: =IF(Downloads_maandcijfers!H212="", "", Downloads_maandcijfers!H212) -> 6.23 | I209: =IF(Downloads_maandcijfers!I212="", "", Downloads_maandcijfers!I212) -> 5.57 | ... CF209: =IF(Downloads_maandcijfers!CF212="", "", Downloads_maandcijfers!CF212) | CG209: =IF(Downloads_maandcijfers!CG3671="", "", Downloads_maandcijfers!CG3671) | CH209: =IF(Downloads_maandcijfers!CH3671="", "", Downloads_maandcijfers!CH3671) | CI209: =IF(Downloads_maandcijfers!CI3672=0, "", Downloads_maandcijfers!CI3672) | CJ209: =IF(Downloads_maandcijfers!CJ3672=0, "", Downloads_maandcijfers!CJ3672) | CK209: =IF(Downloads_maandcijfers!CK3672=0, "", Downloads_maandcijfers!CK3672) | CL209: =IF(Downloads_maandcijfers!CL3672=0, "", Downloads_maandcijfers!CL3672) | CM209: =IF(Downloads_maandcijfers!CM3672=0, "", Downloads_maandcijfers!CM3672)
A210: 36647 | B210: =IF(Downloads_maandcijfers!B213="", "", Downloads_maandcijfers!B213) -> 29.64 | C210: =IF(Downloads_maandcijfers!C213="", "", Downloads_maandcijfers!C213) -> 1.0783 | D210: =IF(Downloads_maandcijfers!D213="", "", Downloads_maandcijfers!D213) -> 97.986201 | E210: =IF(Downloads_maandcijfers!E213="", "", Downloads_maandcijfers!E213) -> 84.041663 | F210: =IF(Downloads_maandcijfers!F213="", "", Downloads_maandcijfers!F213) -> 23.65 | G210: =IF(Downloads_maandcijfers!G213="", "", Downloads_maandcijfers!G213) -> 5.38 | H210: =IF(Downloads_maandcijfers!H213="", "", Downloads_maandcijfers!H213) -> 6.29 | I210: =IF(Downloads_maandcijfers!I213="", "", Downloads_maandcijfers!I213) -> 5.57 | ... CF210: =IF(Downloads_maandcijfers!CF213="", "", Downloads_maandcijfers!CF213) | CG210: =IF(Downloads_maandcijfers!CG3672="", "", Downloads_maandcijfers!CG3672) | CH210: =IF(Downloads_maandcijfers!CH3672="", "", Downloads_maandcijfers!CH3672) | CI210: =IF(Downloads_maandcijfers!CI3673=0, "", Downloads_maandcijfers!CI3673) | CJ210: =IF(Downloads_maandcijfers!CJ3673=0, "", Downloads_maandcijfers!CJ3673) | CK210: =IF(Downloads_maandcijfers!CK3673=0, "", Downloads_maandcijfers!CK3673) | CL210: =IF(Downloads_maandcijfers!CL3673=0, "", Downloads_maandcijfers!CL3673) | CM210: =IF(Downloads_maandcijfers!CM3673=0, "", Downloads_maandcijfers!CM3673)
A211: 36678 | B211: =IF(Downloads_maandcijfers!B214="", "", Downloads_maandcijfers!B214) -> 31.58 | C211: =IF(Downloads_maandcijfers!C214="", "", Downloads_maandcijfers!C214) -> 1.0432 | D211: =IF(Downloads_maandcijfers!D214="", "", Downloads_maandcijfers!D214) -> 92.965017 | E211: =IF(Downloads_maandcijfers!E214="", "", Downloads_maandcijfers!E214) -> 59.968966 | F211: =IF(Downloads_maandcijfers!F214="", "", Downloads_maandcijfers!F214) -> 19.54 | G211: =IF(Downloads_maandcijfers!G214="", "", Downloads_maandcijfers!G214) -> 5.19 | H211: =IF(Downloads_maandcijfers!H214="", "", Downloads_maandcijfers!H214) -> 6.03 | I211: =IF(Downloads_maandcijfers!I214="", "", Downloads_maandcijfers!I214) -> 5.56 | ... CF211: =IF(Downloads_maandcijfers!CF214="", "", Downloads_maandcijfers!CF214) | CG211: =IF(Downloads_maandcijfers!CG3673="", "", Downloads_maandcijfers!CG3673) | CH211: =IF(Downloads_maandcijfers!CH3673="", "", Downloads_maandcijfers!CH3673) | CI211: =IF(Downloads_maandcijfers!CI3674=0, "", Downloads_maandcijfers!CI3674) | CJ211: =IF(Downloads_maandcijfers!CJ3674=0, "", Downloads_maandcijfers!CJ3674) | CK211: =IF(Downloads_maandcijfers!CK3674=0, "", Downloads_maandcijfers!CK3674) | CL211: =IF(Downloads_maandcijfers!CL3674=0, "", Downloads_maandcijfers!CL3674) | CM211: =IF(Downloads_maandcijfers!CM3674=0, "", Downloads_maandcijfers!CM3674)
A212: 36708 | B212: =IF(Downloads_maandcijfers!B215="", "", Downloads_maandcijfers!B215) -> 25.3 | C212: =IF(Downloads_maandcijfers!C215="", "", Downloads_maandcijfers!C215) -> 1.0792 | D212: =IF(Downloads_maandcijfers!D215="", "", Downloads_maandcijfers!D215) -> 79.446971 | E212: =IF(Downloads_maandcijfers!E215="", "", Downloads_maandcijfers!E215) -> 58.438124 | F212: =IF(Downloads_maandcijfers!F215="", "", Downloads_maandcijfers!F215) -> 20.74 | G212: =IF(Downloads_maandcijfers!G215="", "", Downloads_maandcijfers!G215) -> 5.27 | H212: =IF(Downloads_maandcijfers!H215="", "", Downloads_maandcijfers!H215) -> 6.04 | I212: =IF(Downloads_maandcijfers!I215="", "", Downloads_maandcijfers!I215) -> 5.55 | ... CF212: =IF(Downloads_maandcijfers!CF215="", "", Downloads_maandcijfers!CF215) | CG212: =IF(Downloads_maandcijfers!CG3674="", "", Downloads_maandcijfers!CG3674) | CH212: =IF(Downloads_maandcijfers!CH3674="", "", Downloads_maandcijfers!CH3674) | CI212: =IF(Downloads_maandcijfers!CI3675=0, "", Downloads_maandcijfers!CI3675) | CJ212: =IF(Downloads_maandcijfers!CJ3675=0, "", Downloads_maandcijfers!CJ3675) | CK212: =IF(Downloads_maandcijfers!CK3675=0, "", Downloads_maandcijfers!CK3675) | CL212: =IF(Downloads_maandcijfers!CL3675=0, "", Downloads_maandcijfers!CL3675) | CM212: =IF(Downloads_maandcijfers!CM3675=0, "", Downloads_maandcijfers!CM3675)
A213: 36739 | B213: =IF(Downloads_maandcijfers!B216="", "", Downloads_maandcijfers!B216) -> 35.08 | C213: =IF(Downloads_maandcijfers!C216="", "", Downloads_maandcijfers!C216) -> 1.1248 | D213: =IF(Downloads_maandcijfers!D216="", "", Downloads_maandcijfers!D216) -> 66.581332 | E213: =IF(Downloads_maandcijfers!E216="", "", Downloads_maandcijfers!E216) -> 63.555976 | F213: =IF(Downloads_maandcijfers!F216="", "", Downloads_maandcijfers!F216) -> 16.84 | G213: =IF(Downloads_maandcijfers!G216="", "", Downloads_maandcijfers!G216) -> 5.21 | H213: =IF(Downloads_maandcijfers!H216="", "", Downloads_maandcijfers!H216) -> 5.73 | I213: =IF(Downloads_maandcijfers!I216="", "", Downloads_maandcijfers!I216) -> 5.65 | ... CF213: =IF(Downloads_maandcijfers!CF216="", "", Downloads_maandcijfers!CF216) | CG213: =IF(Downloads_maandcijfers!CG3675="", "", Downloads_maandcijfers!CG3675) | CH213: =IF(Downloads_maandcijfers!CH3675="", "", Downloads_maandcijfers!CH3675) | CI213: =IF(Downloads_maandcijfers!CI3676=0, "", Downloads_maandcijfers!CI3676) | CJ213: =IF(Downloads_maandcijfers!CJ3676=0, "", Downloads_maandcijfers!CJ3676) | CK213: =IF(Downloads_maandcijfers!CK3676=0, "", Downloads_maandcijfers!CK3676) | CL213: =IF(Downloads_maandcijfers!CL3676=0, "", Downloads_maandcijfers!CL3676) | CM213: =IF(Downloads_maandcijfers!CM3676=0, "", Downloads_maandcijfers!CM3676)
A214: 36770 | B214: =IF(Downloads_maandcijfers!B217="", "", Downloads_maandcijfers!B217) -> 28.42 | C214: =IF(Downloads_maandcijfers!C217="", "", Downloads_maandcijfers!C217) -> 1.1332 | D214: =IF(Downloads_maandcijfers!D217="", "", Downloads_maandcijfers!D217) -> 75.141652 | E214: =IF(Downloads_maandcijfers!E217="", "", Downloads_maandcijfers!E217) -> 70.463777 | F214: =IF(Downloads_maandcijfers!F217="", "", Downloads_maandcijfers!F217) -> 20.57 | G214: =IF(Downloads_maandcijfers!G217="", "", Downloads_maandcijfers!G217) -> 5.26 | H214: =IF(Downloads_maandcijfers!H217="", "", Downloads_maandcijfers!H217) -> 5.8 | I214: =IF(Downloads_maandcijfers!I217="", "", Downloads_maandcijfers!I217) -> 5.6 | ... CF214: =IF(Downloads_maandcijfers!CF217="", "", Downloads_maandcijfers!CF217) | CG214: =IF(Downloads_maandcijfers!CG3676="", "", Downloads_maandcijfers!CG3676) | CH214: =IF(Downloads_maandcijfers!CH3676="", "", Downloads_maandcijfers!CH3676) | CI214: =IF(Downloads_maandcijfers!CI3677=0, "", Downloads_maandcijfers!CI3677) | CJ214: =IF(Downloads_maandcijfers!CJ3677=0, "", Downloads_maandcijfers!CJ3677) | CK214: =IF(Downloads_maandcijfers!CK3677=0, "", Downloads_maandcijfers!CK3677) | CL214: =IF(Downloads_maandcijfers!CL3677=0, "", Downloads_maandcijfers!CL3677) | CM214: =IF(Downloads_maandcijfers!CM3677=0, "", Downloads_maandcijfers!CM3677)
A215: 36800 | B215: =IF(Downloads_maandcijfers!B218="", "", Downloads_maandcijfers!B218) -> 30.15 | C215: =IF(Downloads_maandcijfers!C218="", "", Downloads_maandcijfers!C218) -> 1.1797 | D215: =IF(Downloads_maandcijfers!D218="", "", Downloads_maandcijfers!D218) -> 84.661723 | E215: =IF(Downloads_maandcijfers!E218="", "", Downloads_maandcijfers!E218) -> 72.280553 | F215: =IF(Downloads_maandcijfers!F218="", "", Downloads_maandcijfers!F218) -> 23.63 | G215: =IF(Downloads_maandcijfers!G218="", "", Downloads_maandcijfers!G218) -> 5.21 | H215: =IF(Downloads_maandcijfers!H218="", "", Downloads_maandcijfers!H218) -> 5.77 | I215: =IF(Downloads_maandcijfers!I218="", "", Downloads_maandcijfers!I218) -> 5.59 | ... CF215: =IF(Downloads_maandcijfers!CF218="", "", Downloads_maandcijfers!CF218) | CG215: =IF(Downloads_maandcijfers!CG3677="", "", Downloads_maandcijfers!CG3677) | CH215: =IF(Downloads_maandcijfers!CH3677="", "", Downloads_maandcijfers!CH3677) | CI215: =IF(Downloads_maandcijfers!CI3678=0, "", Downloads_maandcijfers!CI3678) | CJ215: =IF(Downloads_maandcijfers!CJ3678=0, "", Downloads_maandcijfers!CJ3678) | CK215: =IF(Downloads_maandcijfers!CK3678=0, "", Downloads_maandcijfers!CK3678) | CL215: =IF(Downloads_maandcijfers!CL3678=0, "", Downloads_maandcijfers!CL3678) | CM215: =IF(Downloads_maandcijfers!CM3678=0, "", Downloads_maandcijfers!CM3678)
A216: 36831 | B216: =IF(Downloads_maandcijfers!B219="", "", Downloads_maandcijfers!B219) -> 32.53 | C216: =IF(Downloads_maandcijfers!C219="", "", Downloads_maandcijfers!C219) -> 1.1488 | D216: =IF(Downloads_maandcijfers!D219="", "", Downloads_maandcijfers!D219) -> 125.06753 | E216: =IF(Downloads_maandcijfers!E219="", "", Downloads_maandcijfers!E219) -> 108.67674 | F216: =IF(Downloads_maandcijfers!F219="", "", Downloads_maandcijfers!F219) -> 29.65 | G216: =IF(Downloads_maandcijfers!G219="", "", Downloads_maandcijfers!G219) -> 5.15 | H216: =IF(Downloads_maandcijfers!H219="", "", Downloads_maandcijfers!H219) -> 5.48 | I216: =IF(Downloads_maandcijfers!I219="", "", Downloads_maandcijfers!I219) -> 5.38 | ... CF216: =IF(Downloads_maandcijfers!CF219="", "", Downloads_maandcijfers!CF219) | CG216: =IF(Downloads_maandcijfers!CG3678="", "", Downloads_maandcijfers!CG3678) | CH216: =IF(Downloads_maandcijfers!CH3678="", "", Downloads_maandcijfers!CH3678) | CI216: =IF(Downloads_maandcijfers!CI3679=0, "", Downloads_maandcijfers!CI3679) | CJ216: =IF(Downloads_maandcijfers!CJ3679=0, "", Downloads_maandcijfers!CJ3679) | CK216: =IF(Downloads_maandcijfers!CK3679=0, "", Downloads_maandcijfers!CK3679) | CL216: =IF(Downloads_maandcijfers!CL3679=0, "", Downloads_maandcijfers!CL3679) | CM216: =IF(Downloads_maandcijfers!CM3679=0, "", Downloads_maandcijfers!CM3679)
A217: 36861 | B217: =IF(Downloads_maandcijfers!B220="", "", Downloads_maandcijfers!B220) -> 22.58 | C217: =IF(Downloads_maandcijfers!C220="", "", Downloads_maandcijfers!C220) -> 1.0651 | D217: =IF(Downloads_maandcijfers!D220="", "", Downloads_maandcijfers!D220) -> 115.26872 | E217: =IF(Downloads_maandcijfers!E220="", "", Downloads_maandcijfers!E220) -> 99.956842 | F217: =IF(Downloads_maandcijfers!F220="", "", Downloads_maandcijfers!F220) -> 26.85 | G217: =IF(Downloads_maandcijfers!G220="", "", Downloads_maandcijfers!G220) -> 4.89 | H217: =IF(Downloads_maandcijfers!H220="", "", Downloads_maandcijfers!H220) -> 5.12 | I217: =IF(Downloads_maandcijfers!I220="", "", Downloads_maandcijfers!I220) -> 5.27 | ... CF217: =IF(Downloads_maandcijfers!CF220="", "", Downloads_maandcijfers!CF220) | CG217: =IF(Downloads_maandcijfers!CG3679="", "", Downloads_maandcijfers!CG3679) | CH217: =IF(Downloads_maandcijfers!CH3679="", "", Downloads_maandcijfers!CH3679) | CI217: =IF(Downloads_maandcijfers!CI3680=0, "", Downloads_maandcijfers!CI3680) | CJ217: =IF(Downloads_maandcijfers!CJ3680=0, "", Downloads_maandcijfers!CJ3680) | CK217: =IF(Downloads_maandcijfers!CK3680=0, "", Downloads_maandcijfers!CK3680) | CL217: =IF(Downloads_maandcijfers!CL3680=0, "", Downloads_maandcijfers!CL3680) | CM217: =IF(Downloads_maandcijfers!CM3680=0, "", Downloads_maandcijfers!CM3680)
... A221: 36982 | B221: =IF(Downloads_maandcijfers!B224="", "", Downloads_maandcijfers!B224) -> 27.21 | C221: =IF(Downloads_maandcijfers!C224="", "", Downloads_maandcijfers!C224) -> 1.128 | D221: =IF(Downloads_maandcijfers!D224="", "", Downloads_maandcijfers!D224) -> 122.6734 | E221: =IF(Downloads_maandcijfers!E224="", "", Downloads_maandcijfers!E224) -> 97.056588 | F221: =IF(Downloads_maandcijfers!F224="", "", Downloads_maandcijfers!F224) -> 25.48 | G221: =IF(Downloads_maandcijfers!G224="", "", Downloads_maandcijfers!G224) -> 4.83 | H221: =IF(Downloads_maandcijfers!H224="", "", Downloads_maandcijfers!H224) -> 5.35 | I221: =IF(Downloads_maandcijfers!I224="", "", Downloads_maandcijfers!I224) -> 5.46 | ... CF221: =IF(Downloads_maandcijfers!CF224="", "", Downloads_maandcijfers!CF224) | CG221: =IF(Downloads_maandcijfers!CG3683="", "", Downloads_maandcijfers!CG3683) | CH221: =IF(Downloads_maandcijfers!CH3683="", "", Downloads_maandcijfers!CH3683) | CI221: =IF(Downloads_maandcijfers!CI3684=0, "", Downloads_maandcijfers!CI3684) | CJ221: =IF(Downloads_maandcijfers!CJ3684=0, "", Downloads_maandcijfers!CJ3684) | CK221: =IF(Downloads_maandcijfers!CK3684=0, "", Downloads_maandcijfers!CK3684) | CL221: =IF(Downloads_maandcijfers!CL3684=0, "", Downloads_maandcijfers!CL3684) | CM221: =IF(Downloads_maandcijfers!CM3684=0, "", Downloads_maandcijfers!CM3684)
A222: 37012 | B222: =IF(Downloads_maandcijfers!B225="", "", Downloads_maandcijfers!B225) -> 28.55 | C222: =IF(Downloads_maandcijfers!C225="", "", Downloads_maandcijfers!C225) -> 1.1798 | D222: =IF(Downloads_maandcijfers!D225="", "", Downloads_maandcijfers!D225) -> 100.42901 | E222: =IF(Downloads_maandcijfers!E225="", "", Downloads_maandcijfers!E225) -> 75.266984 | F222: =IF(Downloads_maandcijfers!F225="", "", Downloads_maandcijfers!F225) -> 22.64 | G222: =IF(Downloads_maandcijfers!G225="", "", Downloads_maandcijfers!G225) -> 5.05 | H222: =IF(Downloads_maandcijfers!H225="", "", Downloads_maandcijfers!H225) -> 5.43 | I222: =IF(Downloads_maandcijfers!I225="", "", Downloads_maandcijfers!I225) -> 5.55 | ... BI222: =IF(Downloads_maandcijfers!BI225="", "", Downloads_maandcijfers!BI225) -> 62.579789 | BK222: =IF(Downloads_maandcijfers!BK225="", "", Downloads_maandcijfers!BK225) | BL222: 46 | BM222: =IF(Downloads_maandcijfers!BM225="", "", Downloads_maandcijfers!BM225) -> 4.531 | BN222: =IF(Downloads_maandcijfers!BN225="", "", Downloads_maandcijfers!BN225) -> 5.32 | BO222: =IF(Downloads_maandcijfers!BO225="", "", Downloads_maandcijfers!BO225) -> 98.24194 | BP222: =IF(Downloads_maandcijfers!BP225="", "", Downloads_maandcijfers!BP225) -> 98.54784 | BQ222: =IF(Downloads_maandcijfers!BQ225="", "", Downloads_maandcijfers!BQ225) -> 100.1743 | BR222: =IF(Downloads_maandcijfers!BR225="", "", Downloads_maandcijfers!BR225) | BS222: =IF(Downloads_maandcijfers!BS225="", "", Downloads_maandcijfers!BS225) | BT222: =IF(Downloads_maandcijfers!BT225="", "", Downloads_maandcijfers!BT225) | ... CF222: =IF(Downloads_maandcijfers!CF225="", "", Downloads_maandcijfers!CF225) | CG222: =IF(Downloads_maandcijfers!CG3684="", "", Downloads_maandcijfers!CG3684) | CH222: =IF(Downloads_maandcijfers!CH3684="", "", Downloads_maandcijfers!CH3684) | CI222: =IF(Downloads_maandcijfers!CI3685=0, "", Downloads_maandcijfers!CI3685) | CJ222: =IF(Downloads_maandcijfers!CJ3685=0, "", Downloads_maandcijfers!CJ3685) | CK222: =IF(Downloads_maandcijfers!CK3685=0, "", Downloads_maandcijfers!CK3685) | CL222: =IF(Downloads_maandcijfers!CL3685=0, "", Downloads_maandcijfers!CL3685) | CM222: =IF(Downloads_maandcijfers!CM3685=0, "", Downloads_maandcijfers!CM3685)
A223: 37043 | B223: =IF(Downloads_maandcijfers!B226="", "", Downloads_maandcijfers!B226) -> 26.21 | C223: =IF(Downloads_maandcijfers!C226="", "", Downloads_maandcijfers!C226) -> 1.1812 | D223: =IF(Downloads_maandcijfers!D226="", "", Downloads_maandcijfers!D226) -> 86.390268 | E223: =IF(Downloads_maandcijfers!E226="", "", Downloads_maandcijfers!E226) -> 80.029225 | F223: =IF(Downloads_maandcijfers!F226="", "", Downloads_maandcijfers!F226) -> 19.06 | G223: =IF(Downloads_maandcijfers!G226="", "", Downloads_maandcijfers!G226) -> 5 | H223: =IF(Downloads_maandcijfers!H226="", "", Downloads_maandcijfers!H226) -> 5.42 | I223: =IF(Downloads_maandcijfers!I226="", "", Downloads_maandcijfers!I226) -> 5.5 | ... BI223: =IF(Downloads_maandcijfers!BI226="", "", Downloads_maandcijfers!BI226) -> 62.579789 | BK223: =IF(Downloads_maandcijfers!BK226="", "", Downloads_maandcijfers!BK226) | BL223: 46.4 | BM223: =IF(Downloads_maandcijfers!BM226="", "", Downloads_maandcijfers!BM226) -> 4.441 | BN223: =IF(Downloads_maandcijfers!BN226="", "", Downloads_maandcijfers!BN226) -> 5.24 | BO223: =IF(Downloads_maandcijfers!BO226="", "", Downloads_maandcijfers!BO226) -> 98.21902 | BP223: =IF(Downloads_maandcijfers!BP226="", "", Downloads_maandcijfers!BP226) -> 98.41019 | BQ223: =IF(Downloads_maandcijfers!BQ226="", "", Downloads_maandcijfers!BQ226) -> 99.87864 | BR223: =IF(Downloads_maandcijfers!BR226="", "", Downloads_maandcijfers!BR226) | BS223: =IF(Downloads_maandcijfers!BS226="", "", Downloads_maandcijfers!BS226) | BT223: =IF(Downloads_maandcijfers!BT226="", "", Downloads_maandcijfers!BT226) | ... CF223: =IF(Downloads_maandcijfers!CF226="", "", Downloads_maandcijfers!CF226) | CG223: =IF(Downloads_maandcijfers!CG3685="", "", Downloads_maandcijfers!CG3685) | CH223: =IF(Downloads_maandcijfers!CH3685="", "", Downloads_maandcijfers!CH3685) | CI223: =IF(Downloads_maandcijfers!CI3686=0, "", Downloads_maandcijfers!CI3686) | CJ223: =IF(Downloads_maandcijfers!CJ3686=0, "", Downloads_maandcijfers!CJ3686) | CK223: =IF(Downloads_maandcijfers!CK3686=0, "", Downloads_maandcijfers!CK3686) | CL223: =IF(Downloads_maandcijfers!CL3686=0, "", Downloads_maandcijfers!CL3686) | CM223: =IF(Downloads_maandcijfers!CM3686=0, "", Downloads_maandcijfers!CM3686)
A224: 37073 | B224: =IF(Downloads_maandcijfers!B227="", "", Downloads_maandcijfers!B227) -> 24.35 | C224: =IF(Downloads_maandcijfers!C227="", "", Downloads_maandcijfers!C227) -> 1.1429 | D224: =IF(Downloads_maandcijfers!D227="", "", Downloads_maandcijfers!D227) -> 102.13185 | E224: =IF(Downloads_maandcijfers!E227="", "", Downloads_maandcijfers!E227) -> 98.433164 | F224: =IF(Downloads_maandcijfers!F227="", "", Downloads_maandcijfers!F227) -> 21.62 | G224: =IF(Downloads_maandcijfers!G227="", "", Downloads_maandcijfers!G227) -> 5.02 | H224: =IF(Downloads_maandcijfers!H227="", "", Downloads_maandcijfers!H227) -> 5.07 | I224: =IF(Downloads_maandcijfers!I227="", "", Downloads_maandcijfers!I227) -> 5.27 | ... BI224: =IF(Downloads_maandcijfers!BI227="", "", Downloads_maandcijfers!BI227) -> 62.998427 | BK224: =IF(Downloads_maandcijfers!BK227="", "", Downloads_maandcijfers!BK227) | BL224: 47.8 | BM224: =IF(Downloads_maandcijfers!BM227="", "", Downloads_maandcijfers!BM227) -> 4.444 | BN224: =IF(Downloads_maandcijfers!BN227="", "", Downloads_maandcijfers!BN227) -> 5.02 | BO224: =IF(Downloads_maandcijfers!BO227="", "", Downloads_maandcijfers!BO227) -> 98.1748 | BP224: =IF(Downloads_maandcijfers!BP227="", "", Downloads_maandcijfers!BP227) -> 98.22047 | BQ224: =IF(Downloads_maandcijfers!BQ227="", "", Downloads_maandcijfers!BQ227) -> 99.5902 | BR224: =IF(Downloads_maandcijfers!BR227="", "", Downloads_maandcijfers!BR227) | BS224: =IF(Downloads_maandcijfers!BS227="", "", Downloads_maandcijfers!BS227) | BT224: =IF(Downloads_maandcijfers!BT227="", "", Downloads_maandcijfers!BT227) | ... CF224: =IF(Downloads_maandcijfers!CF227="", "", Downloads_maandcijfers!CF227) | CG224: =IF(Downloads_maandcijfers!CG3686="", "", Downloads_maandcijfers!CG3686) | CH224: =IF(Downloads_maandcijfers!CH3686="", "", Downloads_maandcijfers!CH3686) | CI224: =IF(Downloads_maandcijfers!CI3687=0, "", Downloads_maandcijfers!CI3687) | CJ224: =IF(Downloads_maandcijfers!CJ3687=0, "", Downloads_maandcijfers!CJ3687) | CK224: =IF(Downloads_maandcijfers!CK3687=0, "", Downloads_maandcijfers!CK3687) | CL224: =IF(Downloads_maandcijfers!CL3687=0, "", Downloads_maandcijfers!CL3687) | CM224: =IF(Downloads_maandcijfers!CM3687=0, "", Downloads_maandcijfers!CM3687)
A225: 37104 | B225: =IF(Downloads_maandcijfers!B228="", "", Downloads_maandcijfers!B228) -> 26.8 | C225: =IF(Downloads_maandcijfers!C228="", "", Downloads_maandcijfers!C228) -> 1.1009 | D225: =IF(Downloads_maandcijfers!D228="", "", Downloads_maandcijfers!D228) -> 84.289117 | E225: =IF(Downloads_maandcijfers!E228="", "", Downloads_maandcijfers!E228) -> 73.703429 | F225: =IF(Downloads_maandcijfers!F228="", "", Downloads_maandcijfers!F228) -> 24.92 | G225: =IF(Downloads_maandcijfers!G228="", "", Downloads_maandcijfers!G228) -> 4.82 | H225: =IF(Downloads_maandcijfers!H228="", "", Downloads_maandcijfers!H228) -> 4.85 | I225: =IF(Downloads_maandcijfers!I228="", "", Downloads_maandcijfers!I228) -> 5.15 | ... BI225: =IF(Downloads_maandcijfers!BI228="", "", Downloads_maandcijfers!BI228) -> 62.998427 | BK225: =IF(Downloads_maandcijfers!BK228="", "", Downloads_maandcijfers!BK228) | BL225: 47.8 | BM225: =IF(Downloads_maandcijfers!BM228="", "", Downloads_maandcijfers!BM228) -> 4.253 | BN225: =IF(Downloads_maandcijfers!BN228="", "", Downloads_maandcijfers!BN228) -> 4.94 | BO225: =IF(Downloads_maandcijfers!BO228="", "", Downloads_maandcijfers!BO228) -> 98.11225 | BP225: =IF(Downloads_maandcijfers!BP228="", "", Downloads_maandcijfers!BP228) -> 98.01084 | BQ225: =IF(Downloads_maandcijfers!BQ228="", "", Downloads_maandcijfers!BQ228) -> 99.33225 | BR225: =IF(Downloads_maandcijfers!BR228="", "", Downloads_maandcijfers!BR228) | BS225: =IF(Downloads_maandcijfers!BS228="", "", Downloads_maandcijfers!BS228) | BT225: =IF(Downloads_maandcijfers!BT228="", "", Downloads_maandcijfers!BT228) | ... CF225: =IF(Downloads_maandcijfers!CF228="", "", Downloads_maandcijfers!CF228) | CG225: =IF(Downloads_maandcijfers!CG3687="", "", Downloads_maandcijfers!CG3687) | CH225: =IF(Downloads_maandcijfers!CH3687="", "", Downloads_maandcijfers!CH3687) | CI225: =IF(Downloads_maandcijfers!CI3688=0, "", Downloads_maandcijfers!CI3688) | CJ225: =IF(Downloads_maandcijfers!CJ3688=0, "", Downloads_maandcijfers!CJ3688) | CK225: =IF(Downloads_maandcijfers!CK3688=0, "", Downloads_maandcijfers!CK3688) | CL225: =IF(Downloads_maandcijfers!CL3688=0, "", Downloads_maandcijfers!CL3688) | CM225: =IF(Downloads_maandcijfers!CM3688=0, "", Downloads_maandcijfers!CM3688)
A226: 37135 | B226: =IF(Downloads_maandcijfers!B229="", "", Downloads_maandcijfers!B229) -> 21.87 | C226: =IF(Downloads_maandcijfers!C229="", "", Downloads_maandcijfers!C229) -> 1.098 | D226: =IF(Downloads_maandcijfers!D229="", "", Downloads_maandcijfers!D229) -> 188.05949 | E226: =IF(Downloads_maandcijfers!E229="", "", Downloads_maandcijfers!E229) -> 215.05122 | F226: =IF(Downloads_maandcijfers!F229="", "", Downloads_maandcijfers!F229) -> 31.93 | G226: =IF(Downloads_maandcijfers!G229="", "", Downloads_maandcijfers!G229) -> 4.81 | H226: =IF(Downloads_maandcijfers!H229="", "", Downloads_maandcijfers!H229) -> 4.6 | I226: =IF(Downloads_maandcijfers!I229="", "", Downloads_maandcijfers!I229) -> 5.15 | ... BI226: =IF(Downloads_maandcijfers!BI229="", "", Downloads_maandcijfers!BI229) -> 62.998427 | BK226: =IF(Downloads_maandcijfers!BK229="", "", Downloads_maandcijfers!BK229) | BL226: 46.1 | BM226: =IF(Downloads_maandcijfers!BM229="", "", Downloads_maandcijfers!BM229) -> 3.656 | BN226: =IF(Downloads_maandcijfers!BN229="", "", Downloads_maandcijfers!BN229) -> 4.93 | BO226: =IF(Downloads_maandcijfers!BO229="", "", Downloads_maandcijfers!BO229) -> 98.07177 | BP226: =IF(Downloads_maandcijfers!BP229="", "", Downloads_maandcijfers!BP229) -> 97.82968 | BQ226: =IF(Downloads_maandcijfers!BQ229="", "", Downloads_maandcijfers!BQ229) -> 99.13004 | BR226: =IF(Downloads_maandcijfers!BR229="", "", Downloads_maandcijfers!BR229) | BS226: =IF(Downloads_maandcijfers!BS229="", "", Downloads_maandcijfers!BS229) | BT226: =IF(Downloads_maandcijfers!BT229="", "", Downloads_maandcijfers!BT229) | ... CF226: =IF(Downloads_maandcijfers!CF229="", "", Downloads_maandcijfers!CF229) | CG226: =IF(Downloads_maandcijfers!CG3688="", "", Downloads_maandcijfers!CG3688) | CH226: =IF(Downloads_maandcijfers!CH3688="", "", Downloads_maandcijfers!CH3688) | CI226: =IF(Downloads_maandcijfers!CI3689=0, "", Downloads_maandcijfers!CI3689) | CJ226: =IF(Downloads_maandcijfers!CJ3689=0, "", Downloads_maandcijfers!CJ3689) | CK226: =IF(Downloads_maandcijfers!CK3689=0, "", Downloads_maandcijfers!CK3689) | CL226: =IF(Downloads_maandcijfers!CL3689=0, "", Downloads_maandcijfers!CL3689) | CM226: =IF(Downloads_maandcijfers!CM3689=0, "", Downloads_maandcijfers!CM3689)
A227: 37165 | B227: =IF(Downloads_maandcijfers!B230="", "", Downloads_maandcijfers!B230) -> 19.63 | C227: =IF(Downloads_maandcijfers!C230="", "", Downloads_maandcijfers!C230) -> 1.1103 | D227: =IF(Downloads_maandcijfers!D230="", "", Downloads_maandcijfers!D230) -> 173.14334 | E227: =IF(Downloads_maandcijfers!E230="", "", Downloads_maandcijfers!E230) -> 204.65605 | F227: =IF(Downloads_maandcijfers!F230="", "", Downloads_maandcijfers!F230) -> 33.56 | G227: =IF(Downloads_maandcijfers!G230="", "", Downloads_maandcijfers!G230) -> 4.6 | H227: =IF(Downloads_maandcijfers!H230="", "", Downloads_maandcijfers!H230) -> 4.3 | I227: =IF(Downloads_maandcijfers!I230="", "", Downloads_maandcijfers!I230) -> 4.75 | ... BI227: =IF(Downloads_maandcijfers!BI230="", "", Downloads_maandcijfers!BI230) -> 63.630797 | BK227: =IF(Downloads_maandcijfers!BK230="", "", Downloads_maandcijfers!BK230) | BL227: 42.7 | BM227: =IF(Downloads_maandcijfers!BM230="", "", Downloads_maandcijfers!BM230) -> 3.522 | BN227: =IF(Downloads_maandcijfers!BN230="", "", Downloads_maandcijfers!BN230) -> 4.55 | BO227: =IF(Downloads_maandcijfers!BO230="", "", Downloads_maandcijfers!BO230) -> 98.12298 | BP227: =IF(Downloads_maandcijfers!BP230="", "", Downloads_maandcijfers!BP230) -> 97.71069 | BQ227: =IF(Downloads_maandcijfers!BQ230="", "", Downloads_maandcijfers!BQ230) -> 99.02413 | BR227: =IF(Downloads_maandcijfers!BR230="", "", Downloads_maandcijfers!BR230) | BS227: =IF(Downloads_maandcijfers!BS230="", "", Downloads_maandcijfers!BS230) | BT227: =IF(Downloads_maandcijfers!BT230="", "", Downloads_maandcijfers!BT230) | ... CF227: =IF(Downloads_maandcijfers!CF230="", "", Downloads_maandcijfers!CF230) | CG227: =IF(Downloads_maandcijfers!CG3689="", "", Downloads_maandcijfers!CG3689) | CH227: =IF(Downloads_maandcijfers!CH3689="", "", Downloads_maandcijfers!CH3689) | CI227: =IF(Downloads_maandcijfers!CI3690=0, "", Downloads_maandcijfers!CI3690) | CJ227: =IF(Downloads_maandcijfers!CJ3690=0, "", Downloads_maandcijfers!CJ3690) | CK227: =IF(Downloads_maandcijfers!CK3690=0, "", Downloads_maandcijfers!CK3690) | CL227: =IF(Downloads_maandcijfers!CL3690=0, "", Downloads_maandcijfers!CL3690) | CM227: =IF(Downloads_maandcijfers!CM3690=0, "", Downloads_maandcijfers!CM3690)
A228: 37196 | B228: =IF(Downloads_maandcijfers!B231="", "", Downloads_maandcijfers!B231) -> 18.92 | C228: =IF(Downloads_maandcijfers!C231="", "", Downloads_maandcijfers!C231) -> 1.1168 | D228: =IF(Downloads_maandcijfers!D231="", "", Downloads_maandcijfers!D231) -> 130.57563 | E228: =IF(Downloads_maandcijfers!E231="", "", Downloads_maandcijfers!E231) -> 165.2718 | F228: =IF(Downloads_maandcijfers!F231="", "", Downloads_maandcijfers!F231) -> 23.84 | G228: =IF(Downloads_maandcijfers!G231="", "", Downloads_maandcijfers!G231) -> 4.45 | H228: =IF(Downloads_maandcijfers!H231="", "", Downloads_maandcijfers!H231) -> 4.78 | I228: =IF(Downloads_maandcijfers!I231="", "", Downloads_maandcijfers!I231) -> 4.89 | ... BI228: =IF(Downloads_maandcijfers!BI231="", "", Downloads_maandcijfers!BI231) -> 63.630797 | BK228: =IF(Downloads_maandcijfers!BK231="", "", Downloads_maandcijfers!BK231) | BL228: 42.5 | BM228: =IF(Downloads_maandcijfers!BM231="", "", Downloads_maandcijfers!BM231) -> 3.36 | BN228: =IF(Downloads_maandcijfers!BN231="", "", Downloads_maandcijfers!BN231) -> 4.7 | BO228: =IF(Downloads_maandcijfers!BO231="", "", Downloads_maandcijfers!BO231) -> 98.29177 | BP228: =IF(Downloads_maandcijfers!BP231="", "", Downloads_maandcijfers!BP231) -> 97.67709 | BQ228: =IF(Downloads_maandcijfers!BQ231="", "", Downloads_maandcijfers!BQ231) -> 99.02959 | BR228: =IF(Downloads_maandcijfers!BR231="", "", Downloads_maandcijfers!BR231) | BS228: =IF(Downloads_maandcijfers!BS231="", "", Downloads_maandcijfers!BS231) | BT228: =IF(Downloads_maandcijfers!BT231="", "", Downloads_maandcijfers!BT231) | ... CF228: =IF(Downloads_maandcijfers!CF231="", "", Downloads_maandcijfers!CF231) | CG228: =IF(Downloads_maandcijfers!CG3690="", "", Downloads_maandcijfers!CG3690) | CH228: =IF(Downloads_maandcijfers!CH3690="", "", Downloads_maandcijfers!CH3690) | CI228: =IF(Downloads_maandcijfers!CI3691=0, "", Downloads_maandcijfers!CI3691) | CJ228: =IF(Downloads_maandcijfers!CJ3691=0, "", Downloads_maandcijfers!CJ3691) | CK228: =IF(Downloads_maandcijfers!CK3691=0, "", Downloads_maandcijfers!CK3691) | CL228: =IF(Downloads_maandcijfers!CL3691=0, "", Downloads_maandcijfers!CL3691) | CM228: =IF(Downloads_maandcijfers!CM3691=0, "", Downloads_maandcijfers!CM3691)
A229: 37226 | B229: =IF(Downloads_maandcijfers!B232="", "", Downloads_maandcijfers!B232) -> 19.35 | C229: =IF(Downloads_maandcijfers!C232="", "", Downloads_maandcijfers!C232) -> 1.1231 | D229: =IF(Downloads_maandcijfers!D232="", "", Downloads_maandcijfers!D232) -> 117.23658 | E229: =IF(Downloads_maandcijfers!E232="", "", Downloads_maandcijfers!E232) -> 111.50606 | F229: =IF(Downloads_maandcijfers!F232="", "", Downloads_maandcijfers!F232) -> 23.8 | G229: =IF(Downloads_maandcijfers!G232="", "", Downloads_maandcijfers!G232) -> 4.74 | H229: =IF(Downloads_maandcijfers!H232="", "", Downloads_maandcijfers!H232) -> 5.07 | I229: =IF(Downloads_maandcijfers!I232="", "", Downloads_maandcijfers!I232) -> 5.27 | ... BI229: =IF(Downloads_maandcijfers!BI232="", "", Downloads_maandcijfers!BI232) -> 63.630797 | BK229: =IF(Downloads_maandcijfers!BK232="", "", Downloads_maandcijfers!BK232) | BL229: 43.8 | BM229: =IF(Downloads_maandcijfers!BM232="", "", Downloads_maandcijfers!BM232) -> 3.294 | BN229: =IF(Downloads_maandcijfers!BN232="", "", Downloads_maandcijfers!BN232) -> 5.11 | BO229: =IF(Downloads_maandcijfers!BO232="", "", Downloads_maandcijfers!BO232) -> 98.55709 | BP229: =IF(Downloads_maandcijfers!BP232="", "", Downloads_maandcijfers!BP232) -> 97.7356 | BQ229: =IF(Downloads_maandcijfers!BQ232="", "", Downloads_maandcijfers!BQ232) -> 99.13087 | BR229: =IF(Downloads_maandcijfers!BR232="", "", Downloads_maandcijfers!BR232) | BS229: =IF(Downloads_maandcijfers!BS232="", "", Downloads_maandcijfers!BS232) | BT229: =IF(Downloads_maandcijfers!BT232="", "", Downloads_maandcijfers!BT232) | ... CF229: =IF(Downloads_maandcijfers!CF232="", "", Downloads_maandcijfers!CF232) | CG229: =IF(Downloads_maandcijfers!CG3691="", "", Downloads_maandcijfers!CG3691) | CH229: =IF(Downloads_maandcijfers!CH3691="", "", Downloads_maandcijfers!CH3691) | CI229: =IF(Downloads_maandcijfers!CI3692=0, "", Downloads_maandcijfers!CI3692) | CJ229: =IF(Downloads_maandcijfers!CJ3692=0, "", Downloads_maandcijfers!CJ3692) | CK229: =IF(Downloads_maandcijfers!CK3692=0, "", Downloads_maandcijfers!CK3692) | CL229: =IF(Downloads_maandcijfers!CL3692=0, "", Downloads_maandcijfers!CL3692) | CM229: =IF(Downloads_maandcijfers!CM3692=0, "", Downloads_maandcijfers!CM3692)
A230: 37257 | B230: =IF(Downloads_maandcijfers!B233="", "", Downloads_maandcijfers!B233) -> 19.07 | C230: =IF(Downloads_maandcijfers!C233="", "", Downloads_maandcijfers!C233) -> 1.1615 | D230: =IF(Downloads_maandcijfers!D233="", "", Downloads_maandcijfers!D233) -> 116.83745 | E230: =IF(Downloads_maandcijfers!E233="", "", Downloads_maandcijfers!E233) -> 105.63607 | F230: =IF(Downloads_maandcijfers!F233="", "", Downloads_maandcijfers!F233) -> 21.09 | G230: =IF(Downloads_maandcijfers!G233="", "", Downloads_maandcijfers!G233) -> 4.86 | H230: =IF(Downloads_maandcijfers!H233="", "", Downloads_maandcijfers!H233) -> 5.07 | I230: =IF(Downloads_maandcijfers!I233="", "", Downloads_maandcijfers!I233) -> 5.17 | ... BI230: =IF(Downloads_maandcijfers!BI233="", "", Downloads_maandcijfers!BI233) -> 64.110537 | BK230: =IF(Downloads_maandcijfers!BK233="", "", Downloads_maandcijfers!BK233) | BL230: 45.7 | BM230: =IF(Downloads_maandcijfers!BM233="", "", Downloads_maandcijfers!BM233) -> 3.371 | BN230: =IF(Downloads_maandcijfers!BN233="", "", Downloads_maandcijfers!BN233) -> 5.01 | BO230: =IF(Downloads_maandcijfers!BO233="", "", Downloads_maandcijfers!BO233) -> 98.86447 | BP230: =IF(Downloads_maandcijfers!BP233="", "", Downloads_maandcijfers!BP233) -> 97.86984 | BQ230: =IF(Downloads_maandcijfers!BQ233="", "", Downloads_maandcijfers!BQ233) -> 99.28825 | BR230: =IF(Downloads_maandcijfers!BR233="", "", Downloads_maandcijfers!BR233) | BS230: =IF(Downloads_maandcijfers!BS233="", "", Downloads_maandcijfers!BS233) | BT230: =IF(Downloads_maandcijfers!BT233="", "", Downloads_maandcijfers!BT233) | ... CF230: =IF(Downloads_maandcijfers!CF233="", "", Downloads_maandcijfers!CF233) | CG230: =IF(Downloads_maandcijfers!CG3692="", "", Downloads_maandcijfers!CG3692) | CH230: =IF(Downloads_maandcijfers!CH3692="", "", Downloads_maandcijfers!CH3692) | CI230: =IF(Downloads_maandcijfers!CI3693=0, "", Downloads_maandcijfers!CI3693) | CJ230: =IF(Downloads_maandcijfers!CJ3693=0, "", Downloads_maandcijfers!CJ3693) | CK230: =IF(Downloads_maandcijfers!CK3693=0, "", Downloads_maandcijfers!CK3693) | CL230: =IF(Downloads_maandcijfers!CL3693=0, "", Downloads_maandcijfers!CL3693) | CM230: =IF(Downloads_maandcijfers!CM3693=0, "", Downloads_maandcijfers!CM3693)
A231: 37288 | B231: =IF(Downloads_maandcijfers!B234="", "", Downloads_maandcijfers!B234) -> 20.73 | C231: =IF(Downloads_maandcijfers!C234="", "", Downloads_maandcijfers!C234) -> 1.1561 | D231: =IF(Downloads_maandcijfers!D234="", "", Downloads_maandcijfers!D234) -> 87.600685 | E231: =IF(Downloads_maandcijfers!E234="", "", Downloads_maandcijfers!E234) -> 101.53128 | F231: =IF(Downloads_maandcijfers!F234="", "", Downloads_maandcijfers!F234) -> 21.59 | G231: =IF(Downloads_maandcijfers!G234="", "", Downloads_maandcijfers!G234) -> 4.92 | H231: =IF(Downloads_maandcijfers!H234="", "", Downloads_maandcijfers!H234) -> 4.88 | I231: =IF(Downloads_maandcijfers!I234="", "", Downloads_maandcijfers!I234) -> 5.23 | ... BI231: =IF(Downloads_maandcijfers!BI234="", "", Downloads_maandcijfers!BI234) -> 64.110537 | BK231: =IF(Downloads_maandcijfers!BK234="", "", Downloads_maandcijfers!BK234) | BL231: 48 | BM231: =IF(Downloads_maandcijfers!BM234="", "", Downloads_maandcijfers!BM234) -> 3.366 | BN231: =IF(Downloads_maandcijfers!BN234="", "", Downloads_maandcijfers!BN234) -> 5.06 | BO231: =IF(Downloads_maandcijfers!BO234="", "", Downloads_maandcijfers!BO234) -> 99.15599 | BP231: =IF(Downloads_maandcijfers!BP234="", "", Downloads_maandcijfers!BP234) -> 98.08976 | BQ231: =IF(Downloads_maandcijfers!BQ234="", "", Downloads_maandcijfers!BQ234) -> 99.46198 | BR231: =IF(Downloads_maandcijfers!BR234="", "", Downloads_maandcijfers!BR234) | BS231: =IF(Downloads_maandcijfers!BS234="", "", Downloads_maandcijfers!BS234) | BT231: =IF(Downloads_maandcijfers!BT234="", "", Downloads_maandcijfers!BT234) | ... CF231: =IF(Downloads_maandcijfers!CF234="", "", Downloads_maandcijfers!CF234) | CG231: =IF(Downloads_maandcijfers!CG3693="", "", Downloads_maandcijfers!CG3693) | CH231: =IF(Downloads_maandcijfers!CH3693="", "", Downloads_maandcijfers!CH3693) | CI231: =IF(Downloads_maandcijfers!CI3694=0, "", Downloads_maandcijfers!CI3694) | CJ231: =IF(Downloads_maandcijfers!CJ3694=0, "", Downloads_maandcijfers!CJ3694) | CK231: =IF(Downloads_maandcijfers!CK3694=0, "", Downloads_maandcijfers!CK3694) | CL231: =IF(Downloads_maandcijfers!CL3694=0, "", Downloads_maandcijfers!CL3694) | CM231: =IF(Downloads_maandcijfers!CM3694=0, "", Downloads_maandcijfers!CM3694)
A232: 37316 | B232: =IF(Downloads_maandcijfers!B235="", "", Downloads_maandcijfers!B235) -> 25.34 | C232: =IF(Downloads_maandcijfers!C235="", "", Downloads_maandcijfers!C235) -> 1.1463 | D232: =IF(Downloads_maandcijfers!D235="", "", Downloads_maandcijfers!D235) -> 83.440433 | E232: =IF(Downloads_maandcijfers!E235="", "", Downloads_maandcijfers!E235) -> 85.988839 | F232: =IF(Downloads_maandcijfers!F235="", "", Downloads_maandcijfers!F235) -> 17.4 | G232: =IF(Downloads_maandcijfers!G235="", "", Downloads_maandcijfers!G235) -> 5.16 | H232: =IF(Downloads_maandcijfers!H235="", "", Downloads_maandcijfers!H235) -> 5.42 | I232: =IF(Downloads_maandcijfers!I235="", "", Downloads_maandcijfers!I235) -> 5.48 | ... BI232: =IF(Downloads_maandcijfers!BI235="", "", Downloads_maandcijfers!BI235) -> 64.110537 | BK232: =IF(Downloads_maandcijfers!BK235="", "", Downloads_maandcijfers!BK235) | BL232: 49.2 | BM232: =IF(Downloads_maandcijfers!BM235="", "", Downloads_maandcijfers!BM235) -> 3.448 | BN232: =IF(Downloads_maandcijfers!BN235="", "", Downloads_maandcijfers!BN235) -> 5.33 | BO232: =IF(Downloads_maandcijfers!BO235="", "", Downloads_maandcijfers!BO235) -> 99.37519 | BP232: =IF(Downloads_maandcijfers!BP235="", "", Downloads_maandcijfers!BP235) -> 98.37974 | BQ232: =IF(Downloads_maandcijfers!BQ235="", "", Downloads_maandcijfers!BQ235) -> 99.61085 | BR232: =IF(Downloads_maandcijfers!BR235="", "", Downloads_maandcijfers!BR235) | BS232: =IF(Downloads_maandcijfers!BS235="", "", Downloads_maandcijfers!BS235) | BT232: =IF(Downloads_maandcijfers!BT235="", "", Downloads_maandcijfers!BT235) | ... CF232: =IF(Downloads_maandcijfers!CF235="", "", Downloads_maandcijfers!CF235) | CG232: =IF(Downloads_maandcijfers!CG3694="", "", Downloads_maandcijfers!CG3694) | CH232: =IF(Downloads_maandcijfers!CH3694="", "", Downloads_maandcijfers!CH3694) | CI232: =IF(Downloads_maandcijfers!CI3695=0, "", Downloads_maandcijfers!CI3695) | CJ232: =IF(Downloads_maandcijfers!CJ3695=0, "", Downloads_maandcijfers!CJ3695) | CK232: =IF(Downloads_maandcijfers!CK3695=0, "", Downloads_maandcijfers!CK3695) | CL232: =IF(Downloads_maandcijfers!CL3695=0, "", Downloads_maandcijfers!CL3695) | CM232: =IF(Downloads_maandcijfers!CM3695=0, "", Downloads_maandcijfers!CM3695)
A233: 37347 | B233: =IF(Downloads_maandcijfers!B236="", "", Downloads_maandcijfers!B236) -> 26.98 | C233: =IF(Downloads_maandcijfers!C236="", "", Downloads_maandcijfers!C236) -> 1.1098 | D233: =IF(Downloads_maandcijfers!D236="", "", Downloads_maandcijfers!D236) -> 88.566104 | E233: =IF(Downloads_maandcijfers!E236="", "", Downloads_maandcijfers!E236) -> 108.53879 | F233: =IF(Downloads_maandcijfers!F236="", "", Downloads_maandcijfers!F236) -> 21.91 | G233: =IF(Downloads_maandcijfers!G236="", "", Downloads_maandcijfers!G236) -> 5.15 | H233: =IF(Downloads_maandcijfers!H236="", "", Downloads_maandcijfers!H236) -> 5.11 | I233: =IF(Downloads_maandcijfers!I236="", "", Downloads_maandcijfers!I236) -> 5.36 | ... BI233: =IF(Downloads_maandcijfers!BI236="", "", Downloads_maandcijfers!BI236) -> 64.605855 | BK233: =IF(Downloads_maandcijfers!BK236="", "", Downloads_maandcijfers!BK236) | BL233: 50.5 | BM233: =IF(Downloads_maandcijfers!BM236="", "", Downloads_maandcijfers!BM236) -> 3.385 | BN233: =IF(Downloads_maandcijfers!BN236="", "", Downloads_maandcijfers!BN236) -> 5.21 | BO233: =IF(Downloads_maandcijfers!BO236="", "", Downloads_maandcijfers!BO236) -> 99.46628 | BP233: =IF(Downloads_maandcijfers!BP236="", "", Downloads_maandcijfers!BP236) -> 98.70612 | BQ233: =IF(Downloads_maandcijfers!BQ236="", "", Downloads_maandcijfers!BQ236) -> 99.69638 | BR233: =IF(Downloads_maandcijfers!BR236="", "", Downloads_maandcijfers!BR236) | BS233: =IF(Downloads_maandcijfers!BS236="", "", Downloads_maandcijfers!BS236) | BT233: =IF(Downloads_maandcijfers!BT236="", "", Downloads_maandcijfers!BT236) | ... CF233: =IF(Downloads_maandcijfers!CF236="", "", Downloads_maandcijfers!CF236) | CG233: =IF(Downloads_maandcijfers!CG3695="", "", Downloads_maandcijfers!CG3695) | CH233: =IF(Downloads_maandcijfers!CH3695="", "", Downloads_maandcijfers!CH3695) | CI233: =IF(Downloads_maandcijfers!CI3696=0, "", Downloads_maandcijfers!CI3696) | CJ233: =IF(Downloads_maandcijfers!CJ3696=0, "", Downloads_maandcijfers!CJ3696) | CK233: =IF(Downloads_maandcijfers!CK3696=0, "", Downloads_maandcijfers!CK3696) | CL233: =IF(Downloads_maandcijfers!CL3696=0, "", Downloads_maandcijfers!CL3696) | CM233: =IF(Downloads_maandcijfers!CM3696=0, "", Downloads_maandcijfers!CM3696)
... A469: 44531 | B469: =IF(Downloads_maandcijfers!B472="", "", Downloads_maandcijfers!B472) -> 77.24 | C469: =IF(Downloads_maandcijfers!C472="", "", Downloads_maandcijfers!C472) -> 0.8793 | D469: =IF(Downloads_maandcijfers!D472="", "", Downloads_maandcijfers!D472) -> 166.24266 | E469: =IF(Downloads_maandcijfers!E472="", "", Downloads_maandcijfers!E472) -> 298.15951 | F469: =IF(Downloads_maandcijfers!F472="", "", Downloads_maandcijfers!F472) -> 17.22 | G469: =IF(Downloads_maandcijfers!G472="", "", Downloads_maandcijfers!G472) -> -0.38 | H469: =IF(Downloads_maandcijfers!H472="", "", Downloads_maandcijfers!H472) -> 1.52 | I469: =IF(Downloads_maandcijfers!I472="", "", Downloads_maandcijfers!I472) -> 1.17 | ... BI469: =IF(Downloads_maandcijfers!BI472="", "", Downloads_maandcijfers!BI472) -> 101.35447 | BK469: =IF(Downloads_maandcijfers!BK472="", "", Downloads_maandcijfers!BK472) -> 70 | BL469: 58.7 | BM469: =IF(Downloads_maandcijfers!BM472="", "", Downloads_maandcijfers!BM472) -> -0.572 | BN469: =IF(Downloads_maandcijfers!BN472="", "", Downloads_maandcijfers!BN472) -> -0.03 | BO469: =IF(Downloads_maandcijfers!BO472="", "", Downloads_maandcijfers!BO472) -> 101.0752 | BP469: =IF(Downloads_maandcijfers!BP472="", "", Downloads_maandcijfers!BP472) -> 99.57385 | BQ469: =IF(Downloads_maandcijfers!BQ472="", "", Downloads_maandcijfers!BQ472) -> 101.9658 | BR469: =IF(Downloads_maandcijfers!BR472="", "", Downloads_maandcijfers!BR472) -> 328.67 | BS469: =IF(Downloads_maandcijfers!BS472="", "", Downloads_maandcijfers!BS472) -> 150.51 | BT469: =IF(Downloads_maandcijfers!BT472="", "", Downloads_maandcijfers!BT472) -> 150.65 | ... CF469: =IF(Downloads_maandcijfers!CF472="", "", Downloads_maandcijfers!CF472) -> 1.65 | CG469: =IF(Downloads_maandcijfers!CG3931="", "", Downloads_maandcijfers!CG3931) | CH469: =IF(Downloads_maandcijfers!CH3931="", "", Downloads_maandcijfers!CH3931) | CI469: =IF(Downloads_maandcijfers!CI3932=0, "", Downloads_maandcijfers!CI3932) | CJ469: =IF(Downloads_maandcijfers!CJ3932=0, "", Downloads_maandcijfers!CJ3932) | CK469: =IF(Downloads_maandcijfers!CK3932=0, "", Downloads_maandcijfers!CK3932) | CL469: =IF(Downloads_maandcijfers!CL3932=0, "", Downloads_maandcijfers!CL3932) | CM469: =IF(Downloads_maandcijfers!CM3932=0, "", Downloads_maandcijfers!CM3932)
A470: 44562 | B470: =IF(Downloads_maandcijfers!B473="", "", Downloads_maandcijfers!B473) -> 92.35 | C470: =IF(Downloads_maandcijfers!C473="", "", Downloads_maandcijfers!C473) -> 0.8919 | D470: =IF(Downloads_maandcijfers!D473="", "", Downloads_maandcijfers!D473) -> 139.23758 | E470: =IF(Downloads_maandcijfers!E473="", "", Downloads_maandcijfers!E473) -> 264.63419 | F470: =IF(Downloads_maandcijfers!F473="", "", Downloads_maandcijfers!F473) -> 24.83 | G470: =IF(Downloads_maandcijfers!G473="", "", Downloads_maandcijfers!G473) -> -0.12 | H470: =IF(Downloads_maandcijfers!H473="", "", Downloads_maandcijfers!H473) -> 1.79 | I470: =IF(Downloads_maandcijfers!I473="", "", Downloads_maandcijfers!I473) -> 1.35 | ... BK470: =IF(Downloads_maandcijfers!BK473="", "", Downloads_maandcijfers!BK473) -> 84 | BL470: 60.1 | BM470: =IF(Downloads_maandcijfers!BM473="", "", Downloads_maandcijfers!BM473) -> -0.552 | BN470: =IF(Downloads_maandcijfers!BN473="", "", Downloads_maandcijfers!BN473) -> 0.14 | BO470: =IF(Downloads_maandcijfers!BO473="", "", Downloads_maandcijfers!BO473) -> 100.9829 | BP470: =IF(Downloads_maandcijfers!BP473="", "", Downloads_maandcijfers!BP473) -> 99.29681 | BQ470: =IF(Downloads_maandcijfers!BQ473="", "", Downloads_maandcijfers!BQ473) -> 101.5629 | BR470: =IF(Downloads_maandcijfers!BR473="", "", Downloads_maandcijfers!BR473) -> 297.46 | BS470: =IF(Downloads_maandcijfers!BS473="", "", Downloads_maandcijfers!BS473) -> 159.38 | BT470: =IF(Downloads_maandcijfers!BT473="", "", Downloads_maandcijfers!BT473) -> 161.48 | ... CF470: =IF(Downloads_maandcijfers!CF473="", "", Downloads_maandcijfers!CF473) -> 1.67 | CG470: =IF(Downloads_maandcijfers!CG3932="", "", Downloads_maandcijfers!CG3932) | CH470: =IF(Downloads_maandcijfers!CH3932="", "", Downloads_maandcijfers!CH3932) | CI470: =IF(Downloads_maandcijfers!CI3933=0, "", Downloads_maandcijfers!CI3933) | CJ470: =IF(Downloads_maandcijfers!CJ3933=0, "", Downloads_maandcijfers!CJ3933) | CK470: =IF(Downloads_maandcijfers!CK3933=0, "", Downloads_maandcijfers!CK3933) | CL470: =IF(Downloads_maandcijfers!CL3933=0, "", Downloads_maandcijfers!CL3933) | CM470: =IF(Downloads_maandcijfers!CM3933=0, "", Downloads_maandcijfers!CM3933)
A471: 44593 | B471: =IF(Downloads_maandcijfers!B474="", "", Downloads_maandcijfers!B474) -> 103.08 | C471: =IF(Downloads_maandcijfers!C474="", "", Downloads_maandcijfers!C474) -> 0.8904 | D471: =IF(Downloads_maandcijfers!D474="", "", Downloads_maandcijfers!D474) -> 138.05353 | E471: =IF(Downloads_maandcijfers!E474="", "", Downloads_maandcijfers!E474) -> 220.46791 | F471: =IF(Downloads_maandcijfers!F474="", "", Downloads_maandcijfers!F474) -> 30.15 | G471: =IF(Downloads_maandcijfers!G474="", "", Downloads_maandcijfers!G474) -> 0.15 | H471: =IF(Downloads_maandcijfers!H474="", "", Downloads_maandcijfers!H474) -> 1.83 | I471: =IF(Downloads_maandcijfers!I474="", "", Downloads_maandcijfers!I474) -> 1.76 | ... BK471: =IF(Downloads_maandcijfers!BK474="", "", Downloads_maandcijfers!BK474) -> 100.5 | BL471: 60.6 | BM471: =IF(Downloads_maandcijfers!BM474="", "", Downloads_maandcijfers!BM474) -> -0.533 | BN471: =IF(Downloads_maandcijfers!BN474="", "", Downloads_maandcijfers!BN474) -> 0.4 | BO471: =IF(Downloads_maandcijfers!BO474="", "", Downloads_maandcijfers!BO474) -> 100.8373 | BP471: =IF(Downloads_maandcijfers!BP474="", "", Downloads_maandcijfers!BP474) -> 98.97958 | BQ471: =IF(Downloads_maandcijfers!BQ474="", "", Downloads_maandcijfers!BQ474) -> 101.0584 | BR471: =IF(Downloads_maandcijfers!BR474="", "", Downloads_maandcijfers!BR474) -> 305.61 | BS471: =IF(Downloads_maandcijfers!BS474="", "", Downloads_maandcijfers!BS474) -> 168.17 | BT471: =IF(Downloads_maandcijfers!BT474="", "", Downloads_maandcijfers!BT474) -> 169.65 | ... CF471: =IF(Downloads_maandcijfers!CF474="", "", Downloads_maandcijfers!CF474) -> 1.67 | CG471: =IF(Downloads_maandcijfers!CG3933="", "", Downloads_maandcijfers!CG3933) | CH471: =IF(Downloads_maandcijfers!CH3933="", "", Downloads_maandcijfers!CH3933) | CI471: =IF(Downloads_maandcijfers!CI3934=0, "", Downloads_maandcijfers!CI3934) | CJ471: =IF(Downloads_maandcijfers!CJ3934=0, "", Downloads_maandcijfers!CJ3934) | CK471: =IF(Downloads_maandcijfers!CK3934=0, "", Downloads_maandcijfers!CK3934) | CL471: =IF(Downloads_maandcijfers!CL3934=0, "", Downloads_maandcijfers!CL3934) | CM471: =IF(Downloads_maandcijfers!CM3934=0, "", Downloads_maandcijfers!CM3934)
A472: 44621 | B472: =IF(Downloads_maandcijfers!B475="", "", Downloads_maandcijfers!B475) -> 107.29 | C472: =IF(Downloads_maandcijfers!C475="", "", Downloads_maandcijfers!C475) -> 0.8993 | D472: =IF(Downloads_maandcijfers!D475="", "", Downloads_maandcijfers!D475) -> 190.01241 | E472: =IF(Downloads_maandcijfers!E475="", "", Downloads_maandcijfers!E475) -> 392.01202 | F472: =IF(Downloads_maandcijfers!F475="", "", Downloads_maandcijfers!F475) -> 20.56 | G472: =IF(Downloads_maandcijfers!G475="", "", Downloads_maandcijfers!G475) -> 0.28 | H472: =IF(Downloads_maandcijfers!H475="", "", Downloads_maandcijfers!H475) -> 2.32 | I472: =IF(Downloads_maandcijfers!I475="", "", Downloads_maandcijfers!I475) -> 2.04 | ... BK472: =IF(Downloads_maandcijfers!BK475="", "", Downloads_maandcijfers!BK475) -> 125 | BL472: 58.4 | BM472: =IF(Downloads_maandcijfers!BM475="", "", Downloads_maandcijfers!BM475) -> -0.458 | BN472: =IF(Downloads_maandcijfers!BN475="", "", Downloads_maandcijfers!BN475) -> 0.8 | BO472: =IF(Downloads_maandcijfers!BO475="", "", Downloads_maandcijfers!BO475) -> 100.6289 | BP472: =IF(Downloads_maandcijfers!BP475="", "", Downloads_maandcijfers!BP475) -> 98.64712 | BQ472: =IF(Downloads_maandcijfers!BQ475="", "", Downloads_maandcijfers!BQ475) -> 100.4931 | BR472: =IF(Downloads_maandcijfers!BR475="", "", Downloads_maandcijfers!BR475) -> 426.93 | BS472: =IF(Downloads_maandcijfers!BS475="", "", Downloads_maandcijfers!BS475) -> 188.83 | BT472: =IF(Downloads_maandcijfers!BT475="", "", Downloads_maandcijfers!BT475) -> 192.72 | ... CF472: =IF(Downloads_maandcijfers!CF475="", "", Downloads_maandcijfers!CF475) -> 1.77 | CG472: =IF(Downloads_maandcijfers!CG3934="", "", Downloads_maandcijfers!CG3934) | CH472: =IF(Downloads_maandcijfers!CH3934="", "", Downloads_maandcijfers!CH3934) | CI472: =IF(Downloads_maandcijfers!CI3935=0, "", Downloads_maandcijfers!CI3935) | CJ472: =IF(Downloads_maandcijfers!CJ3935=0, "", Downloads_maandcijfers!CJ3935) | CK472: =IF(Downloads_maandcijfers!CK3935=0, "", Downloads_maandcijfers!CK3935) | CL472: =IF(Downloads_maandcijfers!CL3935=0, "", Downloads_maandcijfers!CL3935) | CM472: =IF(Downloads_maandcijfers!CM3935=0, "", Downloads_maandcijfers!CM3935)
A473: 44652 | B473: =IF(Downloads_maandcijfers!B476="", "", Downloads_maandcijfers!B476) -> 108.36 | C473: =IF(Downloads_maandcijfers!C476="", "", Downloads_maandcijfers!C476) -> 0.9481 | D473: =IF(Downloads_maandcijfers!D476="", "", Downloads_maandcijfers!D476) -> 154.66196 | E473: =IF(Downloads_maandcijfers!E476="", "", Downloads_maandcijfers!E476) -> 334.669 | F473: =IF(Downloads_maandcijfers!F476="", "", Downloads_maandcijfers!F476) -> 33.4 | G473: =IF(Downloads_maandcijfers!G476="", "", Downloads_maandcijfers!G476) -> 0.75 | H473: =IF(Downloads_maandcijfers!H476="", "", Downloads_maandcijfers!H476) -> 2.89 | I473: =IF(Downloads_maandcijfers!I476="", "", Downloads_maandcijfers!I476) -> 2.78 | ... BK473: =IF(Downloads_maandcijfers!BK476="", "", Downloads_maandcijfers!BK476) -> 98.5 | BL473: 59.9 | BM473: =IF(Downloads_maandcijfers!BM476="", "", Downloads_maandcijfers!BM476) -> -0.429 | BN473: =IF(Downloads_maandcijfers!BN476="", "", Downloads_maandcijfers!BN476) -> 1.22 | BO473: =IF(Downloads_maandcijfers!BO476="", "", Downloads_maandcijfers!BO476) -> 100.3607 | BP473: =IF(Downloads_maandcijfers!BP476="", "", Downloads_maandcijfers!BP476) -> 98.33479 | BQ473: =IF(Downloads_maandcijfers!BQ476="", "", Downloads_maandcijfers!BQ476) -> 99.94083 | BR473: =IF(Downloads_maandcijfers!BR476="", "", Downloads_maandcijfers!BR476) -> 369.34 | BS473: =IF(Downloads_maandcijfers!BS476="", "", Downloads_maandcijfers!BS476) -> 189.69 | BT473: =IF(Downloads_maandcijfers!BT476="", "", Downloads_maandcijfers!BT476) -> 191.59 | ... CF473: =IF(Downloads_maandcijfers!CF476="", "", Downloads_maandcijfers!CF476) -> 1.88 | CG473: =IF(Downloads_maandcijfers!CG3935="", "", Downloads_maandcijfers!CG3935) | CH473: =IF(Downloads_maandcijfers!CH3935="", "", Downloads_maandcijfers!CH3935) | CI473: =IF(Downloads_maandcijfers!CI3936=0, "", Downloads_maandcijfers!CI3936) | CJ473: =IF(Downloads_maandcijfers!CJ3936=0, "", Downloads_maandcijfers!CJ3936) | CK473: =IF(Downloads_maandcijfers!CK3936=0, "", Downloads_maandcijfers!CK3936) | CL473: =IF(Downloads_maandcijfers!CL3936=0, "", Downloads_maandcijfers!CL3936) | CM473: =IF(Downloads_maandcijfers!CM3936=0, "", Downloads_maandcijfers!CM3936)
A474: 44682 | B474: =IF(Downloads_maandcijfers!B477="", "", Downloads_maandcijfers!B477) -> 125.53 | C474: =IF(Downloads_maandcijfers!C477="", "", Downloads_maandcijfers!C477) -> 0.9333 | D474: =IF(Downloads_maandcijfers!D477="", "", Downloads_maandcijfers!D477) -> 168.00082 | E474: =IF(Downloads_maandcijfers!E477="", "", Downloads_maandcijfers!E477) -> 328.47521 | F474: =IF(Downloads_maandcijfers!F477="", "", Downloads_maandcijfers!F477) -> 26.19 | G474: =IF(Downloads_maandcijfers!G477="", "", Downloads_maandcijfers!G477) -> 0.95 | H474: =IF(Downloads_maandcijfers!H477="", "", Downloads_maandcijfers!H477) -> 2.85 | I474: =IF(Downloads_maandcijfers!I477="", "", Downloads_maandcijfers!I477) -> 3.15 | ... BK474: =IF(Downloads_maandcijfers!BK477="", "", Downloads_maandcijfers!BK477) -> 90.61 | BL474: 57.8 | BM474: =IF(Downloads_maandcijfers!BM477="", "", Downloads_maandcijfers!BM477) -> -0.338 | BN474: =IF(Downloads_maandcijfers!BN477="", "", Downloads_maandcijfers!BN477) -> 1.42 | BO474: =IF(Downloads_maandcijfers!BO477="", "", Downloads_maandcijfers!BO477) -> 100.0422 | BP474: =IF(Downloads_maandcijfers!BP477="", "", Downloads_maandcijfers!BP477) -> 98.07478 | BQ474: =IF(Downloads_maandcijfers!BQ477="", "", Downloads_maandcijfers!BQ477) -> 99.4334 | BR474: =IF(Downloads_maandcijfers!BR477="", "", Downloads_maandcijfers!BR477) -> 359.5 | BS474: =IF(Downloads_maandcijfers!BS477="", "", Downloads_maandcijfers!BS477) -> 177.97 | BT474: =IF(Downloads_maandcijfers!BT477="", "", Downloads_maandcijfers!BT477) -> 172.82 | ... CF474: =IF(Downloads_maandcijfers!CF477="", "", Downloads_maandcijfers!CF477) -> 2.03 | CG474: =IF(Downloads_maandcijfers!CG3936="", "", Downloads_maandcijfers!CG3936) | CH474: =IF(Downloads_maandcijfers!CH3936="", "", Downloads_maandcijfers!CH3936) | CI474: =IF(Downloads_maandcijfers!CI3937=0, "", Downloads_maandcijfers!CI3937) | CJ474: =IF(Downloads_maandcijfers!CJ3937=0, "", Downloads_maandcijfers!CJ3937) | CK474: =IF(Downloads_maandcijfers!CK3937=0, "", Downloads_maandcijfers!CK3937) | CL474: =IF(Downloads_maandcijfers!CL3937=0, "", Downloads_maandcijfers!CL3937) | CM474: =IF(Downloads_maandcijfers!CM3937=0, "", Downloads_maandcijfers!CM3937)
A475: 44713 | B475: =IF(Downloads_maandcijfers!B478="", "", Downloads_maandcijfers!B478) -> 119.78 | C475: =IF(Downloads_maandcijfers!C478="", "", Downloads_maandcijfers!C478) -> 0.9568 | D475: =IF(Downloads_maandcijfers!D478="", "", Downloads_maandcijfers!D478) -> 145.97594 | E475: =IF(Downloads_maandcijfers!E478="", "", Downloads_maandcijfers!E478) -> 332.62825 | F475: =IF(Downloads_maandcijfers!F478="", "", Downloads_maandcijfers!F478) -> 28.71 | G475: =IF(Downloads_maandcijfers!G478="", "", Downloads_maandcijfers!G478) -> 1.45 | H475: =IF(Downloads_maandcijfers!H478="", "", Downloads_maandcijfers!H478) -> 2.98 | I475: =IF(Downloads_maandcijfers!I478="", "", Downloads_maandcijfers!I478) -> 3.31 | ... BK475: =IF(Downloads_maandcijfers!BK478="", "", Downloads_maandcijfers!BK478) -> 145 | BL475: 55.9 | BM475: =IF(Downloads_maandcijfers!BM478="", "", Downloads_maandcijfers!BM478) -> -0.195 | BN475: =IF(Downloads_maandcijfers!BN478="", "", Downloads_maandcijfers!BN478) -> 1.73 | BO475: =IF(Downloads_maandcijfers!BO478="", "", Downloads_maandcijfers!BO478) -> 99.72228 | BP475: =IF(Downloads_maandcijfers!BP478="", "", Downloads_maandcijfers!BP478) -> 97.88691 | BQ475: =IF(Downloads_maandcijfers!BQ478="", "", Downloads_maandcijfers!BQ478) -> 98.97704 | BR475: =IF(Downloads_maandcijfers!BR478="", "", Downloads_maandcijfers!BR478) -> 389.92 | BS475: =IF(Downloads_maandcijfers!BS478="", "", Downloads_maandcijfers!BS478) -> 165.34 | BT475: =IF(Downloads_maandcijfers!BT478="", "", Downloads_maandcijfers!BT478) -> 156.94 | ... CF475: =IF(Downloads_maandcijfers!CF478="", "", Downloads_maandcijfers!CF478) -> 2.21 | CG475: =IF(Downloads_maandcijfers!CG3937="", "", Downloads_maandcijfers!CG3937) | CH475: =IF(Downloads_maandcijfers!CH3937="", "", Downloads_maandcijfers!CH3937) | CI475: =IF(Downloads_maandcijfers!CI3938=0, "", Downloads_maandcijfers!CI3938) | CJ475: =IF(Downloads_maandcijfers!CJ3938=0, "", Downloads_maandcijfers!CJ3938) | CK475: =IF(Downloads_maandcijfers!CK3938=0, "", Downloads_maandcijfers!CK3938) | CL475: =IF(Downloads_maandcijfers!CL3938=0, "", Downloads_maandcijfers!CL3938) | CM475: =IF(Downloads_maandcijfers!CM3938=0, "", Downloads_maandcijfers!CM3938)
A476: 44743 | B476: =IF(Downloads_maandcijfers!B479="", "", Downloads_maandcijfers!B479) -> 111.51 | C476: =IF(Downloads_maandcijfers!C479="", "", Downloads_maandcijfers!C479) -> 0.9808 | D476: =IF(Downloads_maandcijfers!D479="", "", Downloads_maandcijfers!D479) -> 186.92141 | E476: =IF(Downloads_maandcijfers!E479="", "", Downloads_maandcijfers!E479) -> 403.90579 | F476: =IF(Downloads_maandcijfers!F479="", "", Downloads_maandcijfers!F479) -> 21.33 | G476: =IF(Downloads_maandcijfers!G479="", "", Downloads_maandcijfers!G479) -> 1.08 | H476: =IF(Downloads_maandcijfers!H479="", "", Downloads_maandcijfers!H479) -> 2.67 | I476: =IF(Downloads_maandcijfers!I479="", "", Downloads_maandcijfers!I479) -> 3.18 | ... BK476: =IF(Downloads_maandcijfers!BK479="", "", Downloads_maandcijfers!BK479) -> 191.15 | BL476: 54.5 | BM476: =IF(Downloads_maandcijfers!BM479="", "", Downloads_maandcijfers!BM479) -> 0.232 | BN476: =IF(Downloads_maandcijfers!BN479="", "", Downloads_maandcijfers!BN479) -> 1.15 | BO476: =IF(Downloads_maandcijfers!BO479="", "", Downloads_maandcijfers!BO479) -> 99.45039 | BP476: =IF(Downloads_maandcijfers!BP479="", "", Downloads_maandcijfers!BP479) -> 97.77533 | BQ476: =IF(Downloads_maandcijfers!BQ479="", "", Downloads_maandcijfers!BQ479) -> 98.58908 | BR476: =IF(Downloads_maandcijfers!BR479="", "", Downloads_maandcijfers!BR479) -> 485.61 | BS476: =IF(Downloads_maandcijfers!BS479="", "", Downloads_maandcijfers!BS479) -> 153.28 | BT476: =IF(Downloads_maandcijfers!BT479="", "", Downloads_maandcijfers!BT479) -> 145.18 | ... CF476: =IF(Downloads_maandcijfers!CF479="", "", Downloads_maandcijfers!CF479) -> 2.43 | CG476: =IF(Downloads_maandcijfers!CG3938="", "", Downloads_maandcijfers!CG3938) | CH476: =IF(Downloads_maandcijfers!CH3938="", "", Downloads_maandcijfers!CH3938) | CI476: =IF(Downloads_maandcijfers!CI3939=0, "", Downloads_maandcijfers!CI3939) | CJ476: =IF(Downloads_maandcijfers!CJ3939=0, "", Downloads_maandcijfers!CJ3939) | CK476: =IF(Downloads_maandcijfers!CK3939=0, "", Downloads_maandcijfers!CK3939) | CL476: =IF(Downloads_maandcijfers!CL3939=0, "", Downloads_maandcijfers!CL3939) | CM476: =IF(Downloads_maandcijfers!CM3939=0, "", Downloads_maandcijfers!CM3939)
A477: 44774 | B477: =IF(Downloads_maandcijfers!B480="", "", Downloads_maandcijfers!B480) -> 96.55 | C477: =IF(Downloads_maandcijfers!C480="", "", Downloads_maandcijfers!C480) -> 0.9947 | D477: =IF(Downloads_maandcijfers!D480="", "", Downloads_maandcijfers!D480) -> 163.23981 | E477: =IF(Downloads_maandcijfers!E480="", "", Downloads_maandcijfers!E480) -> 327.91541 | F477: =IF(Downloads_maandcijfers!F480="", "", Downloads_maandcijfers!F480) -> 25.87 | G477: =IF(Downloads_maandcijfers!G480="", "", Downloads_maandcijfers!G480) -> 1.03 | H477: =IF(Downloads_maandcijfers!H480="", "", Downloads_maandcijfers!H480) -> 3.15 | I477: =IF(Downloads_maandcijfers!I480="", "", Downloads_maandcijfers!I480) -> 3.88 | ... BK477: =IF(Downloads_maandcijfers!BK480="", "", Downloads_maandcijfers!BK480) -> 235 | BL477: 52.6 | BM477: =IF(Downloads_maandcijfers!BM480="", "", Downloads_maandcijfers!BM480) -> 0.654 | BN477: =IF(Downloads_maandcijfers!BN480="", "", Downloads_maandcijfers!BN480) -> 1.86 | BO477: =IF(Downloads_maandcijfers!BO480="", "", Downloads_maandcijfers!BO480) -> 99.24092 | BP477: =IF(Downloads_maandcijfers!BP480="", "", Downloads_maandcijfers!BP480) -> 97.76255 | BQ477: =IF(Downloads_maandcijfers!BQ480="", "", Downloads_maandcijfers!BQ480) -> 98.29344 | BR477: =IF(Downloads_maandcijfers!BR480="", "", Downloads_maandcijfers!BR480) -> 580.79 | BS477: =IF(Downloads_maandcijfers!BS480="", "", Downloads_maandcijfers!BS480) -> 156.79 | BT477: =IF(Downloads_maandcijfers!BT480="", "", Downloads_maandcijfers!BT480) -> 149.71 | ... CF477: =IF(Downloads_maandcijfers!CF480="", "", Downloads_maandcijfers!CF480) -> 2.66 | CG477: =IF(Downloads_maandcijfers!CG3939="", "", Downloads_maandcijfers!CG3939) | CH477: =IF(Downloads_maandcijfers!CH3939="", "", Downloads_maandcijfers!CH3939) | CI477: =IF(Downloads_maandcijfers!CI3940=0, "", Downloads_maandcijfers!CI3940) | CJ477: =IF(Downloads_maandcijfers!CJ3940=0, "", Downloads_maandcijfers!CJ3940) | CK477: =IF(Downloads_maandcijfers!CK3940=0, "", Downloads_maandcijfers!CK3940) | CL477: =IF(Downloads_maandcijfers!CL3940=0, "", Downloads_maandcijfers!CL3940) | CM477: =IF(Downloads_maandcijfers!CM3940=0, "", Downloads_maandcijfers!CM3940)
A478: 44805 | B478: =IF(Downloads_maandcijfers!B481="", "", Downloads_maandcijfers!B481) -> 88.9 | C478: =IF(Downloads_maandcijfers!C481="", "", Downloads_maandcijfers!C481) -> 1.0205 | D478: =IF(Downloads_maandcijfers!D481="", "", Downloads_maandcijfers!D481) -> 174.18347 | E478: =IF(Downloads_maandcijfers!E481="", "", Downloads_maandcijfers!E481) -> 396.80379 | F478: =IF(Downloads_maandcijfers!F481="", "", Downloads_maandcijfers!F481) -> 31.62 | G478: =IF(Downloads_maandcijfers!G481="", "", Downloads_maandcijfers!G481) -> 1.8 | H478: =IF(Downloads_maandcijfers!H481="", "", Downloads_maandcijfers!H481) -> 3.83 | I478: =IF(Downloads_maandcijfers!I481="", "", Downloads_maandcijfers!I481) -> 4.51 | ... BK478: =IF(Downloads_maandcijfers!BK481="", "", Downloads_maandcijfers!BK481) -> 161 | BL478: 49 | BM478: =IF(Downloads_maandcijfers!BM481="", "", Downloads_maandcijfers!BM481) -> 1.173 | BN478: =IF(Downloads_maandcijfers!BN481="", "", Downloads_maandcijfers!BN481) -> 2.43 | BO478: =IF(Downloads_maandcijfers!BO481="", "", Downloads_maandcijfers!BO481) -> 99.07808 | BP478: =IF(Downloads_maandcijfers!BP481="", "", Downloads_maandcijfers!BP481) -> 97.85403 | BQ478: =IF(Downloads_maandcijfers!BQ481="", "", Downloads_maandcijfers!BQ481) -> 98.10809 | BR478: =IF(Downloads_maandcijfers!BR481="", "", Downloads_maandcijfers!BR481) -> 504.18 | BS478: =IF(Downloads_maandcijfers!BS481="", "", Downloads_maandcijfers!BS481) -> 154.56 | BT478: =IF(Downloads_maandcijfers!BT481="", "", Downloads_maandcijfers!BT481) -> 144.36 | ... CF478: =IF(Downloads_maandcijfers!CF481="", "", Downloads_maandcijfers!CF481) -> 2.85 | CG478: =IF(Downloads_maandcijfers!CG3940="", "", Downloads_maandcijfers!CG3940) | CH478: =IF(Downloads_maandcijfers!CH3940="", "", Downloads_maandcijfers!CH3940) | CI478: =IF(Downloads_maandcijfers!CI3941=0, "", Downloads_maandcijfers!CI3941) | CJ478: =IF(Downloads_maandcijfers!CJ3941=0, "", Downloads_maandcijfers!CJ3941) | CK478: =IF(Downloads_maandcijfers!CK3941=0, "", Downloads_maandcijfers!CK3941) | CL478: =IF(Downloads_maandcijfers!CL3941=0, "", Downloads_maandcijfers!CL3941) | CM478: =IF(Downloads_maandcijfers!CM3941=0, "", Downloads_maandcijfers!CM3941)
A479: 44835 | B479: =IF(Downloads_maandcijfers!B482="", "", Downloads_maandcijfers!B482) -> 93.3 | C479: =IF(Downloads_maandcijfers!C482="", "", Downloads_maandcijfers!C482) -> 1.0117 | D479: =IF(Downloads_maandcijfers!D482="", "", Downloads_maandcijfers!D482) -> 177.42313 | E479: =IF(Downloads_maandcijfers!E482="", "", Downloads_maandcijfers!E482) -> 418.61884 | F479: =IF(Downloads_maandcijfers!F482="", "", Downloads_maandcijfers!F482) -> 25.88 | G479: =IF(Downloads_maandcijfers!G482="", "", Downloads_maandcijfers!G482) -> 2.19 | H479: =IF(Downloads_maandcijfers!H482="", "", Downloads_maandcijfers!H482) -> 4.1 | I479: =IF(Downloads_maandcijfers!I482="", "", Downloads_maandcijfers!I482) -> 4.3 | ... BK479: =IF(Downloads_maandcijfers!BK482="", "", Downloads_maandcijfers!BK482) -> 34.75 | BL479: 47.9 | BM479: =IF(Downloads_maandcijfers!BM482="", "", Downloads_maandcijfers!BM482) -> 1.704 | BN479: =IF(Downloads_maandcijfers!BN482="", "", Downloads_maandcijfers!BN482) -> 2.43 | BO479: =IF(Downloads_maandcijfers!BO482="", "", Downloads_maandcijfers!BO482) -> 98.94864 | BP479: =IF(Downloads_maandcijfers!BP482="", "", Downloads_maandcijfers!BP482) -> 98.04763 | BQ479: =IF(Downloads_maandcijfers!BQ482="", "", Downloads_maandcijfers!BQ482) -> 98.06408 | BR479: =IF(Downloads_maandcijfers!BR482="", "", Downloads_maandcijfers!BR482) -> 311.05 | BS479: =IF(Downloads_maandcijfers!BS482="", "", Downloads_maandcijfers!BS482) -> 151.89 | BT479: =IF(Downloads_maandcijfers!BT482="", "", Downloads_maandcijfers!BT482) -> 142.21 | ... CF479: =IF(Downloads_maandcijfers!CF482="", "", Downloads_maandcijfers!CF482) -> 3.06 | CG479: =IF(Downloads_maandcijfers!CG3941="", "", Downloads_maandcijfers!CG3941) | CH479: =IF(Downloads_maandcijfers!CH3941="", "", Downloads_maandcijfers!CH3941) | CI479: =IF(Downloads_maandcijfers!CI3942=0, "", Downloads_maandcijfers!CI3942) | CJ479: =IF(Downloads_maandcijfers!CJ3942=0, "", Downloads_maandcijfers!CJ3942) | CK479: =IF(Downloads_maandcijfers!CK3942=0, "", Downloads_maandcijfers!CK3942) | CL479: =IF(Downloads_maandcijfers!CL3942=0, "", Downloads_maandcijfers!CL3942) | CM479: =IF(Downloads_maandcijfers!CM3942=0, "", Downloads_maandcijfers!CM3942)
A480: 44866 | B480: =IF(Downloads_maandcijfers!B483="", "", Downloads_maandcijfers!B483) -> 85.61 | C480: =IF(Downloads_maandcijfers!C483="", "", Downloads_maandcijfers!C483) -> 0.9709 | D480: =IF(Downloads_maandcijfers!D483="", "", Downloads_maandcijfers!D483) -> 171.73726 | E480: =IF(Downloads_maandcijfers!E483="", "", Downloads_maandcijfers!E483) -> 357.08668 | F480: =IF(Downloads_maandcijfers!F483="", "", Downloads_maandcijfers!F483) -> 20.58 | G480: =IF(Downloads_maandcijfers!G483="", "", Downloads_maandcijfers!G483) -> 2.07 | H480: =IF(Downloads_maandcijfers!H483="", "", Downloads_maandcijfers!H483) -> 3.68 | I480: =IF(Downloads_maandcijfers!I483="", "", Downloads_maandcijfers!I483) -> 3.87 | ... BK480: =IF(Downloads_maandcijfers!BK483="", "", Downloads_maandcijfers!BK483) -> 142.185 | BL480: 46 | BM480: =IF(Downloads_maandcijfers!BM483="", "", Downloads_maandcijfers!BM483) -> 1.973 | BN480: =IF(Downloads_maandcijfers!BN483="", "", Downloads_maandcijfers!BN483) -> 2.22 | BO480: =IF(Downloads_maandcijfers!BO483="", "", Downloads_maandcijfers!BO483) -> 98.84549 | BP480: =IF(Downloads_maandcijfers!BP483="", "", Downloads_maandcijfers!BP483) -> 98.35251 | BQ480: =IF(Downloads_maandcijfers!BQ483="", "", Downloads_maandcijfers!BQ483) -> 98.14977 | BR480: =IF(Downloads_maandcijfers!BR483="", "", Downloads_maandcijfers!BR483) -> 336.42 | BS480: =IF(Downloads_maandcijfers!BS483="", "", Downloads_maandcijfers!BS483) -> 147.78 | BT480: =IF(Downloads_maandcijfers!BT483="", "", Downloads_maandcijfers!BT483) -> 139.92 | ... CF480: =IF(Downloads_maandcijfers!CF483="", "", Downloads_maandcijfers!CF483) -> 3.22 | CG480: =IF(Downloads_maandcijfers!CG3942="", "", Downloads_maandcijfers!CG3942) | CH480: =IF(Downloads_maandcijfers!CH3942="", "", Downloads_maandcijfers!CH3942) | CI480: =IF(Downloads_maandcijfers!CI3943=0, "", Downloads_maandcijfers!CI3943) | CJ480: =IF(Downloads_maandcijfers!CJ3943=0, "", Downloads_maandcijfers!CJ3943) | CK480: =IF(Downloads_maandcijfers!CK3943=0, "", Downloads_maandcijfers!CK3943) | CL480: =IF(Downloads_maandcijfers!CL3943=0, "", Downloads_maandcijfers!CL3943) | CM480: =IF(Downloads_maandcijfers!CM3943=0, "", Downloads_maandcijfers!CM3943)
A481: 44896 | B481: =IF(Downloads_maandcijfers!B484="", "", Downloads_maandcijfers!B484) -> 82.82 | C481: =IF(Downloads_maandcijfers!C484="", "", Downloads_maandcijfers!C484) -> 0.9372 | D481: =IF(Downloads_maandcijfers!D484="", "", Downloads_maandcijfers!D484) -> 136.43315 | E481: =IF(Downloads_maandcijfers!E484="", "", Downloads_maandcijfers!E484) -> 279.6471 | F481: =IF(Downloads_maandcijfers!F484="", "", Downloads_maandcijfers!F484) -> 21.67 | G481: =IF(Downloads_maandcijfers!G484="", "", Downloads_maandcijfers!G484) -> 2.09 | H481: =IF(Downloads_maandcijfers!H484="", "", Downloads_maandcijfers!H484) -> 3.88 | I481: =IF(Downloads_maandcijfers!I484="", "", Downloads_maandcijfers!I484) -> 4.67 | ... BK481: =IF(Downloads_maandcijfers!BK484="", "", Downloads_maandcijfers!BK484) -> 70.128 | BL481: 48.6 | BM481: =IF(Downloads_maandcijfers!BM484="", "", Downloads_maandcijfers!BM484) -> 2.132 | BN481: =IF(Downloads_maandcijfers!BN484="", "", Downloads_maandcijfers!BN484) -> 2.9 | BO481: =IF(Downloads_maandcijfers!BO484="", "", Downloads_maandcijfers!BO484) -> 98.77307 | BP481: =IF(Downloads_maandcijfers!BP484="", "", Downloads_maandcijfers!BP484) -> 98.76288 | BQ481: =IF(Downloads_maandcijfers!BQ484="", "", Downloads_maandcijfers!BQ484) -> 98.31564 | BR481: =IF(Downloads_maandcijfers!BR484="", "", Downloads_maandcijfers!BR484) -> 350.96 | BS481: =IF(Downloads_maandcijfers!BS484="", "", Downloads_maandcijfers!BS484) -> 146.5 | BT481: =IF(Downloads_maandcijfers!BT484="", "", Downloads_maandcijfers!BT484) -> 141.46 | ... CF481: =IF(Downloads_maandcijfers!CF484="", "", Downloads_maandcijfers!CF484) -> 3.38 | CG481: =IF(Downloads_maandcijfers!CG3943="", "", Downloads_maandcijfers!CG3943) | CH481: =IF(Downloads_maandcijfers!CH3943="", "", Downloads_maandcijfers!CH3943) | CI481: =IF(Downloads_maandcijfers!CI3944=0, "", Downloads_maandcijfers!CI3944) | CJ481: =IF(Downloads_maandcijfers!CJ3944=0, "", Downloads_maandcijfers!CJ3944) | CK481: =IF(Downloads_maandcijfers!CK3944=0, "", Downloads_maandcijfers!CK3944) | CL481: =IF(Downloads_maandcijfers!CL3944=0, "", Downloads_maandcijfers!CL3944) | CM481: =IF(Downloads_maandcijfers!CM3944=0, "", Downloads_maandcijfers!CM3944)
... A500: 45474 | B500: =IF(Downloads_maandcijfers!B503="", "", Downloads_maandcijfers!B503) -> 81.39 | C500: =IF(Downloads_maandcijfers!C503="", "", Downloads_maandcijfers!C503) -> 0.9239 | D500: =IF(Downloads_maandcijfers!D503="", "", Downloads_maandcijfers!D503) -> 116.29613 | E500: =IF(Downloads_maandcijfers!E503="", "", Downloads_maandcijfers!E503) -> 361.85379 | F500: =IF(Downloads_maandcijfers!F503="", "", Downloads_maandcijfers!F503) -> 16.36 | G500: =IF(Downloads_maandcijfers!G503="", "", Downloads_maandcijfers!G503) -> 2.46 | H500: =IF(Downloads_maandcijfers!H503="", "", Downloads_maandcijfers!H503) -> 4.09 | I500: =IF(Downloads_maandcijfers!I503="", "", Downloads_maandcijfers!I503) -> 3.65 | ... BK500: =IF(Downloads_maandcijfers!BK503="", "", Downloads_maandcijfers!BK503) -> 35.131 | BL500: 49.2 | BM500: =IF(Downloads_maandcijfers!BM503="", "", Downloads_maandcijfers!BM503) -> 3.647 | BN500: =IF(Downloads_maandcijfers!BN503="", "", Downloads_maandcijfers!BN503) -> 2.59 | BO500: =IF(Downloads_maandcijfers!BO503="", "", Downloads_maandcijfers!BO503) -> 99.79372 | BP500: =IF(Downloads_maandcijfers!BP503="", "", Downloads_maandcijfers!BP503) -> 99.02969 | BQ500: =IF(Downloads_maandcijfers!BQ503="", "", Downloads_maandcijfers!BQ503) -> 100.0732 | BR500: =IF(Downloads_maandcijfers!BR503="", "", Downloads_maandcijfers!BR503) -> 207.24 | BS500: =IF(Downloads_maandcijfers!BS503="", "", Downloads_maandcijfers!BS503) -> 151.68 | BT500: =IF(Downloads_maandcijfers!BT503="", "", Downloads_maandcijfers!BT503) -> 138.12 | ... CF500: =IF(Downloads_maandcijfers!CF503="", "", Downloads_maandcijfers!CF503) -> 3.94 | CG500: =IF(Downloads_maandcijfers!CG3962="", "", Downloads_maandcijfers!CG3962) | CH500: =IF(Downloads_maandcijfers!CH3962="", "", Downloads_maandcijfers!CH3962) | CI500: =IF(Downloads_maandcijfers!CI3963=0, "", Downloads_maandcijfers!CI3963) | CJ500: =IF(Downloads_maandcijfers!CJ3963=0, "", Downloads_maandcijfers!CJ3963) | CK500: =IF(Downloads_maandcijfers!CK3963=0, "", Downloads_maandcijfers!CK3963) | CL500: =IF(Downloads_maandcijfers!CL3963=0, "", Downloads_maandcijfers!CL3963) | CM500: =IF(Downloads_maandcijfers!CM3963=0, "", Downloads_maandcijfers!CM3963)
A501: 45505 | B501: =IF(Downloads_maandcijfers!B504="", "", Downloads_maandcijfers!B504) -> 80.2 | C501: =IF(Downloads_maandcijfers!C504="", "", Downloads_maandcijfers!C504) -> 0.9036 | D501: =IF(Downloads_maandcijfers!D504="", "", Downloads_maandcijfers!D504) -> 112.31229 | E501: =IF(Downloads_maandcijfers!E504="", "", Downloads_maandcijfers!E504) -> 263.42825 | F501: =IF(Downloads_maandcijfers!F504="", "", Downloads_maandcijfers!F504) -> 15 | G501: =IF(Downloads_maandcijfers!G504="", "", Downloads_maandcijfers!G504) -> 2.21 | H501: =IF(Downloads_maandcijfers!H504="", "", Downloads_maandcijfers!H504) -> 3.91 | I501: =IF(Downloads_maandcijfers!I504="", "", Downloads_maandcijfers!I504) -> 3.67 | ... BK501: =IF(Downloads_maandcijfers!BK504="", "", Downloads_maandcijfers!BK504) -> 38.8 | BL501: 47.7 | BM501: =IF(Downloads_maandcijfers!BM504="", "", Downloads_maandcijfers!BM504) -> 3.49 | BN501: =IF(Downloads_maandcijfers!BN504="", "", Downloads_maandcijfers!BN504) -> 2.56 | BO501: =IF(Downloads_maandcijfers!BO504="", "", Downloads_maandcijfers!BO504) -> 99.87848 | BP501: =IF(Downloads_maandcijfers!BP504="", "", Downloads_maandcijfers!BP504) -> 98.9936 | BQ501: =IF(Downloads_maandcijfers!BQ504="", "", Downloads_maandcijfers!BQ504) -> 100.1238 | BR501: =IF(Downloads_maandcijfers!BR504="", "", Downloads_maandcijfers!BR504) -> 207.36 | BS501: =IF(Downloads_maandcijfers!BS504="", "", Downloads_maandcijfers!BS504) -> 145.29 | BT501: =IF(Downloads_maandcijfers!BT504="", "", Downloads_maandcijfers!BT504) -> 133.25 | ... CF501: =IF(Downloads_maandcijfers!CF504="", "", Downloads_maandcijfers!CF504) -> 3.92 | CG501: =IF(Downloads_maandcijfers!CG3963="", "", Downloads_maandcijfers!CG3963) | CH501: =IF(Downloads_maandcijfers!CH3963="", "", Downloads_maandcijfers!CH3963) | CI501: =IF(Downloads_maandcijfers!CI3963="", "", Downloads_maandcijfers!CI3963) | CJ501: =IF(Downloads_maandcijfers!CJ3963="", "", Downloads_maandcijfers!CJ3963) | CK501: =IF(Downloads_maandcijfers!CK3963="", "", Downloads_maandcijfers!CK3963) | CL501: =IF(Downloads_maandcijfers!CL3963="", "", Downloads_maandcijfers!CL3963) | CM501: =IF(Downloads_maandcijfers!CM3964=0, "", Downloads_maandcijfers!CM3964)
A502: 45536 | B502: =IF(Downloads_maandcijfers!B505="", "", Downloads_maandcijfers!B505) -> 72.35 | C502: =IF(Downloads_maandcijfers!C505="", "", Downloads_maandcijfers!C505) -> 0.896 | D502: =IF(Downloads_maandcijfers!D505="", "", Downloads_maandcijfers!D505) -> 105.89523 | E502: =IF(Downloads_maandcijfers!E505="", "", Downloads_maandcijfers!E505) -> 345.05096 | F502: =IF(Downloads_maandcijfers!F505="", "", Downloads_maandcijfers!F505) -> 16.73 | G502: =IF(Downloads_maandcijfers!G505="", "", Downloads_maandcijfers!G505) -> 2.17 | H502: =IF(Downloads_maandcijfers!H505="", "", Downloads_maandcijfers!H505) -> 3.81 | I502: =IF(Downloads_maandcijfers!I505="", "", Downloads_maandcijfers!I505) -> 3.37 | ... BK502: =IF(Downloads_maandcijfers!BK505="", "", Downloads_maandcijfers!BK505) -> 39.031 | BL502: 48.2 | BM502: =IF(Downloads_maandcijfers!BM505="", "", Downloads_maandcijfers!BM505) -> 3.279 | BN502: =IF(Downloads_maandcijfers!BN505="", "", Downloads_maandcijfers!BN505) -> 2.42 | BO502: =IF(Downloads_maandcijfers!BO505="", "", Downloads_maandcijfers!BO505) -> 100.0104 | BP502: =IF(Downloads_maandcijfers!BP505="", "", Downloads_maandcijfers!BP505) -> 99.0765 | BQ502: =IF(Downloads_maandcijfers!BQ505="", "", Downloads_maandcijfers!BQ505) -> 100.1491 | BR502: =IF(Downloads_maandcijfers!BR505="", "", Downloads_maandcijfers!BR505) -> 197.6 | BS502: =IF(Downloads_maandcijfers!BS505="", "", Downloads_maandcijfers!BS505) -> 146.51 | BT502: =IF(Downloads_maandcijfers!BT505="", "", Downloads_maandcijfers!BT505) -> 134.64 | ... CF502: =IF(Downloads_maandcijfers!CF505="", "", Downloads_maandcijfers!CF505) -> 3.89 | CG502: =IF(Downloads_maandcijfers!CG3964="", "", Downloads_maandcijfers!CG3964) | CH502: =IF(Downloads_maandcijfers!CH3964="", "", Downloads_maandcijfers!CH3964) | CI502: =IF(Downloads_maandcijfers!CI3964="", "", Downloads_maandcijfers!CI3964) | CJ502: =IF(Downloads_maandcijfers!CJ3964="", "", Downloads_maandcijfers!CJ3964) | CK502: =IF(Downloads_maandcijfers!CK3964="", "", Downloads_maandcijfers!CK3964) | CL502: =IF(Downloads_maandcijfers!CL3964="", "", Downloads_maandcijfers!CL3964) | CM502: =IF(Downloads_maandcijfers!CM3965=0, "", Downloads_maandcijfers!CM3965)
A503: 45566 | B503: =IF(Downloads_maandcijfers!B506="", "", Downloads_maandcijfers!B506) -> 73.25 | C503: =IF(Downloads_maandcijfers!C506="", "", Downloads_maandcijfers!C506) -> 0.9208 | D503: =IF(Downloads_maandcijfers!D506="", "", Downloads_maandcijfers!D506) -> 95.299966 | E503: =IF(Downloads_maandcijfers!E506="", "", Downloads_maandcijfers!E506) -> 392.07715 | F503: =IF(Downloads_maandcijfers!F506="", "", Downloads_maandcijfers!F506) -> 23.16 | G503: =IF(Downloads_maandcijfers!G506="", "", Downloads_maandcijfers!G506) -> 2.23 | H503: =IF(Downloads_maandcijfers!H506="", "", Downloads_maandcijfers!H506) -> 4.28 | I503: =IF(Downloads_maandcijfers!I506="", "", Downloads_maandcijfers!I506) -> 3.65 | ... BK503: =IF(Downloads_maandcijfers!BK506="", "", Downloads_maandcijfers!BK506) -> 40.101 | BL503: 47 | BM503: =IF(Downloads_maandcijfers!BM506="", "", Downloads_maandcijfers!BM506) -> 3.062 | BN503: =IF(Downloads_maandcijfers!BN506="", "", Downloads_maandcijfers!BN506) -> 2.64 | BO503: =IF(Downloads_maandcijfers!BO506="", "", Downloads_maandcijfers!BO506) -> 100.1684 | BP503: =IF(Downloads_maandcijfers!BP506="", "", Downloads_maandcijfers!BP506) -> 99.26118 | BQ503: =IF(Downloads_maandcijfers!BQ506="", "", Downloads_maandcijfers!BQ506) -> 100.162 | BR503: =IF(Downloads_maandcijfers!BR506="", "", Downloads_maandcijfers!BR506) -> 211.27 | BS503: =IF(Downloads_maandcijfers!BS506="", "", Downloads_maandcijfers!BS506) -> 153.98 | BT503: =IF(Downloads_maandcijfers!BT506="", "", Downloads_maandcijfers!BT506) -> 142.69 | ... CF503: =IF(Downloads_maandcijfers!CF506="", "", Downloads_maandcijfers!CF506) -> 3.77 | CG503: =IF(Downloads_maandcijfers!CG3965="", "", Downloads_maandcijfers!CG3965) | CH503: =IF(Downloads_maandcijfers!CH3965="", "", Downloads_maandcijfers!CH3965) | CI503: =IF(Downloads_maandcijfers!CI3965="", "", Downloads_maandcijfers!CI3965) | CJ503: =IF(Downloads_maandcijfers!CJ3965="", "", Downloads_maandcijfers!CJ3965) | CK503: =IF(Downloads_maandcijfers!CK3965="", "", Downloads_maandcijfers!CK3965) | CL503: =IF(Downloads_maandcijfers!CL3965="", "", Downloads_maandcijfers!CL3965) | CM503: =IF(Downloads_maandcijfers!CM3966=0, "", Downloads_maandcijfers!CM3966)
A504: 45597 | B504: =IF(Downloads_maandcijfers!B507="", "", Downloads_maandcijfers!B507) -> 74.16 | C504: =IF(Downloads_maandcijfers!C507="", "", Downloads_maandcijfers!C507) -> 0.9474 | D504: =IF(Downloads_maandcijfers!D507="", "", Downloads_maandcijfers!D507) -> 160.52062 | E504: =IF(Downloads_maandcijfers!E507="", "", Downloads_maandcijfers!E507) -> 479.98873 | F504: =IF(Downloads_maandcijfers!F507="", "", Downloads_maandcijfers!F507) -> 13.51 | G504: =IF(Downloads_maandcijfers!G507="", "", Downloads_maandcijfers!G507) -> 2.31 | H504: =IF(Downloads_maandcijfers!H507="", "", Downloads_maandcijfers!H507) -> 4.18 | I504: =IF(Downloads_maandcijfers!I507="", "", Downloads_maandcijfers!I507) -> 3.28 | ... BK504: =IF(Downloads_maandcijfers!BK507="", "", Downloads_maandcijfers!BK507) -> 47.25 | BL504: 46.6 | BM504: =IF(Downloads_maandcijfers!BM507="", "", Downloads_maandcijfers!BM507) -> 2.934 | BN504: =IF(Downloads_maandcijfers!BN507="", "", Downloads_maandcijfers!BN507) -> 2.33 | BO504: =IF(Downloads_maandcijfers!BO507="", "", Downloads_maandcijfers!BO507) -> 100.3267 | BP504: =IF(Downloads_maandcijfers!BP507="", "", Downloads_maandcijfers!BP507) -> 99.49578 | BQ504: =IF(Downloads_maandcijfers!BQ507="", "", Downloads_maandcijfers!BQ507) -> 100.1787 | BR504: =IF(Downloads_maandcijfers!BR507="", "", Downloads_maandcijfers!BR507) -> 220.53 | BS504: =IF(Downloads_maandcijfers!BS507="", "", Downloads_maandcijfers!BS507) -> 159.98 | BT504: =IF(Downloads_maandcijfers!BT507="", "", Downloads_maandcijfers!BT507) -> 142.5 | ... CF504: =IF(Downloads_maandcijfers!CF507="", "", Downloads_maandcijfers!CF507) -> 3.75
A505: 45627 | B505: =IF(Downloads_maandcijfers!B508="", "", Downloads_maandcijfers!B508) -> 74.58 | C505: =IF(Downloads_maandcijfers!C508="", "", Downloads_maandcijfers!C508) -> 0.961 | D505: =IF(Downloads_maandcijfers!D508="", "", Downloads_maandcijfers!D508) -> 156.89088 | E505: =IF(Downloads_maandcijfers!E508="", "", Downloads_maandcijfers!E508) -> 484.41531 | F505: =IF(Downloads_maandcijfers!F508="", "", Downloads_maandcijfers!F508) -> 17.35 | G505: =IF(Downloads_maandcijfers!G508="", "", Downloads_maandcijfers!G508) -> 2.18 | H505: =IF(Downloads_maandcijfers!H508="", "", Downloads_maandcijfers!H508) -> 4.58 | I505: =IF(Downloads_maandcijfers!I508="", "", Downloads_maandcijfers!I508) -> 3.52 | ... CF505: =IF(Downloads_maandcijfers!CF508="", "", Downloads_maandcijfers!CF508) -> 3.7
A506: 45658 | B506: =IF(Downloads_maandcijfers!B509="", "", Downloads_maandcijfers!B509) -> 77.11 | C506: =IF(Downloads_maandcijfers!C509="", "", Downloads_maandcijfers!C509) -> 0.9621 | D506: =IF(Downloads_maandcijfers!D509="", "", Downloads_maandcijfers!D509) -> 167.38864 | E506: =IF(Downloads_maandcijfers!E509="", "", Downloads_maandcijfers!E509) -> 479.90402 | F506: =IF(Downloads_maandcijfers!F509="", "", Downloads_maandcijfers!F509) -> 16.43 | G506: =IF(Downloads_maandcijfers!G509="", "", Downloads_maandcijfers!G509) -> 2.48 | H506: =IF(Downloads_maandcijfers!H509="", "", Downloads_maandcijfers!H509) -> 4.58 | I506: =IF(Downloads_maandcijfers!I509="", "", Downloads_maandcijfers!I509) -> 3.55 | ... CF506: =IF(Downloads_maandcijfers!CF509="", "", Downloads_maandcijfers!CF509) -> 2.98
A507: 45689 | B507: =IF(Downloads_maandcijfers!B510="", "", Downloads_maandcijfers!B510) -> 74.76 | C507: =IF(Downloads_maandcijfers!C510="", "", Downloads_maandcijfers!C510) -> 0.9613 | D507: =IF(Downloads_maandcijfers!D510="", "", Downloads_maandcijfers!D510) -> 228.61916 | E507: =IF(Downloads_maandcijfers!E510="", "", Downloads_maandcijfers!E510) -> 396.80715 | F507: =IF(Downloads_maandcijfers!F510="", "", Downloads_maandcijfers!F510) -> 19.63 | G507: =IF(Downloads_maandcijfers!G510="", "", Downloads_maandcijfers!G510) -> 2.41 | H507: =IF(Downloads_maandcijfers!H510="", "", Downloads_maandcijfers!H510) -> 4.24 | I507: =IF(Downloads_maandcijfers!I510="", "", Downloads_maandcijfers!I510) -> 3.47 | ... CF507: =IF(Downloads_maandcijfers!CF510="", "", Downloads_maandcijfers!CF510) -> 3.57
A508: 45717 | B508: =IF(Downloads_maandcijfers!B511="", "", Downloads_maandcijfers!B511) -> 77.23 | C508: =IF(Downloads_maandcijfers!C511="", "", Downloads_maandcijfers!C511) -> 0.9258 | D508: =IF(Downloads_maandcijfers!D511="", "", Downloads_maandcijfers!D511) -> 297.08402 | E508: =IF(Downloads_maandcijfers!E511="", "", Downloads_maandcijfers!E511) -> 576.93663 | F508: =IF(Downloads_maandcijfers!F511="", "", Downloads_maandcijfers!F511) -> 22.28 | G508: =IF(Downloads_maandcijfers!G511="", "", Downloads_maandcijfers!G511) -> 2.74 | H508: =IF(Downloads_maandcijfers!H511="", "", Downloads_maandcijfers!H511) -> 4.23 | I508: =IF(Downloads_maandcijfers!I511="", "", Downloads_maandcijfers!I511) -> 3.86 | ... CF508: =IF(Downloads_maandcijfers!CF511="", "", Downloads_maandcijfers!CF511) -> 3.49
A509: 45748 | B509: =IF(Downloads_maandcijfers!B512="", "", Downloads_maandcijfers!B512) -> 63.37 | C509: =IF(Downloads_maandcijfers!C512="", "", Downloads_maandcijfers!C512) -> 0.8795 | D509: =IF(Downloads_maandcijfers!D512="", "", Downloads_maandcijfers!D512) -> 460.16996 | E509: =IF(Downloads_maandcijfers!E512="", "", Downloads_maandcijfers!E512) -> 776.64014 | F509: =IF(Downloads_maandcijfers!F512="", "", Downloads_maandcijfers!F512) -> 24.7 | G509: =IF(Downloads_maandcijfers!G512="", "", Downloads_maandcijfers!G512) -> 2.51 | H509: =IF(Downloads_maandcijfers!H512="", "", Downloads_maandcijfers!H512) -> 4.17 | I509: =IF(Downloads_maandcijfers!I512="", "", Downloads_maandcijfers!I512) -> 3.58 | ... CF509: =IF(Downloads_maandcijfers!CF512="", "", Downloads_maandcijfers!CF512) -> 3.12
A510: 45778 | B510: =IF(Downloads_maandcijfers!B513="", "", Downloads_maandcijfers!B513) -> 64.32 | C510: =IF(Downloads_maandcijfers!C513="", "", Downloads_maandcijfers!C513) -> 0.8808 | D510: =IF(Downloads_maandcijfers!D513="", "", Downloads_maandcijfers!D513) -> 364.99812 | E510: =IF(Downloads_maandcijfers!E513="", "", Downloads_maandcijfers!E513) -> 626.32891 | F510: =IF(Downloads_maandcijfers!F513="", "", Downloads_maandcijfers!F513) -> 18.57 | G510: =IF(Downloads_maandcijfers!G513="", "", Downloads_maandcijfers!G513) | H510: =IF(Downloads_maandcijfers!H513="", "", Downloads_maandcijfers!H513) -> 4.41 | I510: =IF(Downloads_maandcijfers!I513="", "", Downloads_maandcijfers!I513) -> 3.5 | ... CF510: =IF(Downloads_maandcijfers!CF513="", "", Downloads_maandcijfers!CF513)
A511: 45809

Sheet Downloads_kwartaalcijfers
B4: Germany, World Bank, Global Economic Monitor, Gross Domestic Product, Constant Prices, SA, USD | C4: France, World Bank, Global Economic Monitor, Gross Domestic Product, Constant Prices, SA, USD | D4: Euro Area, Gross Domestic Product, Total, Chain-Linked Volumes, Reference Year 2015, Calendar Adjusted, Constant Prices, SA, Market Prices, EUR | E4: Euro Area, FX Spot Rates, Macrobond, EUR per USD | F4: United Kingdom, World Bank, Global Economic Monitor, Gross Domestic Product, Constant Prices, SA, USD | G4: Italy, World Bank, Global Economic Monitor, Gross Domestic Product, Constant Prices, SA, USD | H4: United States, World Bank, Global Economic Monitor, Gross Domestic Product, Constant Prices, SA, USD | I4: China, World Bank, Global Economic Monitor, Gross Domestic Product, Constant Prices, SA, USD | J4: India, World Bank, Global Economic Monitor, Gross Domestic Product, Constant Prices, SA, USD | K4: World, World Bank, Global Economic Monitor, Gross Domestic Product, Constant Prices, SA, USD | L4: Japan, World Bank, Global Economic Monitor, Gross Domestic Product, Constant Prices, SA, USD | M4: Germany, Expenditure Approach, Final Consumption Expenditure, Households & NPISH, Total, Calendar Adjusted (X13 JDemetra+), Constant Prices, SA (X13 JDemetra+), Chained, EUR | N4: Germany, Expenditure Approach, External Balance, Export, Total, Calendar Adjusted (X13 JDemetra+), Constant Prices, SA (X13 JDemetra+), Chained, EUR | O4: Germany, Expenditure Approach, External Balance, Import, Total, Calendar Adjusted (X13 JDemetra+), Constant Prices, SA (X13 JDemetra+), Chained, EUR | P4: Germany, Expenditure Approach, Gross Fixed Capital Formation, Total, Calendar Adjusted (X13 JDemetra+), Constant Prices, SA (X13 JDemetra+), Chained, EUR | Q4: Germany, Expenditure Approach, Final Consumption Expenditure, Government, Total, All, Calendar Adjusted (X13 JDemetra+), Constant Prices, SA (X13 JDemetra+), Chained, EUR | R4: United States, Expenditure Approach, Personal Consumption Expenditures, Real, Total, Chained, Constant Prices, SA, AR, USD | S4: United States, Expenditure Approach, Export, Total, Constant Prices, SA, Chained, AR, USD | T4: United States, Expenditure Approach, Import, Total, Constant Prices, SA, Chained, AR, USD | U4: United States, Expenditure Approach, Gross Private Domestic Investment, Fixed Investment, Total, Constant Prices, SA, Chained, AR, USD | V4: United States, Expenditure Approach, Government Consumption Expenditures & Gross Investment, Total, Constant Prices, SA, Chained, AR, USD | W4: China, Expenditure Approach, National, Final Consumption Expenditure, Contribution to GDP (Single Quarter) (Revised), Constant Prices, Change Y/Y | X4: China, Expenditure Approach, National, Net Export, Contribution to GDP (Single Quarter) (Revised), Constant Prices, Change Y/Y | Y4: China, Expenditure Approach, National, Gross Capital Formation, Contribution to GDP (Single Quarter) (Revised), Constant Prices, Change Y/Y | Z4: Euro Area, Expenditure Approach, Household & NPISH Final Consumption Expenditure, Chain-Linked Volumes, Reference Year 2015, Calendar Adjusted, Constant Prices, SA, EUR | AA4: Euro Area, Expenditure Approach, Exports of Goods & Services, Chain-Linked Volumes, Reference Year 2015, Calendar Adjusted, Constant Prices, SA, EUR | AB4: Euro Area, Expenditure Approach, Imports of Goods & Services, Chain-Linked Volumes, Reference Year 2015, Calendar Adjusted, Constant Prices, SA, EUR | AC4: Euro Area, Expenditure Approach, Gross Fixed Capital Formation, Chain-Linked Volumes, Reference Year 2015, Calendar Adjusted, Constant Prices, SA, EUR | AD4: Euro Area, Expenditure Approach, Final Consumption Expenditure of General Government, Chain-Linked Volumes, Reference Year 2015, Calendar Adjusted, SA, EUR | AE4: Netherlands, ECB Composite Cost of Borrowing, For Non-Financial Corporations
A5: 17168 | S5: 93767000000 | T5: 53861000000 | V5: 560515000000
A6: 17258 | S6: 92584000000 | T6: 54898000000 | V6: 560091000000
A7: 17349 | S7: 87885000000 | T7: 48687000000 | V7: 560034000000
A8: 17441 | S8: 77928000000 | T8: 51312000000 | V8: 555556000000
A9: 17533 | S9: 74373000000 | T9: 57862000000 | V9: 563895000000
A10: 17624 | S10: 67420000000 | T10: 60156000000 | V10: 583846000000
A11: 17715 | S11: 69005000000 | T11: 63297000000 | V11: 596087000000
A12: 17807 | S12: 66573000000 | T12: 62270000000 | V12: 618100000000
A13: 17899 | S13: 74540000000 | T13: 60402000000 | V13: 634547000000
A14: 17989 | S14: 73902000000 | T14: 59521000000 | V14: 662174000000
A15: 18080 | S15: 67729000000 | T15: 57095000000 | V15: 665721000000
A16: 18172 | S16: 58631000000 | T16: 57955000000 | V16: 654121000000
... A101: 25934 | S101: 197046000000 | T101: 250817000000 | V101: 1656742000000
A102: 26024 | E102: 0.96799692 | S102: 195588000000 | T102: 269738000000 | V102: 1652914000000
A103: 26115 | E103: 0.95211212 | S103: 205365000000 | T103: 275701000000 | V103: 1652012000000
A104: 26207 | E104: 0.92751061 | S104: 186407000000 | T104: 257013000000 | V104: 1640336000000
A105: 26299 | E105: 0.88742769 | S105: 207596000000 | T105: 294575000000 | V105: 1649269000000
A106: 26390 | E106: 0.88282308 | S106: 201538000000 | T106: 284109000000 | V106: 1655872000000
A107: 26481 | E107: 0.89307231 | S107: 213689000000 | T107: 290022000000 | V107: 1624317000000
A108: 26573 | E108: 0.90392308 | S108: 222725000000 | T108: 303087000000 | V108: 1637754000000
A109: 26665 | E109: 0.86678615 | S109: 239018000000 | T109: 317093000000 | V109: 1651865000000
A110: 26755 | E110: 0.81791385 | S110: 250533000000 | T110: 307953000000 | V110: 1640230000000
A111: 26846 | E111: 0.7689 | S111: 251377000000 | T111: 299446000000 | V111: 1620936000000
A112: 26938 | E112: 0.80413939 | S112: 263743000000 | T112: 301679000000 | V112: 1633097000000
A113: 27030 | E113: 0.86827031 | S113: 267163000000 | T113: 291445000000 | V113: 1662599000000
... A180: 33147 | E180: 0.72934394 | S180: 673470000000 | T180: 694844000000 | V180: 2559964000000
A181: 33239 | E181: 0.74493594 | M181: 340791350000 | N181: 111245170000 | O181: 100687800000 | P181: 134443700000 | Q181: 101744650000 | S181: 677584000000 | T181: 686926000000 | V181: 2575220000000
A182: 33329 | E182: 0.84217538 | M182: 340354160000 | N182: 104792750000 | O182: 101358660000 | P182: 1.3580618e+11 | Q182: 103340420000 | S182: 702289000000 | T182: 699135000000 | V182: 2585693000000
A183: 33420 | E183: 0.84939242 | M183: 334845540000 | N183: 109893880000 | O183: 102671220000 | P183: 135769360000 | Q183: 106224340000 | S183: 718914000000 | T183: 718810000000 | V183: 2578454000000
A184: 33512 | E184: 0.79601667 | M184: 340048120000 | N184: 110062790000 | O184: 102437880000 | P184: 139286030000 | Q184: 107243320000 | S184: 735102000000 | T184: 734689000000 | V184: 2559584000000
A185: 33604 | E185: 0.79221385 | M185: 347250900000 | N185: 111439230000 | O185: 105996520000 | P185: 143561890000 | Q185: 109276560000 | S185: 748392000000 | T185: 740026000000 | V185: 2582280000000
A186: 33695 | E186: 0.78688 | M186: 346245380000 | N186: 106034480000 | O186: 103050560000 | P186: 142033850000 | Q186: 110391630000 | S186: 748748000000 | T186: 752192000000 | V186: 2577285000000
A187: 33786 | E187: 0.72419545 | M187: 347819220000 | N187: 109040870000 | O187: 102554690000 | P187: 137928390000 | Q187: 112025780000 | S187: 764615000000 | T187: 764049000000 | V187: 2593701000000
A188: 33878 | E188: 0.79166061 | M188: 350267450000 | N188: 103973920000 | O188: 104013100000 | P188: 138407050000 | Q188: 112256490000 | S188: 768448000000 | T188: 782339000000 | V188: 2593400000000
A189: 33970 | E189: 0.83937031 | M189: 348868490000 | N189: 100401800000 | O189: 94073420000 | P189: 1.3529528e+11 | Q189: 112708380000 | S189: 770163000000 | T189: 799278000000 | V189: 2561222000000
A190: 34060 | E190: 0.82906923 | M190: 346726320000 | N190: 98172150000 | O190: 94861000000 | P190: 1.3424576e+11 | Q190: 112208470000 | S190: 779368000000 | T190: 815792000000 | V190: 2561456000000
A191: 34151 | E191: 0.87390606 | M191: 349043350000 | N191: 98476200000 | O191: 96202820000 | P191: 134871780000 | Q191: 111939290000 | S191: 777273000000 | T191: 826535000000 | V191: 2565100000000
A192: 34243 | E192: 0.87849242 | M192: 351797590000 | N192: 100266670000 | O192: 96377850000 | P192: 133085780000 | Q192: 111766260000 | S192: 802325000000 | T192: 859740000000 | V192: 2574165000000
... A196: 34608 | E196: 0.81042 | M196: 356311670000 | N196: 108534180000 | O196: 106653240000 | P196: 142397620000 | Q196: 117476480000 | S196: 888962000000 | T196: 964609000000 | V196: 2575394000000
A197: 34700 | D197: 1884644900000 | E197: 0.79107538 | M197: 356016490000 | N197: 112925540000 | O197: 107119520000 | P197: 138696850000 | Q197: 116068110000 | S197: 906086000000 | T197: 985774000000 | V197: 2584415000000 | Z197: 1.0511451e+12 | AA197: 450440400000 | AB197: 418797100000 | AC197: 390674000000 | AD197: 387595500000
A198: 34790 | D198: 1899629400000 | E198: 0.75876 | M198: 358814600000 | N198: 113770030000 | O198: 110036720000 | P198: 140298680000 | Q198: 118144540000 | S198: 918791000000 | T198: 995136000000 | V198: 2593101000000 | Z198: 1.0615316e+12 | AA198: 454077500000 | AB198: 425632000000 | AC198: 393762100000 | AD198: 391062500000
A199: 34881 | B199: 751595000000 | C199: 521551200000 | D199: 1904368600000 | E199: 0.7686 | F199: 453088200000 | G199: 488320500000 | H199: 2548768000000 | I199: 364952100000 | K199: 10248718000000 | L199: 1269670000000 | M199: 360126230000 | N199: 114580740000 | O199: 110853540000 | P199: 139801560000 | Q199: 119971020000 | S199: 958551000000 | T199: 998555000000 | V199: 2586304000000 | Z199: 1063476700000 | AA199: 454420400000 | AB199: 428165900000 | AC199: 393766900000 | AD199: 393905400000
A200: 34973 | B200: 751899500000 | C200: 521345800000 | D200: 1907814500000 | E200: 0.77526308 | F200: 454521000000 | G200: 492364900000 | H200: 2566042000000 | I200: 372929300000 | K200: 10299167000000 | L200: 1272929000000 | M200: 361394110000 | N200: 116371070000 | O200: 112078760000 | P200: 138733670000 | Q200: 121739820000 | S200: 972233000000 | T200: 1011318000000 | V200: 2559248000000 | Z200: 1067133300000 | AA200: 458790200000 | AB200: 431704600000 | AC200: 393419500000 | AD200: 396578500000
A201: 35065 | B201: 746593300000 | C201: 5.249693e+11 | D201: 1910801800000 | E201: 0.79554 | F201: 457564400000 | G201: 493391000000 | H201: 2585273000000 | I201: 382093100000 | K201: 10374859000000 | L201: 1283283000000 | M201: 363033570000 | N201: 118102050000 | O201: 112450540000 | P201: 131405730000 | Q201: 120437180000 | S201: 983934000000 | T201: 1044193000000 | V201: 2576137000000 | Z201: 1077310500000 | AA201: 467013500000 | AB201: 436304500000 | AC201: 385747600000 | AD201: 395877100000
A202: 35156 | B202: 757006600000 | C202: 525981500000 | D202: 1926427000000 | E202: 0.80884769 | F202: 458969600000 | G202: 494215100000 | H202: 2628367000000 | I202: 389346300000 | J202: 150066500000 | K202: 10498825000000 | L202: 1299567000000 | M202: 364694870000 | N202: 118439880000 | O202: 113208960000 | P202: 141716400000 | Q202: 121744610000 | S202: 999928000000 | T202: 1067562000000 | V202: 2608232000000 | Z202: 1080684800000 | AA202: 468790400000 | AB202: 436918100000 | AC202: 401664300000 | AD202: 397764300000
A203: 35247 | B203: 759630400000 | C203: 5.280123e+11 | D203: 1935282900000 | E203: 0.79297879 | F203: 463203300000 | G203: 495192200000 | H203: 2651962000000 | I203: 399847000000 | J203: 148287600000 | K203: 10586136000000 | L203: 1301203000000 | M203: 365263180000 | N203: 121446490000 | O203: 113996560000 | P203: 141348150000 | Q203: 123551930000 | S203: 1008015000000 | T203: 1102174000000 | V203: 2608223000000 | Z203: 1.0865506e+12 | AA203: 477088200000 | AB203: 441391200000 | AC203: 402788000000 | AD203: 401236000000
A204: 35339 | B204: 766494500000 | C204: 530043100000 | D204: 1945556600000 | E204: 0.79674242 | F204: 469667200000 | G204: 493487800000 | H204: 2679563000000 | I204: 410916900000 | J204: 154680700000 | K204: 10683121000000 | L204: 1315827000000 | M204: 366399840000 | N204: 126817830000 | O204: 118372060000 | P204: 141661160000 | Q204: 123475030000 | S204: 1070864000000 | T204: 1123911000000 | V204: 2626227000000 | Z204: 1088170700000 | AA204: 492227600000 | AB204: 454309300000 | AC204: 403120400000 | AD204: 401853800000
A205: 35431 | B205: 762863300000 | C205: 532306500000 | D205: 1950961800000 | E205: 0.85259844 | F205: 477173700000 | G205: 494911800000 | H205: 2696837000000 | I205: 419942900000 | J205: 155431200000 | K205: 10755595000000 | L205: 1318839000000 | M205: 367722420000 | N205: 129199330000 | O205: 121836200000 | P205: 1.370766e+11 | Q205: 123777800000 | S205: 1091223000000 | T205: 1171915000000 | V205: 2612572000000 | Z205: 1092473800000 | AA205: 504129300000 | AB205: 464951800000 | AC205: 399524900000 | AD205: 402463500000
A206: 35521 | B206: 771449300000 | C206: 5.378927e+11 | D206: 1974052300000 | E206: 0.87842154 | F206: 482562700000 | G206: 502744700000 | H206: 2741711000000 | I206: 429069000000 | J206: 154902100000 | K206: 10883017000000 | L206: 1309291000000 | M206: 368684200000 | N206: 1.3294865e+11 | O206: 123061270000 | P206: 139985690000 | Q206: 124566070000 | S206: 1134842000000 | T206: 1211249000000 | V206: 2646418000000 | Z206: 1099859800000 | AA206: 521021700000 | AB206: 478473300000 | AC206: 406813600000 | AD206: 405819500000
A207: 35612 | B207: 774178600000 | C207: 5.432412e+11 | D207: 1988970500000 | E207: 0.91755303 | F207: 486697900000 | G207: 505096900000 | H207: 2775990000000 | I207: 435591500000 | J207: 155184600000 | K207: 10994439000000 | L207: 1311782000000 | M207: 367722400000 | N207: 140075720000 | O207: 127115670000 | P207: 140261860000 | Q207: 124642970000 | S207: 1161100000000 | T207: 1255884000000 | V207: 2658663000000 | Z207: 1105483500000 | AA207: 540222400000 | AB207: 493727600000 | AC207: 408557300000 | AD207: 406910300000
A208: 35704 | B208: 779929900000 | C208: 548609600000 | D208: 2010052500000 | E208: 0.88997576 | F208: 494047000000 | G208: 512575900000 | H208: 2799674000000 | I208: 446029000000 | J208: 160233400000 | K208: 11083447000000 | L208: 1312344000000 | M208: 370432990000 | N208: 141933500000 | O208: 1.2877827e+11 | P208: 141826870000 | Q208: 122431960000 | S208: 1159431000000 | T208: 1282987000000 | V208: 2672005000000 | Z208: 1119120600000 | AA208: 548446100000 | AB208: 505114200000 | AC208: 416795200000 | AD208: 404765100000
A209: 35796 | B209: 787613900000 | C209: 553869000000 | D209: 2024080400000 | E209: 0.91952656 | F209: 497680100000 | G209: 509986200000 | H209: 2827721000000 | I209: 449429900000 | J209: 163026100000 | K209: 11104144000000 | L209: 1296084000000 | M209: 372236360000 | N209: 145142940000 | O209: 1.3365002e+11 | P209: 145490830000 | Q209: 126988560000 | S209: 1164787000000 | T209: 1331107000000 | V209: 2662448000000 | Z209: 1125285900000 | AA209: 560290400000 | AB209: 522695400000 | AC209: 424317500000 | AD209: 409900300000
A210: 35886 | B210: 783971000000 | C210: 557835300000 | D210: 2032068700000 | E210: 0.90763385 | F210: 500721100000 | G210: 513049800000 | H210: 2853898000000 | I210: 459399900000 | J210: 164618700000 | K210: 11153323000000 | L210: 1290677000000 | M210: 371143340000 | N210: 147406050000 | O210: 136800210000 | P210: 143852170000 | Q210: 127603790000 | S210: 1151950000000 | T210: 1361614000000 | V210: 2709053000000 | Z210: 1132368000000 | AA210: 568806400000 | AB210: 531360500000 | AC210: 425445100000 | AD210: 412286100000
A211: 35977 | B211: 787613900000 | C211: 560719900000 | D211: 2042929100000 | E211: 0.89353788 | F211: 502384500000 | G211: 513442800000 | H211: 2889868000000 | I211: 470604300000 | J211: 166492900000 | K211: 11224832000000 | L211: 1292916000000 | M211: 373941470000 | N211: 145886050000 | O211: 137616930000 | P211: 145306710000 | Q211: 127642240000 | S211: 1146707000000 | T211: 1379986000000 | V211: 2729468000000 | Z211: 1144183100000 | AA211: 569125200000 | AB211: 538358100000 | AC211: 432624200000 | AD211: 413381700000
A212: 36069 | B212: 787403100000 | C212: 564563700000 | D212: 2048530600000 | E212: 0.84601667 | F212: 505723400000 | G212: 511835100000 | H212: 2936346000000 | I212: 487606300000 | J212: 169295900000 | K212: 11328760000000 | L212: 1303321000000 | M212: 377395390000 | N212: 143386490000 | O212: 137033560000 | P212: 144036290000 | Q212: 127219270000 | S212: 1189349000000 | T212: 1424651000000 | V212: 2745584000000 | Z212: 1155584200000 | AA212: 565442400000 | AB212: 545401900000 | AC212: 435776900000 | AD212: 414413400000
A213: 36161 | B213: 796750400000 | C213: 568448300000 | D213: 2070007500000 | E213: 0.89206719 | F213: 509087500000 | G213: 514302400000 | H213: 2963947000000 | I213: 488273500000 | J213: 172715600000 | K213: 11403472000000 | L213: 1285244000000 | M213: 382761820000 | N213: 144265100000 | O213: 142612380000 | P213: 148680630000 | Q213: 131300030000 | S213: 1185370000000 | T213: 1464906000000 | U213: 2076866000000 | V213: 2765048000000 | Z213: 1163119000000 | AA213: 571223900000 | AB213: 553600100000 | AC213: 446250600000 | AD213: 420768700000
A214: 36251 | B214: 795743100000 | C214: 572134800000 | D214: 2079654700000 | E214: 0.94648 | F214: 511543600000 | G214: 516303200000 | H214: 2988699000000 | I214: 495662300000 | J214: 177193500000 | K214: 11492997000000 | L214: 1290317000000 | M214: 384554310000 | N214: 151730000000 | O214: 147104560000 | P214: 149674910000 | Q214: 1.3047328e+11 | S214: 1200094000000 | T214: 1506978000000 | U214: 2126293000000 | V214: 2775035000000 | Z214: 1173292200000 | AA214: 587025100000 | AB214: 566878100000 | AC214: 450717300000 | AD214: 419672700000
A215: 36342 | B215: 806449200000 | C215: 580562300000 | D215: 2107727000000 | E215: 0.95344848 | F215: 519878800000 | G215: 521673700000 | H215: 3028321000000 | I215: 507242700000 | J215: 178517900000 | K215: 11633919000000 | L215: 1297141000000 | M215: 384423160000 | N215: 155074000000 | O215: 150721640000 | P215: 152160600000 | Q215: 131338480000 | S215: 1236298000000 | T215: 1561455000000 | U215: 2175841000000 | V215: 2808440000000 | Z215: 1186185800000 | AA215: 603151700000 | AB215: 582305500000 | AC215: 459373300000 | AD215: 421196400000
A216: 36434 | B216: 810291200000 | C216: 588784400000 | D216: 2.1296657e+12 | E216: 0.96509848 | F216: 5.273648e+11 | G216: 529397600000 | H216: 3078003000000 | I216: 522274400000 | J216: 180987300000 | K216: 11791375000000 | L216: 1297555000000 | M216: 388969940000 | N216: 158249120000 | O216: 150896670000 | P216: 151092690000 | Q216: 1.304156e+11 | S216: 1262725000000 | T216: 1601395000000 | U216: 2187170000000 | V216: 2852137000000 | Z216: 1195635400000 | AA216: 622001900000 | AB216: 598074000000 | AC216: 462475100000 | AD216: 425363500000
A217: 36526 | B217: 823094000000 | C217: 594500500000 | D217: 2157530500000 | E217: 1.0143231 | F217: 5.339068e+11 | G217: 535899500000 | H217: 3089133000000 | I217: 528965500000 | J217: 186232700000 | K217: 11925758000000 | L217: 1319964000000 | M217: 391494810000 | N217: 165798810000 | O217: 156030590000 | P217: 154139840000 | Q217: 1.3404454e+11 | S217: 1280897000000 | T217: 1661851000000 | U217: 2249784000000 | V217: 2831903000000 | Z217: 1207412200000 | AA217: 646733900000 | AB217: 616408700000 | AC217: 472214800000 | AD217: 429998400000
A218: 36617 | B218: 829454400000 | C218: 601112600000 | D218: 2176952900000 | E218: 1.0719754 | F218: 5.378522e+11 | G218: 5.394308e+11 | H218: 3145404000000 | I218: 540925900000 | J218: 186384400000 | K218: 12073139000000 | L218: 1325875000000 | M218: 395123410000 | N218: 171778100000 | O218: 160581120000 | P218: 154176660000 | Q218: 133371620000 | S218: 1319937000000 | T218: 1714792000000 | U218: 2299529000000 | V218: 2859814000000 | Z218: 1216052300000 | AA218: 668188400000 | AB218: 637299600000 | AC218: 476408700000 | AD218: 430465400000
A219: 36708 | B219: 829958100000 | C219: 605748300000 | D219: 2.1910362e+12 | E219: 1.1057031 | F219: 5.412908e+11 | G219: 544309100000 | H219: 3148610000000 | I219: 552552800000 | J219: 188810800000 | K219: 12152623000000 | L219: 1326249000000 | M219: 395123400000 | N219: 174717080000 | O219: 165802570000 | P219: 155667980000 | Q219: 132910210000 | S219: 1351623000000 | T219: 1776491000000 | U219: 2309549000000 | V219: 2847750000000 | Z219: 1220859100000 | AA219: 682647000000 | AB219: 654487700000 | AC219: 482389200000 | AD219: 433243000000
A220: 36800 | B220: 826420600000 | C220: 609434900000 | D220: 2200757600000 | E220: 1.1511446 | F220: 544604400000 | G220: 549582900000 | H220: 3167485000000 | I220: 564576300000 | J220: 188205700000 | K220: 12232211000000 | L220: 1339053000000 | M220: 394686220000 | N220: 183838050000 | O220: 174407730000 | P220: 153826850000 | Q220: 133929190000 | S220: 1338104000000 | T220: 1779089000000 | U220: 2316544000000 | V220: 2865194000000 | Z220: 1223974700000 | AA220: 706491200000 | AB220: 677339000000 | AC220: 480892700000 | AD220: 436720800000
A221: 36892 | B221: 844225100000 | C221: 612614100000 | D221: 2271395800000 | E221: 1.0841231 | F221: 549688400000 | G221: 553907700000 | H221: 3157068000000 | I221: 576066400000 | J221: 189334600000 | K221: 12286709000000 | L221: 1349034000000 | M221: 399342360000 | N221: 183482920000 | O221: 167749580000 | P221: 154857780000 | Q221: 134155080000 | S221: 1321256000000 | T221: 1756138000000 | U221: 2303027000000 | V221: 2909984000000 | Z221: 1265388200000 | AA221: 718114700000 | AB221: 682422700000 | AC221: 496053200000 | AD221: 448908000000
A222: 36982 | B222: 841800400000 | C222: 612766300000 | D222: 2272241200000 | E222: 1.1456815 | F222: 552018400000 | G222: 553536600000 | H222: 3176745000000 | I222: 586892800000 | J222: 193426900000 | K222: 12320672000000 | L222: 1338869000000 | M222: 396413090000 | N222: 184023370000 | O222: 168187120000 | P222: 151764660000 | Q222: 133674450000 | S222: 1282544000000 | T222: 1699930000000 | U222: 2275999000000 | V222: 2960454000000 | Z222: 1266571400000 | AA222: 713425600000 | AB222: 681716500000 | AC222: 495006100000 | AD222: 448850700000
A223: 37073 | B223: 841706700000 | C223: 616268500000 | D223: 2276851000000 | E223: 1.1239908 | F223: 554896100000 | G223: 551404900000 | H223: 3164013000000 | I223: 596921600000 | J223: 195661800000 | K223: 12331249000000 | L223: 1324433000000 | M223: 398074450000 | N223: 183651800000 | O223: 164891040000 | P223: 149408010000 | Q223: 133174600000 | S223: 1216869000000 | T223: 1661369000000 | U223: 2259665000000 | V223: 2957571000000 | Z223: 1271432300000 | AA223: 710186000000 | AB223: 674430600000 | AC223: 490895100000 | AD223: 449964600000
A224: 37165 | B224: 839176600000 | C224: 613569400000 | D224: 2275485400000 | E224: 1.1172379 | F224: 556563100000 | G224: 550607700000 | H224: 3172739000000 | I224: 610161100000 | J224: 200371100000 | K224: 12360259000000 | L224: 1319726000000 | M224: 399473500000 | N224: 185914950000 | O224: 162790890000 | P224: 147566870000 | Q224: 135154820000 | S224: 1174568000000 | T224: 1644162000000 | U224: 2208105000000 | V224: 3006637000000 | Z224: 1276276000000 | AA224: 708971100000 | AB224: 666665600000 | AC224: 489383600000 | AD224: 455735900000
... A228: 37530 | B228: 842081600000 | C228: 623103300000 | D228: 2304184600000 | E228: 0.99944242 | F228: 569167900000 | G228: 556986000000 | H228: 3235955000000 | I228: 670128800000 | J228: 205151900000 | K228: 12700994000000 | L228: 1340651000000 | M228: 398249410000 | N228: 197205870000 | O228: 164664940000 | P228: 140100690000 | Q228: 137625480000 | S228: 1221597000000 | T228: 1801535000000 | U228: 2174296000000 | V228: 3121374000000 | Z228: 1291045100000 | AA228: 737064600000 | AB228: 689027800000 | AC228: 487587200000 | AD228: 464519300000
A229: 37622 | B229: 830766300000 | C229: 625030100000 | D229: 2297426600000 | E229: 0.93207656 | F229: 573321100000 | G229: 554657000000 | H229: 3252961000000 | I229: 690162800000 | J229: 208141900000 | K229: 12756157000000 | L229: 1341492000000 | M229: 397746620000 | N229: 191260650000 | O229: 168114280000 | P229: 139787770000 | Q229: 1.3573644e+11 | S229: 1217842000000 | T229: 1793694000000 | U229: 2194030000000 | V229: 3124051000000 | Z229: 1291419300000 | AA229: 725685300000 | AB229: 691291600000 | AC229: 487163100000 | AD229: 464316900000 | AE229: 4.2133333
A230: 37712 | B230: 831773700000 | C230: 622222200000 | D230: 2297706900000 | E230: 0.88136462 | F230: 578359400000 | G230: 553679900000 | H230: 3281809000000 | I230: 696012300000 | J230: 213792300000 | K230: 12825472000000 | L230: 1350563000000 | M230: 397877760000 | N230: 190449940000 | O230: 166276460000 | P230: 139161730000 | Q230: 135928710000 | S230: 1219986000000 | T230: 1819841000000 | U230: 2246775000000 | V230: 3152710000000 | Z230: 1293900200000 | AA230: 721060100000 | AB230: 689021000000 | AC230: 487347100000 | AD230: 466684400000 | AE230: 3.9666667
A231: 37803 | B231: 839352300000 | C231: 628975300000 | D231: 2312457600000 | E231: 0.88811515 | F231: 583669200000 | G231: 552324400000 | H231: 3336388000000 | I231: 721744200000 | J231: 219424400000 | K231: 12992002000000 | L231: 1354767000000 | M231: 400588290000 | N231: 196091160000 | O231: 167589180000 | P231: 139327440000 | Q231: 1.3725531e+11 | S231: 1253316000000 | T231: 1848341000000 | U231: 2319726000000 | V231: 3159860000000 | Z231: 1301630600000 | AA231: 731721900000 | AB231: 695029100000 | AC231: 491326200000 | AD231: 470724100000 | AE231: 3.68
A232: 37895 | B232: 840371400000 | C232: 631157100000 | D232: 2326376500000 | E232: 0.8396697 | F232: 588576600000 | G232: 557514900000 | H232: 3375119000000 | I232: 741559600000 | J232: 229400600000 | K232: 13149711000000 | L232: 1369492000000 | M232: 400632000000 | N232: 200820310000 | O232: 172664990000 | P232: 139382690000 | Q232: 138139720000 | S232: 1309666000000 | T232: 1907048000000 | U232: 2361865000000 | V232: 3178923000000 | Z232: 1305732000000 | AA232: 749590500000 | AB232: 711112100000 | AC232: 496173400000 | AD232: 472365200000 | AE232: 3.76
A233: 37987 | B233: 839328900000 | C233: 638000500000 | D233: 2339082800000 | E233: 0.80006154 | F233: 590924600000 | G233: 559842600000 | H233: 3394262000000 | I233: 759616100000 | J233: 226138200000 | K233: 13266730000000 | L233: 1379873000000 | M233: 400850640000 | N233: 208935690000 | O233: 174174370000 | P233: 136837230000 | Q233: 1.3612578e+11 | S233: 1339286000000 | T233: 1960461000000 | U233: 2355416000000 | V233: 3193302000000 | Z233: 1312365400000 | AA233: 764350200000 | AB233: 717164500000 | AC233: 495795200000 | AD233: 471653800000 | AE233: 3.65
A234: 38078 | B234: 844072800000 | C234: 640838200000 | D234: 2353395400000 | E234: 0.83002769 | F234: 594299500000 | G234: 561277700000 | H234: 3420528000000 | I234: 774515500000 | J234: 232129200000 | K234: 13385406000000 | L234: 1379579000000 | M234: 400282280000 | N234: 218056560000 | O234: 177733100000 | P234: 138089250000 | Q234: 135875820000 | S234: 1367358000000 | T234: 2037690000000 | U234: 2419763000000 | V234: 3201827000000 | Z234: 1314606400000 | AA234: 788083100000 | AB234: 734333000000 | AC234: 500369900000 | AD234: 474168500000 | AE234: 3.6166667
A235: 38169 | B235: 841355300000 | C235: 643084300000 | D235: 2358227500000 | E235: 0.81812424 | F235: 596483000000 | G235: 561675600000 | H235: 3453026000000 | I235: 794016500000 | J235: 238629900000 | K235: 13499486000000 | L235: 1388185000000 | M235: 399101910000 | N235: 214137960000 | O235: 181204340000 | P235: 137592130000 | Q235: 1.368564e+11 | S235: 1371930000000 | T235: 2065934000000 | U235: 2471232000000 | V235: 3207809000000 | Z235: 1316077300000 | AA235: 788530100000 | AB235: 745245600000 | AC235: 500668800000 | AD235: 476775900000 | AE235: 3.64
A236: 38261 | B236: 840945300000 | C236: 648741000000 | D236: 2367758000000 | E236: 0.77111667 | F236: 599339100000 | G236: 563119300000 | H236: 3488196000000 | I236: 810358900000 | J236: 241241100000 | K236: 13607470000000 | L236: 1385578000000 | M236: 401244080000 | N236: 215252740000 | O236: 181816910000 | P236: 1.3681882e+11 | Q236: 1.351452e+11 | S236: 1404510000000 | T236: 2114053000000 | U236: 2516261000000 | V236: 3205846000000 | Z236: 1327691800000 | AA236: 798337000000 | AB236: 756399900000 | AC236: 502267000000 | AD236: 476270200000 | AE236: 3.5933333
A237: 38353 | B237: 842515000000 | C237: 650768000000 | D237: 2373999800000 | E237: 0.76302812 | F237: 603761300000 | G237: 562098100000 | H237: 3526927000000 | I237: 841657100000 | J237: 246859500000 | K237: 13741601000000 | L237: 1392616000000 | M237: 403626810000 | N237: 220581440000 | O237: 178893040000 | P237: 1.349637e+11 | Q237: 135505730000 | S237: 1430827000000 | T237: 2132265000000 | U237: 2560385000000 | V237: 3221699000000 | Z237: 1332292300000 | AA237: 803189400000 | AB237: 755414800000 | AC237: 503330500000 | AD237: 479174900000 | AE237: 3.6
A238: 38443 | B238: 847153500000 | C238: 652177600000 | D238: 2387873200000 | E238: 0.79500308 | F238: 608810400000 | G238: 566945700000 | H238: 3544289000000 | I238: 856889700000 | J238: 253936100000 | K238: 13864434000000 | L238: 1403380000000 | M238: 404982140000 | N238: 224466120000 | O238: 187877070000 | P238: 137504630000 | Q238: 137447570000 | S238: 1462813000000 | T238: 2160811000000 | U238: 2603795000000 | V238: 3219797000000 | Z238: 1341855500000 | AA238: 816620700000 | AB238: 778107200000 | AC238: 511862700000 | AD238: 481769900000 | AE238: 3.57
A239: 38534 | B239: 854134700000 | C239: 657106600000 | D239: 2405593300000 | E239: 0.81995758 | F239: 613886000000 | G239: 569957900000 | H239: 3572069000000 | I239: 883388400000 | J239: 258054800000 | K239: 14006724000000 | L239: 1417665000000 | M239: 404938390000 | N239: 233350180000 | O239: 192806630000 | P239: 139603660000 | Q239: 137063040000 | S239: 1462546000000 | T239: 2172945000000 | U239: 2649330000000 | V239: 3230377000000 | Z239: 1348057900000 | AA239: 834482300000 | AB239: 792270100000 | AC239: 518331500000 | AD239: 482853100000 | AE239: 3.48
A240: 38626 | B240: 857367600000 | C240: 661627300000 | D240: 2421611500000 | E240: 0.84147077 | F240: 619654500000 | G240: 572616200000 | H240: 3591924000000 | I240: 913232900000 | J240: 2.639631e+11 | K240: 14151379000000 | L240: 1420198000000 | M240: 404763510000 | N240: 236897040000 | O240: 200098860000 | P240: 143654400000 | Q240: 137082270000 | S240: 1507833000000 | T240: 2242978000000 | U240: 2661221000000 | V240: 3232898000000 | Z240: 1353048500000 | AA240: 849871900000 | AB240: 809376700000 | AC240: 522987800000 | AD240: 483312200000 | AE240: 3.6833333
... A244: 38991 | B244: 901480600000 | C244: 679625700000 | D244: 2511785300000 | E244: 0.77562615 | F244: 630024200000 | G244: 586218800000 | H244: 3686570000000 | I244: 1028915000000 | J244: 289882600000 | K244: 14745887000000 | L244: 1440926000000 | M244: 414490950000 | N244: 2.7386101e+11 | O244: 218651130000 | P244: 156004040000 | Q244: 139230770000 | S244: 1656573000000 | T244: 2332033000000 | U244: 2660267000000 | V244: 3294635000000 | Z244: 1383507600000 | AA244: 926655000000 | AB244: 873734000000 | AC244: 557416100000 | AD244: 495638300000 | AE244: 4.7033333
A245: 39083 | B245: 902663600000 | C245: 686729100000 | D245: 2537986100000 | E245: 0.76307385 | F245: 635824000000 | G245: 584995500000 | H245: 3697611000000 | I245: 1073869000000 | J245: 297992400000 | K245: 14910776000000 | L245: 1450547000000 | M245: 408545300000 | N245: 271942970000 | O245: 220729780000 | P245: 156132910000 | Q245: 140384380000 | R245: 1.1183323e+13 | S245: 1689392000000 | T245: 2365980000000 | U245: 2786977000000 | V245: 3299115000000 | Z245: 1390266300000 | AA245: 941129800000 | AB245: 891885400000 | AC245: 565858600000 | AD245: 499758000000 | AE245: 4.7766667
A246: 39173 | B246: 908625800000 | C246: 691236100000 | D246: 2554523100000 | E246: 0.74167538 | F246: 640374700000 | G246: 586687700000 | H246: 3720226000000 | I246: 1109285000000 | J246: 302616900000 | K246: 15056406000000 | L246: 1451041000000 | M246: 411386950000 | N246: 278766860000 | O246: 221867400000 | P246: 154715200000 | Q246: 140961160000 | R246: 1.1212669e+13 | S246: 1714981000000 | T246: 2378558000000 | U246: 2800103000000 | V246: 3329139000000 | Z246: 1400665400000 | AA246: 957212900000 | AB246: 900474700000 | AC246: 568555900000 | AD246: 502337400000 | AE246: 5.04
A247: 39264 | B247: 913170600000 | C247: 693442600000 | D247: 2564276900000 | E247: 0.72768154 | F247: 645016700000 | G247: 586883700000 | H247: 3741684000000 | I247: 1136226000000 | J247: 308943600000 | K247: 15167557000000 | L247: 1443168000000 | M247: 410993500000 | N247: 283969280000 | O247: 226738800000 | P247: 155193910000 | Q247: 140865020000 | R247: 1.1287468e+13 | S247: 1768587000000 | T247: 2391879000000 | U247: 2784117000000 | V247: 3344222000000 | Z247: 1404932700000 | AA247: 970865800000 | AB247: 917900400000 | AC247: 572091100000 | AD247: 504111900000 | AE247: 5.2866667
A248: 39356 | B248: 919941000000 | C248: 694148000000 | D248: 2576414500000 | E248: 0.69074545 | F248: 648867200000 | G248: 585646900000 | H248: 3765190000000 | I248: 1172378000000 | J248: 321303600000 | K248: 15330500000000 | L248: 1449262000000 | M248: 410512590000 | N248: 286536680000 | O248: 226855470000 | P248: 158268690000 | Q248: 141999310000 | R248: 11331949000000 | S248: 1809181000000 | T248: 2369287000000 | U248: 2757412000000 | V248: 3370950000000 | Z248: 1409089700000 | AA248: 975816900000 | AB248: 928162000000 | AC248: 583132700000 | AD248: 507048800000 | AE248: 5.3833333
A249: 39448 | B249: 925551800000 | C249: 700143800000 | D249: 2599847000000 | E249: 0.66771692 | F249: 651925000000 | G249: 591652900000 | H249: 3749163000000 | I249: 1201024000000 | J249: 324499400000 | K249: 15426608000000 | L249: 1455063000000 | M249: 411605530000 | N249: 289103180000 | O249: 228350480000 | P249: 160344550000 | Q249: 144445870000 | R249: 1.1316411e+13 | S249: 1838024000000 | T249: 2378171000000 | U249: 2714675000000 | V249: 3378654000000 | Z249: 1415817100000 | AA249: 994064600000 | AB249: 930011200000 | AC249: 582806400000 | AD249: 511725800000 | AE249: 5.28
A250: 39539 | B250: 922213400000 | C250: 694943800000 | D250: 2586637900000 | E250: 0.64012769 | F250: 648458900000 | G250: 586122000000 | H250: 3771422000000 | I250: 1228678000000 | J250: 326663300000 | K250: 15476384000000 | L250: 1446250000000 | M250: 409987940000 | N250: 287887190000 | O250: 225958460000 | P250: 157380320000 | Q250: 147272110000 | R250: 1.1347595e+13 | S250: 1892001000000 | T250: 2355670000000 | U250: 2692443000000 | V250: 3407753000000 | Z250: 1410300200000 | AA250: 985753900000 | AB250: 924822000000 | AC250: 573076600000 | AD250: 517009400000 | AE250: 5.4233333
A251: 39630 | B251: 917164900000 | C251: 693273100000 | D251: 2572605200000 | E251: 0.66605152 | F251: 638491500000 | G251: 577402600000 | H251: 3751656000000 | I251: 1243227000000 | J251: 328622300000 | K251: 15433252000000 | L251: 1428230000000 | M251: 410250260000 | N251: 285083640000 | O251: 230159100000 | P251: 157361910000 | Q251: 146349260000 | R251: 11260136000000 | S251: 1883563000000 | T251: 2325941000000 | U251: 2624372000000 | V251: 3435100000000 | Z251: 1405290200000 | AA251: 973831300000 | AB251: 920251100000 | AC251: 564514200000 | AD251: 517189800000 | AE251: 5.5633333
A252: 39722 | B252: 903026800000 | C252: 684453300000 | D252: 2529016200000 | E252: 0.75877121 | F252: 624813000000 | G252: 564151500000 | H252: 3669564000000 | I252: 1256181000000 | J252: 327712900000 | K252: 15156914000000 | L252: 1392600000000 | M252: 407976930000 | N252: 269039240000 | O252: 222487140000 | P252: 155152550000 | Q252: 147560510000 | R252: 11158801000000 | S252: 1772800000000 | T252: 2241832000000 | U252: 2451093000000 | V252: 3458839000000 | Z252: 1397174500000 | AA252: 918644900000 | AB252: 877428800000 | AC252: 546693000000 | AD252: 520792000000 | AE252: 5.1066667
A253: 39814 | B253: 860565400000 | C253: 671419700000 | D253: 2469363300000 | E253: 0.76715625 | F253: 612101200000 | G253: 550351800000 | H253: 3627895000000 | I253: 1280249000000 | J253: 325281000000 | K253: 14857790000000 | L253: 1325848000000 | M253: 411310460000 | N253: 237842860000 | O253: 208777530000 | P253: 142540330000 | Q253: 149526340000 | R253: 1.1130464e+13 | S253: 1631257000000 | T253: 2028740000000 | U253: 2256202000000 | V253: 3498103000000 | Z253: 1403232400000 | AA253: 849729400000 | AB253: 825949500000 | AC253: 521011400000 | AD253: 5.287807e+11 | AE253: 3.5033333
